Workbook

Sheet NOTES
J1: EXPORT THE ON HAND DATA FROM THE INV -> REPORTING TAB WITH THE STOCK FILTER ENABLED | X1: DISCONTINUED | Y1: SKU | Z1: LINK
A2: Matte Finish Copper Mug. A festive gift. | B2: YS0004300000 | C2: COPPER | D2: FOR GIFTING 25 EACH | J2: MUST HAVE THE COLS IN THE RIGHT ENABLED FOR THIS EXPORT | X2: LB NOTEBOOK | Y2: HO0076400000 | Z2: https://ishalife.sadhguru.org/usa/linga-bhairavi-handcrafted-notebook
X3: Spatik Mala (Quartz Stones) | Y3: RS0001000100 | AA3: SMALLEST SIZE DKED
J4: THIS IS THE STOCK | X4: Isha Wooden Ball Pen | Y4: HO0079300000
J5: FOR THE SALES GO TO SALES REPORTING, LAST 365 DAYS SELECT ONLY THE QTY ORDEREDED AND MAKE THE LEFT SIDE THE EXPANDED PROD VARIANTS AND PASTE THAT AS IS | X5: Adiyogi Car Hanging | Y5: HO0088100000
A8: ORDER REMARKS | H8: Q2 ORDER REMARKS
A9: S No | B9: GLOBAL SKU | C9: NAME | D9: ORDER | E9: Remarks
A10: 1 | B10: HI0000600001 | C10: nilavembu tablets | D10: 1670 | E10: Need to confirm Import clearance
A11: 2 | B11: BC0002206001 | C11: turmeric face pack | D11: 175 | E11: Need to confirm Import clearance
A12: 3 | B12: HO0030800002 | C12: Instant Herbal Dhoop 20pcs | D12: 115 | E12: Previous orders were cancelled due to cow dung Ingredient
A13: 6 | B13: YS0008416900 | C13: Shivanga Kit with Mala | D13: 255 | E13: Currently we have dispatched Shivanga Kit with Rudraksh Mala (without Hundi & Vibhuti)-YS0019900000, Pls check and confirm the SKU
A20: DEVI SHAWL COTTON GOLD WRITING
A21: TC0004016600 | B21: ENGLISH
A22: TC0004000400 | B22: TAMIL
A29: DOES ISHA LIFE STILL SELL SANNIDH ITEMS, VIBHUTI, SHAWL, SUTRA, ETC
A30: add in clothing and t shirts
A31: NEW PRODS AT FLOOR / ONLINE CHECK
A32: PRICING CHECK
A34: brass plates for buddha lamps ?
A37: clear our the sun hats only the bucket hat
A50: FABRIC | B50: CODE | D50: PRINT | E50: P
A51: ORGANIC SATIN | B51: 1 | D51: NO PRINT | E51: N
A52: COTTEN LINEN | B52: 2
A53: COTTON GUAZE | B53: 3
A54: COTTON CREPE | B54: 4
A55: COTTON SLUB | B55: 5
A56: EYELET | B56: 6
A57: VOILE | B57: 7
A58: COTTON JERSEY | B58: 8

Sheet ORDER LIST
A1: US SKU | B1: NAME | C1: SKU | D1: CAT | E1: RETAIL PRICE | F1: SHIP | G1: SEA | H1: AIR | I1: SEA ROUND | J1: AIR ROUND | K1: SEA COST | L1: AIR COST | M1: AIR SHIP? | N1: SHIPPING COST BY AIR | O1: UNIT WEIGHT (G) | P1: PROFIT LOST BY AIR | Q1: MARGIN | R1: LEAD TIME (MONTHS) | S1: CASE
A2: {=XLOOKUP(C2,INV!D:D,INV!I:I)} -> BK107 | B2: {=XLOOKUP(C2,INV!A:A,INV!B:B)} -> Taste of Isha Cookbook | C2: ME0008101506 | D2: A & A | E2: {=XLOOKUP(C2,INV!A:A,INV!K:K)} -> 15 | F2: DOMESTIC | M2: {=XLOOKUP(C2,SEA!B:B,SEA!R:R)} -> #N/A
A3: {=XLOOKUP(C3,INV!D:D,INV!I:I)} -> HO0079300000 | B3: Isha Wooden Ball Pen | C3: HO0079300000 | D3: ACCESSORY | E3: {=XLOOKUP(C3,INV!A:A,INV!K:K)} -> 5 | G3: {=XLOOKUP(C3,SEA!B:B,SEA!Q:Q)} -> #N/A | H3: {=XLOOKUP(C3,SEA!B:B,SEA!S:S)} -> #N/A | I3: =CEILING(G3,S3) -> #N/A | J3: =CEILING(H3,S3) -> #N/A | K3: {=I3*XLOOKUP(C3,'PRICE LIST'!E:E,'PRICE LIST'!J:J)} -> #N/A | L3: {=J3*XLOOKUP(C3,'PRICE LIST'!E:E,'PRICE LIST'!J:J)} -> #N/A | M3: {=XLOOKUP(C3,SEA!B:B,SEA!R:R)} -> #N/A | P3: =Q3*J3 -> #N/A | Q3: {=E3-XLOOKUP(C3,'PRICE LIST'!E:E,'PRICE LIST'!J:J)} -> #N/A | S3: 1
A4: {=XLOOKUP(C4,INV!D:D,INV!I:I)} -> EX102 | B4: Adiyogi Car Hanging | C4: HO0088100000 | D4: ACCESSORY | E4: {=XLOOKUP(C4,INV!A:A,INV!K:K)} -> 5 | G4: {=XLOOKUP(C4,SEA!B:B,SEA!Q:Q)} -> #N/A | H4: {=XLOOKUP(C4,SEA!B:B,SEA!S:S)} -> #N/A | I4: =CEILING(G4,S4) -> #N/A | J4: =CEILING(H4,S4) -> #N/A | K4: {=I4*XLOOKUP(C4,'PRICE LIST'!E:E,'PRICE LIST'!J:J)} -> #N/A | L4: {=J4*XLOOKUP(C4,'PRICE LIST'!E:E,'PRICE LIST'!J:J)} -> #N/A | M4: {=XLOOKUP(C4,SEA!B:B,SEA!R:R)} -> #N/A | P4: =Q4*J4 -> #N/A | Q4: {=E4-XLOOKUP(C4,'PRICE LIST'!E:E,'PRICE LIST'!J:J)} -> 5 | S4: 1
A5: {=XLOOKUP(C5,INV!D:D,INV!I:I)} -> EX127 | B5: Car-Stand-Photo | C5: ME0016300000 | D5: ACCESSORY | E5: {=XLOOKUP(C5,INV!A:A,INV!K:K)} -> 5 | G5: {=XLOOKUP(C5,SEA!B:B,SEA!Q:Q)} -> 16.083333 | H5: {=XLOOKUP(C5,SEA!B:B,SEA!S:S)} -> 0 | I5: =CEILING(G5,S5) -> 17 | J5: =CEILING(H5,S5) -> 0 | K5: {=I5*XLOOKUP(C5,'PRICE LIST'!E:E,'PRICE LIST'!J:J)} -> #N/A | L5: {=J5*XLOOKUP(C5,'PRICE LIST'!E:E,'PRICE LIST'!J:J)} -> #N/A | M5: {=XLOOKUP(C5,SEA!B:B,SEA!R:R)} | P5: =Q5*J5 -> #N/A | Q5: {=E5-XLOOKUP(C5,'PRICE LIST'!E:E,'PRICE LIST'!J:J)} -> #N/A | S5: 1
A6: {=XLOOKUP(C6,INV!D:D,INV!I:I)} -> EX401 | B6: Adiyogi miniature 2" car stand - Black | C6: ME0037600000 | D6: ACCESSORY | E6: {=XLOOKUP(C6,INV!A:A,INV!K:K)} -> 15 | G6: {=XLOOKUP(C6,SEA!B:B,SEA!Q:Q)} -> 98.583333 | H6: {=XLOOKUP(C6,SEA!B:B,SEA!S:S)} -> 0 | I6: =CEILING(G6,S6) -> 99 | J6: =CEILING(H6,S6) -> 0 | K6: {=I6*XLOOKUP(C6,'PRICE LIST'!E:E,'PRICE LIST'!J:J)} -> 0 | L6: {=J6*XLOOKUP(C6,'PRICE LIST'!E:E,'PRICE LIST'!J:J)} -> 0 | M6: {=XLOOKUP(C6,SEA!B:B,SEA!R:R)} | P6: =Q6*J6 -> 0 | Q6: {=E6-XLOOKUP(C6,'PRICE LIST'!E:E,'PRICE LIST'!J:J)} -> 15 | S6: 1
A7: {=XLOOKUP(C7,INV!D:D,INV!I:I)} -> EX128 | B7: Devi-Car-Hanging | C7: ME0018900000 | D7: ACCESSORY | E7: {=XLOOKUP(C7,INV!A:A,INV!K:K)} -> 5 | G7: {=XLOOKUP(C7,SEA!B:B,SEA!Q:Q)} -> 131.75 | H7: {=XLOOKUP(C7,SEA!B:B,SEA!S:S)} -> 0 | I7: =CEILING(G7,S7) -> 132 | J7: =CEILING(H7,S7) -> 0 | K7: {=I7*XLOOKUP(C7,'PRICE LIST'!E:E,'PRICE LIST'!J:J)} -> 0 | L7: {=J7*XLOOKUP(C7,'PRICE LIST'!E:E,'PRICE LIST'!J:J)} -> 0 | M7: {=XLOOKUP(C7,SEA!B:B,SEA!R:R)} | P7: =Q7*J7 -> 0 | Q7: {=E7-XLOOKUP(C7,'PRICE LIST'!E:E,'PRICE LIST'!J:J)} -> 5 | S7: 1
A8: {=XLOOKUP(C8,INV!D:D,INV!I:I)} -> HO0108200000 | B8: Devi Journal (Tree free Banana Paper) | C8: HO0108200000 | D8: ACCESSORY | E8: {=XLOOKUP(C8,INV!A:A,INV!K:K)} -> 5 | G8: {=XLOOKUP(C8,SEA!B:B,SEA!Q:Q)} -> 30 | H8: {=XLOOKUP(C8,SEA!B:B,SEA!S:S)} -> 0 | I8: =CEILING(G8,S8) -> 30 | J8: =CEILING(H8,S8) -> 0 | K8: {=I8*XLOOKUP(C8,'PRICE LIST'!E:E,'PRICE LIST'!J:J)} -> 0 | L8: {=J8*XLOOKUP(C8,'PRICE LIST'!E:E,'PRICE LIST'!J:J)} -> 0 | M8: {=XLOOKUP(C8,SEA!B:B,SEA!R:R)} | P8: =Q8*J8 -> 0 | Q8: {=E8-XLOOKUP(C8,'PRICE LIST'!E:E,'PRICE LIST'!J:J)} -> 5 | S8: 1
A9: {=XLOOKUP(C9,INV!D:D,INV!I:I)} -> HO0088917200 | B9: Adiyogi Galactic - Printed Notebook | C9: HO0088917200 | D9: ACCESSORY | E9: {=XLOOKUP(C9,INV!A:A,INV!K:K)} -> 5 | G9: {=XLOOKUP(C9,SEA!B:B,SEA!Q:Q)} -> 20 | H9: {=XLOOKUP(C9,SEA!B:B,SEA!S:S)} -> 0 | I9: =CEILING(G9,S9) -> 20 | J9: =CEILING(H9,S9) -> 0 | K9: {=I9*XLOOKUP(C9,'PRICE LIST'!E:E,'PRICE LIST'!J:J)} -> 0 | L9: {=J9*XLOOKUP(C9,'PRICE LIST'!E:E,'PRICE LIST'!J:J)} -> 0 | M9: {=XLOOKUP(C9,SEA!B:B,SEA!R:R)} | P9: =Q9*J9 -> 0 | Q9: {=E9-XLOOKUP(C9,'PRICE LIST'!E:E,'PRICE LIST'!J:J)} -> 5 | S9: 1
A10: {=XLOOKUP(C10,INV!D:D,INV!I:I)} -> HO0125900000 | B10: Adiyogi Glow-in-the-Dark Keychain (hues of slendour) | C10: HO0125900000 | D10: ACCESSORY | E10: {=XLOOKUP(C10,INV!A:A,INV!K:K)} -> 4 | G10: {=XLOOKUP(C10,SEA!B:B,SEA!Q:Q)} -> 20 | H10: {=XLOOKUP(C10,SEA!B:B,SEA!S:S)} -> 0 | I10: =CEILING(G10,S10) -> 20 | J10: =CEILING(H10,S10) -> 0 | K10: {=I10*XLOOKUP(C10,'PRICE LIST'!E:E,'PRICE LIST'!J:J)} -> 0 | L10: {=J10*XLOOKUP(C10,'PRICE LIST'!E:E,'PRICE LIST'!J:J)} -> 0 | M10: {=XLOOKUP(C10,SEA!B:B,SEA!R:R)} | P10: =Q10*J10 -> 0 | Q10: {=E10-XLOOKUP(C10,'PRICE LIST'!E:E,'PRICE LIST'!J:J)} -> 4 | S10: 1
A11: {=XLOOKUP(C11,INV!D:D,INV!I:I)} -> HO0126100000 | B11: Linga Bhairavi Glow-in-the-Dark Keychain | C11: HO0126100000 | D11: ACCESSORY | E11: {=XLOOKUP(C11,INV!A:A,INV!K:K)} -> 4 | G11: {=XLOOKUP(C11,SEA!B:B,SEA!Q:Q)} -> 20 | H11: {=XLOOKUP(C11,SEA!B:B,SEA!S:S)} -> 0 | I11: =CEILING(G11,S11) -> 20 | J11: =CEILING(H11,S11) -> 0 | K11: {=I11*XLOOKUP(C11,'PRICE LIST'!E:E,'PRICE LIST'!J:J)} -> 0 | L11: {=J11*XLOOKUP(C11,'PRICE LIST'!E:E,'PRICE LIST'!J:J)} -> 0 | M11: {=XLOOKUP(C11,SEA!B:B,SEA!R:R)} | P11: =Q11*J11 -> 0 | Q11: {=E11-XLOOKUP(C11,'PRICE LIST'!E:E,'PRICE LIST'!J:J)} -> 4 | S11: 1
A12: {=XLOOKUP(C12,INV!D:D,INV!I:I)} -> BG162 | B12: Jute Canvas Backpack | C12: CA0000100000 | D12: ACCESSORY | E12: {=XLOOKUP(C12,INV!A:A,INV!K:K)} -> 19 | G12: {=XLOOKUP(C12,SEA!B:B,SEA!Q:Q)} -> 0 | H12: {=XLOOKUP(C12,SEA!B:B,SEA!S:S)} -> 0 | I12: =CEILING(G12,S12) -> 0 | J12: =CEILING(H12,S12) -> 0 | K12: {=I12*XLOOKUP(C12,'PRICE LIST'!E:E,'PRICE LIST'!J:J)} -> 0 | L12: {=J12*XLOOKUP(C12,'PRICE LIST'!E:E,'PRICE LIST'!J:J)} -> 0 | M12: {=XLOOKUP(C12,SEA!B:B,SEA!R:R)} | P12: =Q12*J12 -> 0 | Q12: {=E12-XLOOKUP(C12,'PRICE LIST'!E:E,'PRICE LIST'!J:J)} -> 19 | S12: 1
A13: {=XLOOKUP(C13,INV!D:D,INV!I:I)} -> EX274 | B13: Naga - Foil printed notebook | C13: HO0088916900 | D13: ACCESSORY | E13: {=XLOOKUP(C13,INV!A:A,INV!K:K)} -> 10 | G13: {=XLOOKUP(C13,SEA!B:B,SEA!Q:Q)} -> 0 | H13: {=XLOOKUP(C13,SEA!B:B,SEA!S:S)} -> 0 | I13: =CEILING(G13,S13) -> 0 | J13: =CEILING(H13,S13) -> 0 | K13: {=I13*XLOOKUP(C13,'PRICE LIST'!E:E,'PRICE LIST'!J:J)} -> 0 | L13: {=J13*XLOOKUP(C13,'PRICE LIST'!E:E,'PRICE LIST'!J:J)} -> 0 | M13: {=XLOOKUP(C13,SEA!B:B,SEA!R:R)} | P13: =Q13*J13 -> 0 | Q13: {=E13-XLOOKUP(C13,'PRICE LIST'!E:E,'PRICE LIST'!J:J)} -> 10 | S13: 1
A14: {=XLOOKUP(C14,INV!D:D,INV!I:I)} -> EX328 | B14: Infinite - Screen Printed Notebook | C14: HO0116117000 | D14: ACCESSORY | E14: {=XLOOKUP(C14,INV!A:A,INV!K:K)} -> 5 | G14: {=XLOOKUP(C14,SEA!B:B,SEA!Q:Q)} -> 0 | H14: {=XLOOKUP(C14,SEA!B:B,SEA!S:S)} -> 0 | I14: =CEILING(G14,S14) -> 0 | J14: =CEILING(H14,S14) -> 0 | K14: {=I14*XLOOKUP(C14,'PRICE LIST'!E:E,'PRICE LIST'!J:J)} -> 0 | L14: {=J14*XLOOKUP(C14,'PRICE LIST'!E:E,'PRICE LIST'!J:J)} -> 0 | M14: {=XLOOKUP(C14,SEA!B:B,SEA!R:R)} | P14: =Q14*J14 -> 0 | Q14: {=E14-XLOOKUP(C14,'PRICE LIST'!E:E,'PRICE LIST'!J:J)} -> 5 | S14: 1
... A18: {=XLOOKUP(C18,INV!D:D,INV!I:I)} -> EX327 | B18: Linga Bhairavi Metal Keychain | C18: HO0110400000 | D18: ACCESSORY | E18: {=XLOOKUP(C18,INV!A:A,INV!K:K)} -> 3 | G18: {=XLOOKUP(C18,SEA!B:B,SEA!Q:Q)} -> 0 | H18: {=XLOOKUP(C18,SEA!B:B,SEA!S:S)} -> 0 | I18: =CEILING(G18,S18) -> 0 | J18: =CEILING(H18,S18) -> 0 | K18: {=I18*XLOOKUP(C18,'PRICE LIST'!E:E,'PRICE LIST'!J:J)} -> 0 | L18: {=J18*XLOOKUP(C18,'PRICE LIST'!E:E,'PRICE LIST'!J:J)} -> 0 | M18: {=XLOOKUP(C18,SEA!B:B,SEA!R:R)} | P18: =Q18*J18 -> 0 | Q18: {=E18-XLOOKUP(C18,'PRICE LIST'!E:E,'PRICE LIST'!J:J)} -> 3 | S18: 1
A19: {=XLOOKUP(C19,INV!D:D,INV!I:I)} -> RJ201-150 | B19: Herbal-Toothpaste | C19: BC0000706502 | D19: BODY CARE | E19: {=XLOOKUP(C19,INV!A:A,INV!K:K)} -> 8 | F19: TOOTHPASTE | G19: {=XLOOKUP(C19,UNIQUE!B:B,UNIQUE!I:I)} -> 8056 | I19: =CEILING(G19,S19) -> 8056 | J19: =CEILING(H19,S19) -> 0 | K19: {=I19*XLOOKUP(C19,'PRICE LIST'!E:E,'PRICE LIST'!J:J)} -> 0 | L19: {=J19*XLOOKUP(C19,'PRICE LIST'!E:E,'PRICE LIST'!J:J)} -> 0 | M19: {=XLOOKUP(C19,SEA!B:B,SEA!R:R)} -> #N/A | S19: 1
A20: {=XLOOKUP(C20,INV!D:D,INV!I:I)} -> BC227 | B20: Shikakai & Jatamansi Certified Organic Strengthening Shampoo - 200ml (Bloom) | C20: BC0003503302 | D20: BODY CARE | E20: {=XLOOKUP(C20,INV!A:A,INV!K:K)} -> 21 | F20: BLOOM | G20: {=XLOOKUP(C20,BLOOM!B:B,BLOOM!J:J)} -> #N/A | H20: {=XLOOKUP(C20,BLOOM!B:B,BLOOM!L:L)} -> #N/A | I20: =CEILING(G20,S20) -> #N/A | J20: =CEILING(H20,S20) -> #N/A | K20: {=I20*XLOOKUP(C20,'PRICE LIST'!E:E,'PRICE LIST'!J:J)} -> #N/A | L20: {=J20*XLOOKUP(C20,'PRICE LIST'!E:E,'PRICE LIST'!J:J)} -> #N/A | M20: {=XLOOKUP(C20,SEA!B:B,SEA!R:R)} -> #N/A | S20: 24
A21: {=XLOOKUP(C21,INV!D:D,INV!I:I)} -> BC221 | B21: Saffron & Sandalwood Certified Organic Refreshing Shower Gel - 200ml (Bloom) - Cosmos Organic certified by Ecocert Greenlife | C21: BC0002403302 | D21: BODY CARE | E21: {=XLOOKUP(C21,INV!A:A,INV!K:K)} -> 21 | F21: BLOOM | G21: {=XLOOKUP(C21,BLOOM!B:B,BLOOM!J:J)} -> #N/A | H21: {=XLOOKUP(C21,BLOOM!B:B,BLOOM!L:L)} -> #N/A | I21: =CEILING(G21,S21) -> #N/A | J21: =CEILING(H21,S21) -> #N/A | K21: {=I21*XLOOKUP(C21,'PRICE LIST'!E:E,'PRICE LIST'!J:J)} -> #N/A | L21: {=J21*XLOOKUP(C21,'PRICE LIST'!E:E,'PRICE LIST'!J:J)} -> #N/A | M21: {=XLOOKUP(C21,SEA!B:B,SEA!R:R)} -> #N/A | S21: 24
A22: {=XLOOKUP(C22,INV!D:D,INV!I:I)} -> BC231 | B22: Argan & Acai Organic Restorative Hair Oil - 100ml (Bloom) | C22: BC0003803102 | D22: BODY CARE | E22: {=XLOOKUP(C22,INV!A:A,INV!K:K)} -> 18 | F22: BLOOM | G22: {=XLOOKUP(C22,BLOOM!B:B,BLOOM!J:J)} -> #N/A | H22: {=XLOOKUP(C22,BLOOM!B:B,BLOOM!L:L)} -> #N/A | I22: =CEILING(G22,S22) -> #N/A | J22: =CEILING(H22,S22) -> #N/A | K22: {=I22*XLOOKUP(C22,'PRICE LIST'!E:E,'PRICE LIST'!J:J)} -> #N/A | L22: {=J22*XLOOKUP(C22,'PRICE LIST'!E:E,'PRICE LIST'!J:J)} -> #N/A | M22: {=XLOOKUP(C22,SEA!B:B,SEA!R:R)} -> #N/A | S22: 24
A23: {=XLOOKUP(C23,INV!D:D,INV!I:I)} -> BC223 | B23: Hibiscus & Aloe Vera Organic Moisturizing Body Lotion - 100ml (Bloom) | C23: BC0002603102 | D23: BODY CARE | E23: {=XLOOKUP(C23,INV!A:A,INV!K:K)} -> 15 | F23: BLOOM | G23: {=XLOOKUP(C23,BLOOM!B:B,BLOOM!J:J)} -> #N/A | H23: {=XLOOKUP(C23,BLOOM!B:B,BLOOM!L:L)} -> #N/A | I23: =CEILING(G23,S23) -> #N/A | J23: =CEILING(H23,S23) -> #N/A | K23: {=I23*XLOOKUP(C23,'PRICE LIST'!E:E,'PRICE LIST'!J:J)} -> #N/A | L23: {=J23*XLOOKUP(C23,'PRICE LIST'!E:E,'PRICE LIST'!J:J)} -> #N/A | M23: {=XLOOKUP(C23,SEA!B:B,SEA!R:R)} -> #N/A | S23: 24
A24: {=XLOOKUP(C24,INV!D:D,INV!I:I)} -> RJ201-50 | B24: Herbal-Toothpaste | C24: BC0000706002 | D24: BODY CARE | E24: {=XLOOKUP(C24,INV!A:A,INV!K:K)} -> 4 | F24: TOOTHPASTE | G24: {=XLOOKUP(C24,UNIQUE!B:B,UNIQUE!I:I)} -> 2400 | I24: =CEILING(G24,S24) -> 2400 | J24: =CEILING(H24,S24) -> 0 | K24: {=I24*XLOOKUP(C24,'PRICE LIST'!E:E,'PRICE LIST'!J:J)} -> 0 | L24: {=J24*XLOOKUP(C24,'PRICE LIST'!E:E,'PRICE LIST'!J:J)} -> 0 | M24: {=XLOOKUP(C24,SEA!B:B,SEA!R:R)} -> #N/A | S24: 1
A25: {=XLOOKUP(C25,INV!D:D,INV!I:I)} -> BC236 | B25: Sandalwood and Turmeric Face Wash 100 ml (Bloom) | C25: BC0003003102 | D25: BODY CARE | E25: {=XLOOKUP(C25,INV!A:A,INV!K:K)} -> 14 | F25: BLOOM | G25: {=XLOOKUP(C25,BLOOM!B:B,BLOOM!J:J)} -> #N/A | H25: {=XLOOKUP(C25,BLOOM!B:B,BLOOM!L:L)} -> #N/A | I25: =CEILING(G25,S25) -> #N/A | J25: =CEILING(H25,S25) -> #N/A | K25: {=I25*XLOOKUP(C25,'PRICE LIST'!E:E,'PRICE LIST'!J:J)} -> #N/A | L25: {=J25*XLOOKUP(C25,'PRICE LIST'!E:E,'PRICE LIST'!J:J)} -> #N/A | S25: 24
A26: {=XLOOKUP(C26,INV!D:D,INV!I:I)} -> BC225 | B26: Neem & Tulsi Certified Organic Cleansing Face Wash - 100ml (Bloom) | C26: BC0002903102 | D26: BODY CARE | E26: {=XLOOKUP(C26,INV!A:A,INV!K:K)} -> 14 | F26: BLOOM | G26: {=XLOOKUP(C26,BLOOM!B:B,BLOOM!J:J)} -> #N/A | H26: {=XLOOKUP(C26,BLOOM!B:B,BLOOM!L:L)} -> #N/A | I26: =CEILING(G26,S26) -> #N/A | J26: =CEILING(H26,S26) -> #N/A | K26: {=I26*XLOOKUP(C26,'PRICE LIST'!E:E,'PRICE LIST'!J:J)} -> #N/A | L26: {=J26*XLOOKUP(C26,'PRICE LIST'!E:E,'PRICE LIST'!J:J)} -> #N/A | M26: {=XLOOKUP(C26,SEA!B:B,SEA!R:R)} -> #N/A | S26: 24
A27: {=XLOOKUP(C27,INV!D:D,INV!I:I)} -> BC233 | B27: US Bloom 24 Hours Organic Body Lotion (Extra Dry Skin) (100 ml) | C27: BC0002703102 | D27: BODY CARE | E27: {=XLOOKUP(C27,INV!A:A,INV!K:K)} -> 15 | F27: BLOOM | G27: {=XLOOKUP(C27,BLOOM!B:B,BLOOM!J:J)} -> #N/A | H27: {=XLOOKUP(C27,BLOOM!B:B,BLOOM!L:L)} -> #N/A | I27: =CEILING(G27,S27) -> #N/A | J27: =CEILING(H27,S27) -> #N/A | K27: {=I27*XLOOKUP(C27,'PRICE LIST'!E:E,'PRICE LIST'!J:J)} -> #N/A | L27: {=J27*XLOOKUP(C27,'PRICE LIST'!E:E,'PRICE LIST'!J:J)} -> #N/A | S27: 24
A28: {=XLOOKUP(C28,INV!D:D,INV!I:I)} -> BC229 | B28: Hibiscus & Grapeseed Organic Strengthening Conditioner - 100ml (Bloom) | C28: BC0003603102 | D28: BODY CARE | E28: {=XLOOKUP(C28,INV!A:A,INV!K:K)} -> 15 | F28: BLOOM | G28: {=XLOOKUP(C28,BLOOM!B:B,BLOOM!J:J)} -> #N/A | H28: {=XLOOKUP(C28,BLOOM!B:B,BLOOM!L:L)} -> #N/A | I28: =CEILING(G28,S28) -> #N/A | J28: =CEILING(H28,S28) -> #N/A | K28: {=I28*XLOOKUP(C28,'PRICE LIST'!E:E,'PRICE LIST'!J:J)} -> #N/A | L28: {=J28*XLOOKUP(C28,'PRICE LIST'!E:E,'PRICE LIST'!J:J)} -> #N/A | S28: 24
A29: {=XLOOKUP(C29,INV!D:D,INV!I:I)} -> BC234 | B29: US Bloom Refreshing & Age Defence Shower Gel (200 ml) | C29: BC0002803302 | D29: BODY CARE | E29: {=XLOOKUP(C29,INV!A:A,INV!K:K)} -> 21 | F29: BLOOM | G29: {=XLOOKUP(C29,BLOOM!B:B,BLOOM!J:J)} -> #N/A | H29: {=XLOOKUP(C29,BLOOM!B:B,BLOOM!L:L)} -> #N/A | I29: =CEILING(G29,S29) -> #N/A | J29: =CEILING(H29,S29) -> #N/A | K29: {=I29*XLOOKUP(C29,'PRICE LIST'!E:E,'PRICE LIST'!J:J)} -> #N/A | L29: {=J29*XLOOKUP(C29,'PRICE LIST'!E:E,'PRICE LIST'!J:J)} -> #N/A | S29: 24
A30: {=XLOOKUP(C30,INV!D:D,INV!I:I)} -> BC220 | B30: Saffron & Sandalwood Certified Organic Refreshing Shower Gel - 30ml (Bloom) | C30: BC0002403002 | D30: BODY CARE | E30: {=XLOOKUP(C30,INV!A:A,INV!K:K)} -> 7 | F30: BLOOM | G30: {=XLOOKUP(C30,BLOOM!B:B,BLOOM!J:J)} -> #N/A | H30: {=XLOOKUP(C30,BLOOM!B:B,BLOOM!L:L)} -> #N/A | I30: =CEILING(G30,S30) -> #N/A | J30: =CEILING(H30,S30) -> #N/A | K30: {=I30*XLOOKUP(C30,'PRICE LIST'!E:E,'PRICE LIST'!J:J)} -> #N/A | L30: {=J30*XLOOKUP(C30,'PRICE LIST'!E:E,'PRICE LIST'!J:J)} -> #N/A | S30: 32
A31: {=XLOOKUP(C31,INV!D:D,INV!I:I)} -> BC222 | B31: Hibiscus & Aloe Vera Organic Moisturizing Body Lotion - 30ml (Bloom) | C31: BC0002603002 | D31: BODY CARE | E31: {=XLOOKUP(C31,INV!A:A,INV!K:K)} -> 7 | F31: BLOOM | G31: {=XLOOKUP(C31,BLOOM!B:B,BLOOM!J:J)} -> #N/A | H31: {=XLOOKUP(C31,BLOOM!B:B,BLOOM!L:L)} -> #N/A | I31: =CEILING(G31,S31) -> #N/A | J31: =CEILING(H31,S31) -> #N/A | K31: {=I31*XLOOKUP(C31,'PRICE LIST'!E:E,'PRICE LIST'!J:J)} -> #N/A | L31: {=J31*XLOOKUP(C31,'PRICE LIST'!E:E,'PRICE LIST'!J:J)} -> #N/A | S31: 32
A32: {=XLOOKUP(C32,INV!D:D,INV!I:I)} -> BC228 | B32: Hibiscus & Grapeseed Organic Strengthening Conditioner - 30ml (Bloom) | C32: BC0003603002 | D32: BODY CARE | E32: {=XLOOKUP(C32,INV!A:A,INV!K:K)} -> 7 | F32: BLOOM | G32: {=XLOOKUP(C32,BLOOM!B:B,BLOOM!J:J)} -> #N/A | H32: {=XLOOKUP(C32,BLOOM!B:B,BLOOM!L:L)} -> #N/A | I32: =CEILING(G32,S32) -> #N/A | J32: =CEILING(H32,S32) -> #N/A | K32: {=I32*XLOOKUP(C32,'PRICE LIST'!E:E,'PRICE LIST'!J:J)} -> #N/A | L32: {=J32*XLOOKUP(C32,'PRICE LIST'!E:E,'PRICE LIST'!J:J)} -> #N/A | S32: 32
A33: {=XLOOKUP(C33,INV!D:D,INV!I:I)} -> BC226 | B33: Shikakai & Jatamansi Certified Organic Strengthening Shampoo - 30ml (Bloom) | C33: BC0003503002 | D33: BODY CARE | E33: {=XLOOKUP(C33,INV!A:A,INV!K:K)} -> 7 | F33: BLOOM | G33: {=XLOOKUP(C33,BLOOM!B:B,BLOOM!J:J)} -> #N/A | H33: {=XLOOKUP(C33,BLOOM!B:B,BLOOM!L:L)} -> #N/A | I33: =CEILING(G33,S33) -> #N/A | J33: =CEILING(H33,S33) -> #N/A | K33: {=I33*XLOOKUP(C33,'PRICE LIST'!E:E,'PRICE LIST'!J:J)} -> #N/A | L33: {=J33*XLOOKUP(C33,'PRICE LIST'!E:E,'PRICE LIST'!J:J)} -> #N/A | S33: 32
A34: {=XLOOKUP(C34,INV!D:D,INV!I:I)} -> BC235 | B34: Sandalwood and Turmeric Face Wash 30ml (Bloom) | C34: BC0003003002 | D34: BODY CARE | E34: {=XLOOKUP(C34,INV!A:A,INV!K:K)} -> 7 | F34: BLOOM | G34: {=XLOOKUP(C34,BLOOM!B:B,BLOOM!J:J)} -> #N/A | H34: {=XLOOKUP(C34,BLOOM!B:B,BLOOM!L:L)} -> #N/A | I34: =CEILING(G34,S34) -> #N/A | J34: =CEILING(H34,S34) -> #N/A | K34: {=I34*XLOOKUP(C34,'PRICE LIST'!E:E,'PRICE LIST'!J:J)} -> #N/A | L34: {=J34*XLOOKUP(C34,'PRICE LIST'!E:E,'PRICE LIST'!J:J)} -> #N/A | S34: 32
A35: {=XLOOKUP(C35,INV!D:D,INV!I:I)} -> BC230 | B35: Argan & Acai Organic Restorative Hair Oil - 30ml (Bloom) | C35: BC0003803002 | D35: BODY CARE | E35: {=XLOOKUP(C35,INV!A:A,INV!K:K)} -> 7 | F35: BLOOM | G35: {=XLOOKUP(C35,BLOOM!B:B,BLOOM!J:J)} -> #N/A | H35: {=XLOOKUP(C35,BLOOM!B:B,BLOOM!L:L)} -> #N/A | I35: =CEILING(G35,S35) -> #N/A | J35: =CEILING(H35,S35) -> #N/A | K35: {=I35*XLOOKUP(C35,'PRICE LIST'!E:E,'PRICE LIST'!J:J)} -> #N/A | L35: {=J35*XLOOKUP(C35,'PRICE LIST'!E:E,'PRICE LIST'!J:J)} -> #N/A | S35: 32
A36: {=XLOOKUP(C36,INV!D:D,INV!I:I)} -> BC224 | B36: Neem & Tulsi Certified Organic Cleansing Face Wash - 30ml (Bloom) | C36: BC0002903002 | D36: BODY CARE | E36: {=XLOOKUP(C36,INV!A:A,INV!K:K)} -> 7 | F36: BLOOM | G36: {=XLOOKUP(C36,BLOOM!B:B,BLOOM!J:J)} -> #N/A | H36: {=XLOOKUP(C36,BLOOM!B:B,BLOOM!L:L)} -> #N/A | I36: =CEILING(G36,S36) -> #N/A | J36: =CEILING(H36,S36) -> #N/A | K36: {=I36*XLOOKUP(C36,'PRICE LIST'!E:E,'PRICE LIST'!J:J)} -> #N/A | L36: {=J36*XLOOKUP(C36,'PRICE LIST'!E:E,'PRICE LIST'!J:J)} -> #N/A | S36: 32
A37: {=XLOOKUP(C37,INV!D:D,INV!I:I)} -> BC501 | B37: Jasmine Orient Solid Perfume | C37: BC0001005100 | D37: BODY CARE | E37: {=XLOOKUP(C37,INV!A:A,INV!K:K)} -> 15 | G37: {=XLOOKUP(C37,SEA!B:B,SEA!Q:Q)} -> 68.5 | H37: {=XLOOKUP(C37,SEA!B:B,SEA!S:S)} -> 0 | I37: =CEILING(G37,S37) -> 69 | J37: =CEILING(H37,S37) -> 0 | K37: {=I37*XLOOKUP(C37,'PRICE LIST'!E:E,'PRICE LIST'!J:J)} -> 0 | L37: {=J37*XLOOKUP(C37,'PRICE LIST'!E:E,'PRICE LIST'!J:J)} -> 0 | M37: {=XLOOKUP(C37,SEA!B:B,SEA!R:R)} | P37: =Q37*J37 -> 0 | Q37: {=E37-XLOOKUP(C37,'PRICE LIST'!E:E,'PRICE LIST'!J:J)} -> 15 | S37: 1
A38: {=XLOOKUP(C38,INV!D:D,INV!I:I)} -> RJ203-100 | B38: Ojasvini 100g | C38: BC0002006302 | D38: BODY CARE | E38: {=XLOOKUP(C38,INV!A:A,INV!K:K)} -> 8 | F38: EXPIRY | G38: {=XLOOKUP(C38,SEA!B:B,SEA!Q:Q)} -> #N/A | H38: {=XLOOKUP(C38,SEA!B:B,SEA!S:S)} -> #N/A | I38: =CEILING(G38,S38) -> #N/A | J38: =CEILING(H38,S38) -> #N/A | K38: {=I38*XLOOKUP(C38,'PRICE LIST'!E:E,'PRICE LIST'!J:J)} -> #N/A | L38: {=J38*XLOOKUP(C38,'PRICE LIST'!E:E,'PRICE LIST'!J:J)} -> #N/A | M38: {=XLOOKUP(C38,SEA!B:B,SEA!R:R)} | P38: =Q38*J38 -> #N/A | Q38: {=E38-XLOOKUP(C38,'PRICE LIST'!E:E,'PRICE LIST'!J:J)} -> 8 | S38: 1
A39: {=XLOOKUP(C39,INV!D:D,INV!I:I)} -> EX141 | B39: NeemWoodComb-DualEnd | C39: BC0000400002 | D39: BODY CARE | E39: {=XLOOKUP(C39,INV!A:A,INV!K:K)} -> 7 | G39: {=XLOOKUP(C39,SEA!B:B,SEA!Q:Q)} -> 84.333333 | H39: {=XLOOKUP(C39,SEA!B:B,SEA!S:S)} -> 0 | I39: =CEILING(G39,S39) -> 85 | J39: =CEILING(H39,S39) -> 0 | K39: {=I39*XLOOKUP(C39,'PRICE LIST'!E:E,'PRICE LIST'!J:J)} -> 0 | L39: {=J39*XLOOKUP(C39,'PRICE LIST'!E:E,'PRICE LIST'!J:J)} -> 0 | M39: {=XLOOKUP(C39,SEA!B:B,SEA!R:R)} | P39: =Q39*J39 -> 0 | Q39: {=E39-XLOOKUP(C39,'PRICE LIST'!E:E,'PRICE LIST'!J:J)} -> 7 | S39: 1
A40: {=XLOOKUP(C40,INV!D:D,INV!I:I)} -> BC503 | B40: Relax Solid Perfume | C40: BC0001205100 | D40: BODY CARE | E40: {=XLOOKUP(C40,INV!A:A,INV!K:K)} -> 15 | G40: {=XLOOKUP(C40,SEA!B:B,SEA!Q:Q)} -> 34.75 | H40: {=XLOOKUP(C40,SEA!B:B,SEA!S:S)} -> 0 | I40: =CEILING(G40,S40) -> 35 | J40: =CEILING(H40,S40) -> 0 | K40: {=I40*XLOOKUP(C40,'PRICE LIST'!E:E,'PRICE LIST'!J:J)} -> 0 | L40: {=J40*XLOOKUP(C40,'PRICE LIST'!E:E,'PRICE LIST'!J:J)} -> 0 | M40: {=XLOOKUP(C40,SEA!B:B,SEA!R:R)} | P40: =Q40*J40 -> 0 | Q40: {=E40-XLOOKUP(C40,'PRICE LIST'!E:E,'PRICE LIST'!J:J)} -> 15 | S40: 1
A41: {=XLOOKUP(C41,INV!D:D,INV!I:I)} -> BC504 | B41: Royal Oud Solid Perfume | C41: BC0001305100 | D41: BODY CARE | E41: {=XLOOKUP(C41,INV!A:A,INV!K:K)} -> 15 | G41: {=XLOOKUP(C41,SEA!B:B,SEA!Q:Q)} -> 19.916667 | H41: {=XLOOKUP(C41,SEA!B:B,SEA!S:S)} -> 0 | I41: =CEILING(G41,S41) -> 20 | J41: =CEILING(H41,S41) -> 0 | K41: {=I41*XLOOKUP(C41,'PRICE LIST'!E:E,'PRICE LIST'!J:J)} -> 0 | L41: {=J41*XLOOKUP(C41,'PRICE LIST'!E:E,'PRICE LIST'!J:J)} -> 0 | M41: {=XLOOKUP(C41,SEA!B:B,SEA!R:R)} | P41: =Q41*J41 -> 0 | Q41: {=E41-XLOOKUP(C41,'PRICE LIST'!E:E,'PRICE LIST'!J:J)} -> 15 | S41: 1
A42: {=XLOOKUP(C42,INV!D:D,INV!I:I)} -> EX114 | B42: NeemWoodComb-Handle-NarrowTeeth | C42: BC0000200002 | D42: BODY CARE | E42: {=XLOOKUP(C42,INV!A:A,INV!K:K)} -> 7 | G42: {=XLOOKUP(C42,SEA!B:B,SEA!Q:Q)} -> 36.166667 | H42: {=XLOOKUP(C42,SEA!B:B,SEA!S:S)} -> 0 | I42: =CEILING(G42,S42) -> 37 | J42: =CEILING(H42,S42) -> 0 | K42: {=I42*XLOOKUP(C42,'PRICE LIST'!E:E,'PRICE LIST'!J:J)} -> 0 | L42: {=J42*XLOOKUP(C42,'PRICE LIST'!E:E,'PRICE LIST'!J:J)} -> 0 | M42: {=XLOOKUP(C42,SEA!B:B,SEA!R:R)} | P42: =Q42*J42 -> 0 | Q42: {=E42-XLOOKUP(C42,'PRICE LIST'!E:E,'PRICE LIST'!J:J)} -> 7 | S42: 1
A43: {=XLOOKUP(C43,INV!D:D,INV!I:I)} -> EX197-S | B43: Organic Waffle Towel - Small | C43: CA0009100200 | D43: BODY CARE | E43: {=XLOOKUP(C43,INV!A:A,INV!K:K)} -> 5 | G43: {=XLOOKUP(C43,SEA!B:B,SEA!Q:Q)} -> 14 | H43: {=XLOOKUP(C43,SEA!B:B,SEA!S:S)} -> 0 | I43: =CEILING(G43,S43) -> 14 | J43: =CEILING(H43,S43) -> 0 | K43: {=I43*XLOOKUP(C43,'PRICE LIST'!E:E,'PRICE LIST'!J:J)} -> 0 | L43: {=J43*XLOOKUP(C43,'PRICE LIST'!E:E,'PRICE LIST'!J:J)} -> 0 | M43: {=XLOOKUP(C43,SEA!B:B,SEA!R:R)} | P43: =Q43*J43 -> 0 | Q43: {=E43-XLOOKUP(C43,'PRICE LIST'!E:E,'PRICE LIST'!J:J)} -> 5 | S43: 1
A44: {=XLOOKUP(C44,INV!D:D,INV!I:I)} -> RJ202-500 | B44: Kesh Jyoti 500g | C44: BC0001906902 | D44: BODY CARE | E44: {=XLOOKUP(C44,INV!A:A,INV!K:K)} -> 25 | F44: EXPIRY | G44: {=XLOOKUP(C44,SEA!B:B,SEA!Q:Q)} -> #N/A | H44: {=XLOOKUP(C44,SEA!B:B,SEA!S:S)} -> #N/A | I44: =CEILING(G44,S44) -> #N/A | J44: =CEILING(H44,S44) -> #N/A | K44: {=I44*XLOOKUP(C44,'PRICE LIST'!E:E,'PRICE LIST'!J:J)} -> #N/A | L44: {=J44*XLOOKUP(C44,'PRICE LIST'!E:E,'PRICE LIST'!J:J)} -> #N/A | M44: {=XLOOKUP(C44,SEA!B:B,SEA!R:R)} | P44: =Q44*J44 -> #N/A | Q44: {=E44-XLOOKUP(C44,'PRICE LIST'!E:E,'PRICE LIST'!J:J)} -> 25 | S44: 1
A45: {=XLOOKUP(C45,INV!D:D,INV!I:I)} -> RJ202-100 | B45: Kesh Jyoti 100g | C45: BC0001906302 | D45: BODY CARE | E45: {=XLOOKUP(C45,INV!A:A,INV!K:K)} -> 8 | F45: EXPIRY | G45: {=XLOOKUP(C45,SEA!B:B,SEA!Q:Q)} -> #N/A | H45: {=XLOOKUP(C45,SEA!B:B,SEA!S:S)} -> #N/A | I45: =CEILING(G45,S45) -> #N/A | J45: =CEILING(H45,S45) -> #N/A | K45: {=I45*XLOOKUP(C45,'PRICE LIST'!E:E,'PRICE LIST'!J:J)} -> #N/A | L45: {=J45*XLOOKUP(C45,'PRICE LIST'!E:E,'PRICE LIST'!J:J)} -> #N/A | M45: {=XLOOKUP(C45,SEA!B:B,SEA!R:R)} | P45: =Q45*J45 -> #N/A | Q45: {=E45-XLOOKUP(C45,'PRICE LIST'!E:E,'PRICE LIST'!J:J)} -> 8 | S45: 1
A46: {=XLOOKUP(C46,INV!D:D,INV!I:I)} -> BC505 | B46: Sandalwood & Vetiver Solid Perfume | C46: BC0001405100 | D46: BODY CARE | E46: {=XLOOKUP(C46,INV!A:A,INV!K:K)} -> 15 | G46: {=XLOOKUP(C46,SEA!B:B,SEA!Q:Q)} -> 0 | H46: {=XLOOKUP(C46,SEA!B:B,SEA!S:S)} -> 0 | I46: =CEILING(G46,S46) -> 0 | J46: =CEILING(H46,S46) -> 0 | K46: {=I46*XLOOKUP(C46,'PRICE LIST'!E:E,'PRICE LIST'!J:J)} -> 0 | L46: {=J46*XLOOKUP(C46,'PRICE LIST'!E:E,'PRICE LIST'!J:J)} -> 0 | M46: {=XLOOKUP(C46,SEA!B:B,SEA!R:R)} | P46: =Q46*J46 -> 0 | Q46: {=E46-XLOOKUP(C46,'PRICE LIST'!E:E,'PRICE LIST'!J:J)} -> 15 | S46: 1
A47: {=XLOOKUP(C47,INV!D:D,INV!I:I)} -> RJ203-500 | B47: Ojasvini 500g | C47: BC0002006902 | D47: BODY CARE | E47: {=XLOOKUP(C47,INV!A:A,INV!K:K)} -> 25 | F47: EXPIRY | G47: {=XLOOKUP(C47,SEA!B:B,SEA!Q:Q)} -> #N/A | H47: {=XLOOKUP(C47,SEA!B:B,SEA!S:S)} -> #N/A | I47: =CEILING(G47,S47) -> #N/A | J47: =CEILING(H47,S47) -> #N/A | K47: {=I47*XLOOKUP(C47,'PRICE LIST'!E:E,'PRICE LIST'!J:J)} -> #N/A | L47: {=J47*XLOOKUP(C47,'PRICE LIST'!E:E,'PRICE LIST'!J:J)} -> #N/A | M47: {=XLOOKUP(C47,SEA!B:B,SEA!R:R)} | P47: =Q47*J47 -> #N/A | Q47: {=E47-XLOOKUP(C47,'PRICE LIST'!E:E,'PRICE LIST'!J:J)} -> 25 | S47: 1
A48: {=XLOOKUP(C48,INV!D:D,INV!I:I)} -> YA543 | B48: Copper Tongue Cleaner | C48: BC0006700000 | D48: BODY CARE | E48: {=XLOOKUP(C48,INV!A:A,INV!K:K)} -> 9 | G48: {=XLOOKUP(C48,SEA!B:B,SEA!Q:Q)} -> 0 | H48: {=XLOOKUP(C48,SEA!B:B,SEA!S:S)} -> 0 | I48: =CEILING(G48,S48) -> 0 | J48: =CEILING(H48,S48) -> 0 | K48: {=I48*XLOOKUP(C48,'PRICE LIST'!E:E,'PRICE LIST'!J:J)} -> 0 | L48: {=J48*XLOOKUP(C48,'PRICE LIST'!E:E,'PRICE LIST'!J:J)} -> 0 | M48: {=XLOOKUP(C48,SEA!B:B,SEA!R:R)} | P48: =Q48*J48 -> 0 | Q48: {=E48-XLOOKUP(C48,'PRICE LIST'!E:E,'PRICE LIST'!J:J)} -> 9 | S48: 1
A49: {=XLOOKUP(C49,INV!D:D,INV!I:I)} -> EX197-L | B49: Organic Waffle Towel - Big | C49: CA0009100400 | D49: BODY CARE | E49: {=XLOOKUP(C49,INV!A:A,INV!K:K)} -> 9 | G49: {=XLOOKUP(C49,SEA!B:B,SEA!Q:Q)} -> 0 | H49: {=XLOOKUP(C49,SEA!B:B,SEA!S:S)} -> 0 | I49: =CEILING(G49,S49) -> 0 | J49: =CEILING(H49,S49) -> 0 | K49: {=I49*XLOOKUP(C49,'PRICE LIST'!E:E,'PRICE LIST'!J:J)} -> 0 | L49: {=J49*XLOOKUP(C49,'PRICE LIST'!E:E,'PRICE LIST'!J:J)} -> 0 | M49: {=XLOOKUP(C49,SEA!B:B,SEA!R:R)} | P49: =Q49*J49 -> 0 | Q49: {=E49-XLOOKUP(C49,'PRICE LIST'!E:E,'PRICE LIST'!J:J)} -> 9 | S49: 1
A50: {=XLOOKUP(C50,INV!D:D,INV!I:I)} -> BC237 | B50: US Bloom Extra Nourishment & Protection Organic Shampoo (200 ml) | C50: BC0004203302 | D50: BODY CARE | E50: {=XLOOKUP(C50,INV!A:A,INV!K:K)} -> 21 | F50: BLOOM | G50: {=XLOOKUP(C50,BLOOM!B:B,BLOOM!J:J)} -> #N/A | H50: {=XLOOKUP(C50,BLOOM!B:B,BLOOM!L:L)} -> #N/A | I50: =CEILING(G50,S50) -> #N/A | J50: =CEILING(H50,S50) -> #N/A | K50: {=I50*XLOOKUP(C50,'PRICE LIST'!E:E,'PRICE LIST'!J:J)} -> #N/A | L50: {=J50*XLOOKUP(C50,'PRICE LIST'!E:E,'PRICE LIST'!J:J)} -> #N/A | S50: 24
A51: {=XLOOKUP(C51,INV!D:D,INV!I:I)} -> BK105 | B51: English Mystics Musings Hard | C51: ME0004801500 | D51: BOOK | E51: {=XLOOKUP(C51,INV!A:A,INV!K:K)} -> 30 | G51: {=XLOOKUP(C51,SEA!B:B,SEA!Q:Q)} -> 0.83333333 | H51: {=XLOOKUP(C51,SEA!B:B,SEA!S:S)} -> 4.75 | I51: =CEILING(G51,S51) -> 1 | J51: =CEILING(H51,S51) -> 5 | K51: {=I51*XLOOKUP(C51,'PRICE LIST'!E:E,'PRICE LIST'!J:J)} -> #N/A | L51: {=J51*XLOOKUP(C51,'PRICE LIST'!E:E,'PRICE LIST'!J:J)} -> #N/A | M51: {=XLOOKUP(C51,SEA!B:B,SEA!R:R)} | P51: =Q51*J51 -> #N/A | Q51: {=E51-XLOOKUP(C51,'PRICE LIST'!E:E,'PRICE LIST'!J:J)} -> #N/A | S51: 1
A52: {=XLOOKUP(C52,INV!D:D,INV!I:I)} -> BK106 | B52: English Mystics Musings Soft | C52: ME0004001500 | D52: BOOK | E52: {=XLOOKUP(C52,INV!A:A,INV!K:K)} -> 20 | G52: {=XLOOKUP(C52,SEA!B:B,SEA!Q:Q)} -> 143.5 | H52: {=XLOOKUP(C52,SEA!B:B,SEA!S:S)} -> 0 | I52: =CEILING(G52,S52) -> 144 | J52: =CEILING(H52,S52) -> 0 | K52: {=I52*XLOOKUP(C52,'PRICE LIST'!E:E,'PRICE LIST'!J:J)} -> 0 | L52: {=J52*XLOOKUP(C52,'PRICE LIST'!E:E,'PRICE LIST'!J:J)} -> 0 | M52: {=XLOOKUP(C52,SEA!B:B,SEA!R:R)} | P52: =Q52*J52 -> 0 | Q52: {=E52-XLOOKUP(C52,'PRICE LIST'!E:E,'PRICE LIST'!J:J)} -> 20 | S52: 1
A53: {=XLOOKUP(C53,INV!D:D,INV!I:I)} -> BK137 | B53: English Body The Greatest Gadget | C53: ME0003901500 | D53: BOOK | E53: {=XLOOKUP(C53,INV!A:A,INV!K:K)} -> 7 | G53: {=XLOOKUP(C53,SEA!B:B,SEA!Q:Q)} -> 42.833333 | H53: {=XLOOKUP(C53,SEA!B:B,SEA!S:S)} -> 0 | I53: =CEILING(G53,S53) -> 43 | J53: =CEILING(H53,S53) -> 0 | K53: {=I53*XLOOKUP(C53,'PRICE LIST'!E:E,'PRICE LIST'!J:J)} -> 0 | L53: {=J53*XLOOKUP(C53,'PRICE LIST'!E:E,'PRICE LIST'!J:J)} -> 0 | M53: {=XLOOKUP(C53,SEA!B:B,SEA!R:R)} | P53: =Q53*J53 -> 0 | Q53: {=E53-XLOOKUP(C53,'PRICE LIST'!E:E,'PRICE LIST'!J:J)} -> 7 | S53: 1
A54: {=XLOOKUP(C54,INV!D:D,INV!I:I)} -> BK111 | B54: English Joy 24x7 | C54: ME0002701500 | D54: BOOK | E54: {=XLOOKUP(C54,INV!A:A,INV!K:K)} -> 7 | G54: {=XLOOKUP(C54,SEA!B:B,SEA!Q:Q)} -> 28.5 | H54: {=XLOOKUP(C54,SEA!B:B,SEA!S:S)} -> 0 | I54: =CEILING(G54,S54) -> 29 | J54: =CEILING(H54,S54) -> 0 | K54: {=I54*XLOOKUP(C54,'PRICE LIST'!E:E,'PRICE LIST'!J:J)} -> 0 | L54: {=J54*XLOOKUP(C54,'PRICE LIST'!E:E,'PRICE LIST'!J:J)} -> 0 | M54: {=XLOOKUP(C54,SEA!B:B,SEA!R:R)} | P54: =Q54*J54 -> 0 | Q54: {=E54-XLOOKUP(C54,'PRICE LIST'!E:E,'PRICE LIST'!J:J)} -> 7 | S54: 1
A55: {=XLOOKUP(C55,INV!D:D,INV!I:I)} -> BK136 | B55: English Dont Polish Your Ignorance It may Shine | C55: ME0003601500 | D55: BOOK | E55: {=XLOOKUP(C55,INV!A:A,INV!K:K)} -> 15 | G55: {=XLOOKUP(C55,SEA!B:B,SEA!Q:Q)} -> 19.833333 | H55: {=XLOOKUP(C55,SEA!B:B,SEA!S:S)} -> 0 | I55: =CEILING(G55,S55) -> 20 | J55: =CEILING(H55,S55) -> 0 | K55: {=I55*XLOOKUP(C55,'PRICE LIST'!E:E,'PRICE LIST'!J:J)} -> 0 | L55: {=J55*XLOOKUP(C55,'PRICE LIST'!E:E,'PRICE LIST'!J:J)} -> 0 | M55: {=XLOOKUP(C55,SEA!B:B,SEA!R:R)} | P55: =Q55*J55 -> 0 | Q55: {=E55-XLOOKUP(C55,'PRICE LIST'!E:E,'PRICE LIST'!J:J)} -> 15 | S55: 1
A56: {=XLOOKUP(C56,INV!D:D,INV!I:I)} -> BK115 | B56: English More than a Life English (BK 115) | C56: ME0000501500 | D56: BOOK | E56: {=XLOOKUP(C56,INV!A:A,INV!K:K)} -> 15 | G56: {=XLOOKUP(C56,SEA!B:B,SEA!Q:Q)} -> 16.666667 | H56: {=XLOOKUP(C56,SEA!B:B,SEA!S:S)} -> 0 | I56: =CEILING(G56,S56) -> 17 | J56: =CEILING(H56,S56) -> 0 | K56: {=I56*XLOOKUP(C56,'PRICE LIST'!E:E,'PRICE LIST'!J:J)} -> 0 | L56: {=J56*XLOOKUP(C56,'PRICE LIST'!E:E,'PRICE LIST'!J:J)} -> 0 | M56: {=XLOOKUP(C56,SEA!B:B,SEA!R:R)} | P56: =Q56*J56 -> 0 | Q56: {=E56-XLOOKUP(C56,'PRICE LIST'!E:E,'PRICE LIST'!J:J)} -> 15 | S56: 1
A57: {=XLOOKUP(C57,INV!D:D,INV!I:I)} -> BK156 | B57: A New Beginning Bk (English) | C57: ME0042401500 | D57: BOOK | E57: {=XLOOKUP(C57,INV!A:A,INV!K:K)} -> 15 | G57: {=XLOOKUP(C57,SEA!B:B,SEA!Q:Q)} -> 18.666667 | H57: {=XLOOKUP(C57,SEA!B:B,SEA!S:S)} -> 0 | I57: =CEILING(G57,S57) -> 19 | J57: =CEILING(H57,S57) -> 0 | K57: {=I57*XLOOKUP(C57,'PRICE LIST'!E:E,'PRICE LIST'!J:J)} -> 0 | L57: {=J57*XLOOKUP(C57,'PRICE LIST'!E:E,'PRICE LIST'!J:J)} -> 0 | M57: {=XLOOKUP(C57,SEA!B:B,SEA!R:R)} | P57: =Q57*J57 -> 0 | Q57: {=E57-XLOOKUP(C57,'PRICE LIST'!E:E,'PRICE LIST'!J:J)} -> 15 | S57: 1
A58: {=XLOOKUP(C58,INV!D:D,INV!I:I)} -> BK116 | B58: English Of Mystics and Mistakes | C58: ME0003701500 | D58: BOOK | E58: {=XLOOKUP(C58,INV!A:A,INV!K:K)} -> 15 | G58: {=XLOOKUP(C58,SEA!B:B,SEA!Q:Q)} -> 17.5 | H58: {=XLOOKUP(C58,SEA!B:B,SEA!S:S)} -> 0 | I58: =CEILING(G58,S58) -> 18 | J58: =CEILING(H58,S58) -> 0 | K58: {=I58*XLOOKUP(C58,'PRICE LIST'!E:E,'PRICE LIST'!J:J)} -> 0 | L58: {=J58*XLOOKUP(C58,'PRICE LIST'!E:E,'PRICE LIST'!J:J)} -> 0 | M58: {=XLOOKUP(C58,SEA!B:B,SEA!R:R)} | P58: =Q58*J58 -> 0 | Q58: {=E58-XLOOKUP(C58,'PRICE LIST'!E:E,'PRICE LIST'!J:J)} -> 15 | S58: 1
A59: {=XLOOKUP(C59,INV!D:D,INV!I:I)} -> BK149 | B59: Relationships-Emotion-DualBook | C59: ME0007901500 | D59: BOOK | E59: {=XLOOKUP(C59,INV!A:A,INV!K:K)} -> 15 | G59: {=XLOOKUP(C59,SEA!B:B,SEA!Q:Q)} -> 15.333333 | H59: {=XLOOKUP(C59,SEA!B:B,SEA!S:S)} -> 0 | I59: =CEILING(G59,S59) -> 16 | J59: =CEILING(H59,S59) -> 0 | K59: {=I59*XLOOKUP(C59,'PRICE LIST'!E:E,'PRICE LIST'!J:J)} -> 0 | L59: {=J59*XLOOKUP(C59,'PRICE LIST'!E:E,'PRICE LIST'!J:J)} -> 0 | M59: {=XLOOKUP(C59,SEA!B:B,SEA!R:R)} | P59: =Q59*J59 -> 0 | Q59: {=E59-XLOOKUP(C59,'PRICE LIST'!E:E,'PRICE LIST'!J:J)} -> 15 | S59: 1
A60: {=XLOOKUP(C60,INV!D:D,INV!I:I)} -> BK109 | B60: English Himalayan Lust | C60: ME0003401500 | D60: BOOK | E60: {=XLOOKUP(C60,INV!A:A,INV!K:K)} -> 15 | G60: {=XLOOKUP(C60,SEA!B:B,SEA!Q:Q)} -> 13.666667 | H60: {=XLOOKUP(C60,SEA!B:B,SEA!S:S)} -> 0 | I60: =CEILING(G60,S60) -> 14 | J60: =CEILING(H60,S60) -> 0 | K60: {=I60*XLOOKUP(C60,'PRICE LIST'!E:E,'PRICE LIST'!J:J)} -> 0 | L60: {=J60*XLOOKUP(C60,'PRICE LIST'!E:E,'PRICE LIST'!J:J)} -> 0 | M60: {=XLOOKUP(C60,SEA!B:B,SEA!R:R)} | P60: =Q60*J60 -> 0 | Q60: {=E60-XLOOKUP(C60,'PRICE LIST'!E:E,'PRICE LIST'!J:J)} -> 15 | S60: 1
A61: {=XLOOKUP(C61,INV!D:D,INV!I:I)} -> BK138 | B61: English Ambition to Vision and Greed is God | C61: ME0004401500 | D61: BOOK | E61: {=XLOOKUP(C61,INV!A:A,INV!K:K)} -> 7 | G61: {=XLOOKUP(C61,SEA!B:B,SEA!Q:Q)} -> 23.833333 | H61: {=XLOOKUP(C61,SEA!B:B,SEA!S:S)} -> 0 | I61: =CEILING(G61,S61) -> 24 | J61: =CEILING(H61,S61) -> 0 | K61: {=I61*XLOOKUP(C61,'PRICE LIST'!E:E,'PRICE LIST'!J:J)} -> 0 | L61: {=J61*XLOOKUP(C61,'PRICE LIST'!E:E,'PRICE LIST'!J:J)} -> 0 | M61: {=XLOOKUP(C61,SEA!B:B,SEA!R:R)} | P61: =Q61*J61 -> 0 | Q61: {=E61-XLOOKUP(C61,'PRICE LIST'!E:E,'PRICE LIST'!J:J)} -> 7 | S61: 1
A62: {=XLOOKUP(C62,INV!D:D,INV!I:I)} -> BK154 | B62: Eternal Echoes - A Book Of Poems (1994-2021) | C62: ME0001201500 | D62: BOOK | E62: {=XLOOKUP(C62,INV!A:A,INV!K:K)} -> 25 | G62: {=XLOOKUP(C62,SEA!B:B,SEA!Q:Q)} -> 4.6666667 | H62: {=XLOOKUP(C62,SEA!B:B,SEA!S:S)} -> 0 | I62: =CEILING(G62,S62) -> 5 | J62: =CEILING(H62,S62) -> 0 | K62: {=I62*XLOOKUP(C62,'PRICE LIST'!E:E,'PRICE LIST'!J:J)} -> 0 | L62: {=J62*XLOOKUP(C62,'PRICE LIST'!E:E,'PRICE LIST'!J:J)} -> 0 | M62: {=XLOOKUP(C62,SEA!B:B,SEA!R:R)} | P62: =Q62*J62 -> 0 | Q62: {=E62-XLOOKUP(C62,'PRICE LIST'!E:E,'PRICE LIST'!J:J)} -> 25 | S62: 1
... A72: {=XLOOKUP(C72,INV!D:D,INV!I:I)} -> EX153 | B72: QuotesSromSadhguru-Calendar | C72: HO0074701500 | D72: BOOK | E72: {=XLOOKUP(C72,INV!A:A,INV!K:K)} -> 5 | G72: {=XLOOKUP(C72,SEA!B:B,SEA!Q:Q)} -> 0 | H72: {=XLOOKUP(C72,SEA!B:B,SEA!S:S)} -> 0 | I72: =CEILING(G72,S72) -> 0 | J72: =CEILING(H72,S72) -> 0 | K72: {=I72*XLOOKUP(C72,'PRICE LIST'!E:E,'PRICE LIST'!J:J)} -> 0 | L72: {=J72*XLOOKUP(C72,'PRICE LIST'!E:E,'PRICE LIST'!J:J)} -> 0 | M72: {=XLOOKUP(C72,SEA!B:B,SEA!R:R)} | P72: =Q72*J72 -> 0 | Q72: {=E72-XLOOKUP(C72,'PRICE LIST'!E:E,'PRICE LIST'!J:J)} -> 5 | S72: 1
A73: {=XLOOKUP(C73,INV!D:D,INV!I:I)} -> BC130-LAV | B73: {=XLOOKUP(C73,INV!A:A,INV!B:B)} -> Lavender & Comfrey Soap | C73: BC0007100006 | D73: BOTANIE | E73: {=XLOOKUP(C73,INV!A:A,INV!K:K)} -> 5.5 | F73: DOMESTIC | M73: {=XLOOKUP(C73,SEA!B:B,SEA!R:R)} -> #N/A
A74: {=XLOOKUP(C74,INV!D:D,INV!I:I)} -> BC130-LEM | B74: {=XLOOKUP(C74,INV!A:A,INV!B:B)} -> Bergamot & Lemongrass Soap | C74: BC0007200006 | D74: BOTANIE | E74: {=XLOOKUP(C74,INV!A:A,INV!K:K)} -> 5.5 | F74: DOMESTIC | M74: {=XLOOKUP(C74,SEA!B:B,SEA!R:R)} -> #N/A
A75: {=XLOOKUP(C75,INV!D:D,INV!I:I)} -> BC130-SHEA | B75: {=XLOOKUP(C75,INV!A:A,INV!B:B)} -> Shea Butter & Honey Soap | C75: BC0007400006 | D75: BOTANIE | E75: {=XLOOKUP(C75,INV!A:A,INV!K:K)} -> 5.5 | F75: DOMESTIC | M75: {=XLOOKUP(C75,SEA!B:B,SEA!R:R)} -> #N/A
A76: {=XLOOKUP(C76,INV!D:D,INV!I:I)} -> BC130-TEA | B76: {=XLOOKUP(C76,INV!A:A,INV!B:B)} -> Black Tea Tree Soap | C76: BC0009700006 | D76: BOTANIE | E76: {=XLOOKUP(C76,INV!A:A,INV!K:K)} -> 5.5 | F76: DOMESTIC | M76: {=XLOOKUP(C76,SEA!B:B,SEA!R:R)} -> #N/A
A77: {=XLOOKUP(C77,INV!D:D,INV!I:I)} -> CU823 | B77: Adiyogi Sun Hat - Beige M | C77: CA0155100300 | D77: CLOTHING | E77: {=XLOOKUP(C77,INV!A:A,INV!K:K)} -> 10 | G77: {=XLOOKUP(C77,SEA!B:B,SEA!Q:Q)} -> #N/A | H77: {=XLOOKUP(C77,SEA!B:B,SEA!S:S)} -> #N/A | I77: =CEILING(G77,S77) -> #N/A | J77: =CEILING(H77,S77) -> #N/A | K77: {=I77*XLOOKUP(C77,'PRICE LIST'!E:E,'PRICE LIST'!J:J)} -> #N/A | L77: {=J77*XLOOKUP(C77,'PRICE LIST'!E:E,'PRICE LIST'!J:J)} -> #N/A | M77: {=XLOOKUP(C77,SEA!B:B,SEA!R:R)} -> #N/A | P77: =Q77*J77 -> #N/A | Q77: {=E77-XLOOKUP(C77,'PRICE LIST'!E:E,'PRICE LIST'!J:J)} -> 10 | S77: 1
A78: {=XLOOKUP(C78,INV!D:D,INV!I:I)} -> CU822 | B78: Adiyogi Bucket Hat - Beige M | C78: CA0154900300 | D78: CLOTHING | E78: {=XLOOKUP(C78,INV!A:A,INV!K:K)} -> 10 | G78: {=XLOOKUP(C78,SEA!B:B,SEA!Q:Q)} -> 38 | H78: {=XLOOKUP(C78,SEA!B:B,SEA!S:S)} -> 0 | I78: =CEILING(G78,S78) -> 38 | J78: =CEILING(H78,S78) -> 0 | K78: {=I78*XLOOKUP(C78,'PRICE LIST'!E:E,'PRICE LIST'!J:J)} -> 0 | L78: {=J78*XLOOKUP(C78,'PRICE LIST'!E:E,'PRICE LIST'!J:J)} -> 0 | M78: {=XLOOKUP(C78,SEA!B:B,SEA!R:R)} | P78: =Q78*J78 -> 0 | Q78: {=E78-XLOOKUP(C78,'PRICE LIST'!E:E,'PRICE LIST'!J:J)} -> 10 | S78: 1
A79: {=XLOOKUP(C79,INV!D:D,INV!I:I)} -> CU821 | B79: Adiyogi Bucket Hat - Navy Blue M | C79: CA0154800300 | D79: CLOTHING | E79: {=XLOOKUP(C79,INV!A:A,INV!K:K)} -> 10 | G79: {=XLOOKUP(C79,SEA!B:B,SEA!Q:Q)} -> 9 | H79: {=XLOOKUP(C79,SEA!B:B,SEA!S:S)} -> 0 | I79: =CEILING(G79,S79) -> 9 | J79: =CEILING(H79,S79) -> 0 | K79: {=I79*XLOOKUP(C79,'PRICE LIST'!E:E,'PRICE LIST'!J:J)} -> 0 | L79: {=J79*XLOOKUP(C79,'PRICE LIST'!E:E,'PRICE LIST'!J:J)} -> 0 | M79: {=XLOOKUP(C79,SEA!B:B,SEA!R:R)} | P79: =Q79*J79 -> 0 | Q79: {=E79-XLOOKUP(C79,'PRICE LIST'!E:E,'PRICE LIST'!J:J)} -> 10 | S79: 1
A80: {=XLOOKUP(C80,INV!D:D,INV!I:I)} -> CX822 | B80: Linga-Bhairavi-Kumkum-Brass-Panel | C80: TC0011616900 | D80: CONX | E80: {=XLOOKUP(C80,INV!A:A,INV!K:K)} -> 777 | G80: {=XLOOKUP(C80,SEA!B:B,SEA!Q:Q)} -> 16 | H80: {=XLOOKUP(C80,SEA!B:B,SEA!S:S)} -> 0 | I80: =CEILING(G80,S80) -> 16 | J80: =CEILING(H80,S80) -> 0 | K80: {=I80*XLOOKUP(C80,'PRICE LIST'!E:E,'PRICE LIST'!J:J)} -> 0 | L80: {=J80*XLOOKUP(C80,'PRICE LIST'!E:E,'PRICE LIST'!J:J)} -> 0 | M80: {=XLOOKUP(C80,SEA!B:B,SEA!R:R)} | P80: =Q80*J80 -> 0 | Q80: {=E80-XLOOKUP(C80,'PRICE LIST'!E:E,'PRICE LIST'!J:J)} -> 777 | S80: 1
A81: {=XLOOKUP(C81,INV!D:D,INV!I:I)} -> CX810 | B81: Devi Mukha | C81: TC0017400000 | D81: CONX | E81: {=XLOOKUP(C81,INV!A:A,INV!K:K)} -> 3333 | G81: {=XLOOKUP(C81,SEA!B:B,SEA!Q:Q)} -> 3 | H81: {=XLOOKUP(C81,SEA!B:B,SEA!S:S)} -> 0 | I81: =CEILING(G81,S81) -> 3 | J81: =CEILING(H81,S81) -> 0 | K81: {=I81*XLOOKUP(C81,'PRICE LIST'!E:E,'PRICE LIST'!J:J)} -> 0 | L81: {=J81*XLOOKUP(C81,'PRICE LIST'!E:E,'PRICE LIST'!J:J)} -> 0 | M81: {=XLOOKUP(C81,SEA!B:B,SEA!R:R)} | P81: =Q81*J81 -> 0 | Q81: {=E81-XLOOKUP(C81,'PRICE LIST'!E:E,'PRICE LIST'!J:J)} -> 3333 | S81: 1
A82: {=XLOOKUP(C82,INV!D:D,INV!I:I)} -> CX821 | B82: Jeevarasam | C82: TC0001000000 | D82: CONX | E82: {=XLOOKUP(C82,INV!A:A,INV!K:K)} -> 125 | G82: {=XLOOKUP(C82,SEA!B:B,SEA!Q:Q)} -> 36 | H82: {=XLOOKUP(C82,SEA!B:B,SEA!S:S)} -> 0 | I82: =CEILING(G82,S82) -> 37 | J82: =CEILING(H82,S82) -> 0 | K82: {=I82*XLOOKUP(C82,'PRICE LIST'!E:E,'PRICE LIST'!J:J)} -> 0 | L82: {=J82*XLOOKUP(C82,'PRICE LIST'!E:E,'PRICE LIST'!J:J)} -> 0 | M82: {=XLOOKUP(C82,SEA!B:B,SEA!R:R)} | P82: =Q82*J82 -> 0 | Q82: {=E82-XLOOKUP(C82,'PRICE LIST'!E:E,'PRICE LIST'!J:J)} -> 125 | S82: 1
A83: {=XLOOKUP(C83,INV!D:D,INV!I:I)} -> CX819 | B83: Bhairavi-Raksha | C83: TC0002800300 | D83: CONX | E83: {=XLOOKUP(C83,INV!A:A,INV!K:K)} -> 45 | G83: {=XLOOKUP(C83,SEA!B:B,SEA!Q:Q)} -> 80.916667 | H83: {=XLOOKUP(C83,SEA!B:B,SEA!S:S)} -> 0 | I83: =CEILING(G83,S83) -> 81 | J83: =CEILING(H83,S83) -> 0 | K83: {=I83*XLOOKUP(C83,'PRICE LIST'!E:E,'PRICE LIST'!J:J)} -> 0 | L83: {=J83*XLOOKUP(C83,'PRICE LIST'!E:E,'PRICE LIST'!J:J)} -> 0 | M83: {=XLOOKUP(C83,SEA!B:B,SEA!R:R)} | P83: =Q83*J83 -> 0 | Q83: {=E83-XLOOKUP(C83,'PRICE LIST'!E:E,'PRICE LIST'!J:J)} -> 45 | S83: 1
A84: {=XLOOKUP(C84,INV!D:D,INV!I:I)} -> CX521 | B84: Dhyanalinga-Copper-Pendant | C84: TC0001100009 | D84: CONX | E84: {=XLOOKUP(C84,INV!A:A,INV!K:K)} -> 40 | G84: {=XLOOKUP(C84,SEA!B:B,SEA!Q:Q)} -> 248.66667 | H84: {=XLOOKUP(C84,SEA!B:B,SEA!S:S)} -> 24.416667 | I84: =CEILING(G84,S84) -> 249 | J84: =CEILING(H84,S84) -> 25 | K84: {=I84*XLOOKUP(C84,'PRICE LIST'!E:E,'PRICE LIST'!J:J)} -> 0 | L84: {=J84*XLOOKUP(C84,'PRICE LIST'!E:E,'PRICE LIST'!J:J)} -> 0 | M84: {=XLOOKUP(C84,SEA!B:B,SEA!R:R)} | P84: =Q84*J84 -> 1000 | Q84: {=E84-XLOOKUP(C84,'PRICE LIST'!E:E,'PRICE LIST'!J:J)} -> 40 | S84: 1
A85: {=XLOOKUP(C85,INV!D:D,INV!I:I)} -> CX801 | B85: Isha-Vibhuti | C85: TC0002500000 | D85: CONX | E85: {=XLOOKUP(C85,INV!A:A,INV!K:K)} -> 11 | G85: {=XLOOKUP(C85,SEA!B:B,SEA!Q:Q)} -> 498 | H85: {=XLOOKUP(C85,SEA!B:B,SEA!S:S)} -> 752 | I85: =CEILING(G85,S85) -> 498 | J85: =CEILING(H85,S85) -> 752 | K85: {=I85*XLOOKUP(C85,'PRICE LIST'!E:E,'PRICE LIST'!J:J)} -> 0 | L85: {=J85*XLOOKUP(C85,'PRICE LIST'!E:E,'PRICE LIST'!J:J)} -> 0 | M85: {=XLOOKUP(C85,SEA!B:B,SEA!R:R)} -> X | P85: =Q85*J85 -> 8272 | Q85: {=E85-XLOOKUP(C85,'PRICE LIST'!E:E,'PRICE LIST'!J:J)} -> 11 | S85: 1
A86: {=XLOOKUP(C86,INV!D:D,INV!I:I)} -> CX701 | B86: Linga-Jyoti-Offering-Lamp-Brass/Copper | C86: TC0000900000 | D86: CONX | E86: {=XLOOKUP(C86,INV!A:A,INV!K:K)} -> 65 | G86: {=XLOOKUP(C86,SEA!B:B,SEA!Q:Q)} -> 7 | H86: {=XLOOKUP(C86,SEA!B:B,SEA!S:S)} -> 0 | I86: =CEILING(G86,S86) -> 8 | J86: =CEILING(H86,S86) -> 0 | K86: {=I86*XLOOKUP(C86,'PRICE LIST'!E:E,'PRICE LIST'!J:J)} -> 0 | L86: {=J86*XLOOKUP(C86,'PRICE LIST'!E:E,'PRICE LIST'!J:J)} -> 0 | M86: {=XLOOKUP(C86,SEA!B:B,SEA!R:R)} | P86: =Q86*J86 -> 0 | Q86: {=E86-XLOOKUP(C86,'PRICE LIST'!E:E,'PRICE LIST'!J:J)} -> 65 | S86: 1
A87: {=XLOOKUP(C87,INV!D:D,INV!I:I)} -> CX806 | B87: Devi Shawl Cotton Black Writing | C87: TC0004000200 | D87: CONX | E87: {=XLOOKUP(C87,INV!A:A,INV!K:K)} -> 25 | G87: {=XLOOKUP(C87,SEA!B:B,SEA!Q:Q)} -> 49.333333 | H87: {=XLOOKUP(C87,SEA!B:B,SEA!S:S)} -> 0 | I87: =CEILING(G87,S87) -> 50 | J87: =CEILING(H87,S87) -> 0 | K87: {=I87*XLOOKUP(C87,'PRICE LIST'!E:E,'PRICE LIST'!J:J)} -> 0 | L87: {=J87*XLOOKUP(C87,'PRICE LIST'!E:E,'PRICE LIST'!J:J)} -> 0 | M87: {=XLOOKUP(C87,SEA!B:B,SEA!R:R)} | P87: =Q87*J87 -> 0 | Q87: {=E87-XLOOKUP(C87,'PRICE LIST'!E:E,'PRICE LIST'!J:J)} -> 25 | S87: 1
A88: {=XLOOKUP(C88,INV!D:D,INV!I:I)} -> CX503 | B88: Copper Devi Pendant | C88: TC0003300409 | D88: CONX | E88: {=XLOOKUP(C88,INV!A:A,INV!K:K)} -> 45 | G88: {=XLOOKUP(C88,SEA!B:B,SEA!Q:Q)} -> 60 | H88: {=XLOOKUP(C88,SEA!B:B,SEA!S:S)} -> 90 | I88: =CEILING(G88,S88) -> 60 | J88: =CEILING(H88,S88) -> 90 | K88: {=I88*XLOOKUP(C88,'PRICE LIST'!E:E,'PRICE LIST'!J:J)} -> 0 | L88: {=J88*XLOOKUP(C88,'PRICE LIST'!E:E,'PRICE LIST'!J:J)} -> 0 | M88: {=XLOOKUP(C88,SEA!B:B,SEA!R:R)} | P88: =Q88*J88 -> 4050 | Q88: {=E88-XLOOKUP(C88,'PRICE LIST'!E:E,'PRICE LIST'!J:J)} -> 45 | S88: 1
... A137: {=XLOOKUP(C137,INV!D:D,INV!I:I)} -> CX902 | B137: Adiyogi Sutra | C137: TC0000100000 | D137: CONX | E137: {=XLOOKUP(C137,INV!A:A,INV!K:K)} -> 5 | G137: {=XLOOKUP(C137,SEA!B:B,SEA!Q:Q)} -> 0 | H137: {=XLOOKUP(C137,SEA!B:B,SEA!S:S)} -> 0 | I137: =CEILING(G137,S137) -> 0 | J137: =CEILING(H137,S137) -> 0 | K137: {=I137*XLOOKUP(C137,'PRICE LIST'!E:E,'PRICE LIST'!J:J)} -> 0 | L137: {=J137*XLOOKUP(C137,'PRICE LIST'!E:E,'PRICE LIST'!J:J)} -> 0 | M137: {=XLOOKUP(C137,SEA!B:B,SEA!R:R)} | P137: =Q137*J137 -> 0 | Q137: {=E137-XLOOKUP(C137,'PRICE LIST'!E:E,'PRICE LIST'!J:J)} -> 5 | S137: 1
A138: {=XLOOKUP(C138,INV!D:D,INV!I:I)} -> CX904 | B138: Adiyogi Vastram | C138: TC0000500000 | D138: CONX | E138: {=XLOOKUP(C138,INV!A:A,INV!K:K)} -> 9 | G138: {=XLOOKUP(C138,SEA!B:B,SEA!Q:Q)} -> 0 | H138: {=XLOOKUP(C138,SEA!B:B,SEA!S:S)} -> 0 | I138: =CEILING(G138,S138) -> 0 | J138: =CEILING(H138,S138) -> 0 | M138: {=XLOOKUP(C138,SEA!B:B,SEA!R:R)} | P138: =Q138*J138 -> #N/A | Q138: {=E138-XLOOKUP(C138,'PRICE LIST'!E:E,'PRICE LIST'!J:J)} -> #N/A | S138: 1
A139: {=XLOOKUP(C139,INV!D:D,INV!I:I)} -> CX716 | B139: Gents-Shivanga-pooja-kit-with-Rudraksha-pendant | C139: YS0008416900 | D139: CONX | E139: {=XLOOKUP(C139,INV!A:A,INV!K:K)} -> 25 | G139: {=XLOOKUP(C139,SEA!B:B,SEA!Q:Q)} -> 0 | H139: {=XLOOKUP(C139,SEA!B:B,SEA!S:S)} -> 0 | I139: =CEILING(G139,S139) -> 0 | J139: =CEILING(H139,S139) -> 0 | K139: {=I139*XLOOKUP(C139,'PRICE LIST'!E:E,'PRICE LIST'!J:J)} -> 0 | L139: {=J139*XLOOKUP(C139,'PRICE LIST'!E:E,'PRICE LIST'!J:J)} -> 0 | M139: {=XLOOKUP(C139,SEA!B:B,SEA!R:R)} | P139: =Q139*J139 -> 0 | Q139: {=E139-XLOOKUP(C139,'PRICE LIST'!E:E,'PRICE LIST'!J:J)} -> 25 | S139: 1
A140: {=XLOOKUP(C140,INV!D:D,INV!I:I)} -> CX514-RED | B140: Gold Devi Pendant 4g Red | C140: TC0003105100 | D140: CONX | E140: {=XLOOKUP(C140,INV!A:A,INV!K:K)} -> 1333 | F140: GOLD | H140: {=XLOOKUP(C140,AIR!C:C,AIR!E:E)} -> 13 | I140: =CEILING(G140,S140) -> 0 | J140: =CEILING(H140,S140) -> 13 | K140: {=I140*XLOOKUP(C140,'PRICE LIST'!E:E,'PRICE LIST'!J:J)} -> 0 | L140: {=J140*XLOOKUP(C140,'PRICE LIST'!E:E,'PRICE LIST'!J:J)} -> 0 | P140: =Q140*J140 -> 17329 | Q140: {=E140-XLOOKUP(C140,'PRICE LIST'!E:E,'PRICE LIST'!J:J)} -> 1333 | S140: 1
A141: {=XLOOKUP(C141,INV!D:D,INV!I:I)} -> CX514-SAN | B141: Gold Devi Pendant 4g San | C141: TC0003205700 | D141: CONX | E141: {=XLOOKUP(C141,INV!A:A,INV!K:K)} -> 1333 | F141: GOLD | H141: {=XLOOKUP(C141,AIR!C:C,AIR!E:E)} -> 9.5 | I141: =CEILING(G141,S141) -> 0 | J141: =CEILING(H141,S141) -> 10 | K141: {=I141*XLOOKUP(C141,'PRICE LIST'!E:E,'PRICE LIST'!J:J)} -> 0 | L141: {=J141*XLOOKUP(C141,'PRICE LIST'!E:E,'PRICE LIST'!J:J)} -> 0 | P141: =Q141*J141 -> 13330 | Q141: {=E141-XLOOKUP(C141,'PRICE LIST'!E:E,'PRICE LIST'!J:J)} -> 1333 | S141: 1
A142: {=XLOOKUP(C142,INV!D:D,INV!I:I)} -> CX603-S | B142: Gold Snake Ring (S) | C142: TC0007900200 | D142: CONX | E142: {=XLOOKUP(C142,INV!A:A,INV!K:K)} -> 1777 | F142: GOLD | H142: {=XLOOKUP(C142,AIR!C:C,AIR!E:E)} -> 9.5 | I142: =CEILING(G142,S142) -> 0 | J142: =CEILING(H142,S142) -> 10 | K142: {=I142*XLOOKUP(C142,'PRICE LIST'!E:E,'PRICE LIST'!J:J)} -> 0 | L142: {=J142*XLOOKUP(C142,'PRICE LIST'!E:E,'PRICE LIST'!J:J)} -> 0 | P142: =Q142*J142 -> 17770 | Q142: {=E142-XLOOKUP(C142,'PRICE LIST'!E:E,'PRICE LIST'!J:J)} -> 1777 | S142: 1
A143: {=XLOOKUP(C143,INV!D:D,INV!I:I)} -> CX513-PLN | B143: Gold Devi Pendant 8g Pln | C143: TC0002905200 | D143: CONX | E143: {=XLOOKUP(C143,INV!A:A,INV!K:K)} -> 2333 | F143: GOLD | H143: {=XLOOKUP(C143,AIR!C:C,AIR!E:E)} -> 6.5 | I143: =CEILING(G143,S143) -> 0 | J143: =CEILING(H143,S143) -> 7 | K143: {=I143*XLOOKUP(C143,'PRICE LIST'!E:E,'PRICE LIST'!J:J)} -> 0 | L143: {=J143*XLOOKUP(C143,'PRICE LIST'!E:E,'PRICE LIST'!J:J)} -> 0 | P143: =Q143*J143 -> 16331 | Q143: {=E143-XLOOKUP(C143,'PRICE LIST'!E:E,'PRICE LIST'!J:J)} -> 2333 | S143: 1
A144: {=XLOOKUP(C144,INV!D:D,INV!I:I)} -> CX514-BLK | B144: Gold Devi Pendant 4g Blk | C144: TC0003005100 | D144: CONX | E144: {=XLOOKUP(C144,INV!A:A,INV!K:K)} -> 1333 | F144: GOLD | H144: {=XLOOKUP(C144,AIR!C:C,AIR!E:E)} -> 7.5 | I144: =CEILING(G144,S144) -> 0 | J144: =CEILING(H144,S144) -> 8 | K144: {=I144*XLOOKUP(C144,'PRICE LIST'!E:E,'PRICE LIST'!J:J)} -> 0 | L144: {=J144*XLOOKUP(C144,'PRICE LIST'!E:E,'PRICE LIST'!J:J)} -> 0 | P144: =Q144*J144 -> 10664 | Q144: {=E144-XLOOKUP(C144,'PRICE LIST'!E:E,'PRICE LIST'!J:J)} -> 1333 | S144: 1
A145: {=XLOOKUP(C145,INV!D:D,INV!I:I)} -> CX603-M | B145: Gold Snake Ring (M) | C145: TC0007900300 | D145: CONX | E145: {=XLOOKUP(C145,INV!A:A,INV!K:K)} -> 2033 | F145: GOLD | H145: {=XLOOKUP(C145,AIR!C:C,AIR!E:E)} -> 6.5 | I145: =CEILING(G145,S145) -> 0 | J145: =CEILING(H145,S145) -> 7 | K145: {=I145*XLOOKUP(C145,'PRICE LIST'!E:E,'PRICE LIST'!J:J)} -> 0 | L145: {=J145*XLOOKUP(C145,'PRICE LIST'!E:E,'PRICE LIST'!J:J)} -> 0 | P145: =Q145*J145 -> 14231 | Q145: {=E145-XLOOKUP(C145,'PRICE LIST'!E:E,'PRICE LIST'!J:J)} -> 2033 | S145: 1
A146: {=XLOOKUP(C146,INV!D:D,INV!I:I)} -> CX510-RED | B146: Gold Devi Pendant 8g Red | C146: TC0003105200 | D146: CONX | E146: {=XLOOKUP(C146,INV!A:A,INV!K:K)} -> 2333 | F146: GOLD | H146: {=XLOOKUP(C146,AIR!C:C,AIR!E:E)} -> 4.5 | I146: =CEILING(G146,S146) -> 0 | J146: =CEILING(H146,S146) -> 5 | K146: {=I146*XLOOKUP(C146,'PRICE LIST'!E:E,'PRICE LIST'!J:J)} -> 0 | L146: {=J146*XLOOKUP(C146,'PRICE LIST'!E:E,'PRICE LIST'!J:J)} -> 0 | P146: =Q146*J146 -> 11665 | Q146: {=E146-XLOOKUP(C146,'PRICE LIST'!E:E,'PRICE LIST'!J:J)} -> 2333 | S146: 1
A147: {=XLOOKUP(C147,INV!D:D,INV!I:I)} -> CX510-SAN | B147: Gold Devi Pendant 8g San | C147: TC0003205100 | D147: CONX | E147: {=XLOOKUP(C147,INV!A:A,INV!K:K)} -> 2333 | F147: GOLD | H147: {=XLOOKUP(C147,AIR!C:C,AIR!E:E)} -> 2 | I147: =CEILING(G147,S147) -> 0 | J147: =CEILING(H147,S147) -> 2 | K147: {=I147*XLOOKUP(C147,'PRICE LIST'!E:E,'PRICE LIST'!J:J)} -> 0 | L147: {=J147*XLOOKUP(C147,'PRICE LIST'!E:E,'PRICE LIST'!J:J)} -> 0 | P147: =Q147*J147 -> 4666 | Q147: {=E147-XLOOKUP(C147,'PRICE LIST'!E:E,'PRICE LIST'!J:J)} -> 2333 | S147: 1
A148: {=XLOOKUP(C148,INV!D:D,INV!I:I)} -> CX511-RED | B148: Gold Devi Pendant 16g Red | C148: TC0003105500 | D148: CONX | E148: {=XLOOKUP(C148,INV!A:A,INV!K:K)} -> 4666 | F148: GOLD | H148: {=XLOOKUP(C148,AIR!C:C,AIR!E:E)} -> 2 | I148: =CEILING(G148,S148) -> 0 | J148: =CEILING(H148,S148) -> 2 | K148: {=I148*XLOOKUP(C148,'PRICE LIST'!E:E,'PRICE LIST'!J:J)} -> 0 | L148: {=J148*XLOOKUP(C148,'PRICE LIST'!E:E,'PRICE LIST'!J:J)} -> 0 | P148: =Q148*J148 -> 9332 | Q148: {=E148-XLOOKUP(C148,'PRICE LIST'!E:E,'PRICE LIST'!J:J)} -> 4666 | S148: 1
A149: {=XLOOKUP(C149,INV!D:D,INV!I:I)} -> CX515-RED | B149: Gold Devi Pendant 24g Red | C149: TC0003105700 | D149: CONX | E149: {=XLOOKUP(C149,INV!A:A,INV!K:K)} -> 6999 | F149: GOLD | H149: {=XLOOKUP(C149,AIR!C:C,AIR!E:E)} -> 1.98 | I149: =CEILING(G149,S149) -> 0 | J149: =CEILING(H149,S149) -> 2 | K149: {=I149*XLOOKUP(C149,'PRICE LIST'!E:E,'PRICE LIST'!J:J)} -> 0 | L149: {=J149*XLOOKUP(C149,'PRICE LIST'!E:E,'PRICE LIST'!J:J)} -> 0 | P149: =Q149*J149 -> 13998 | Q149: {=E149-XLOOKUP(C149,'PRICE LIST'!E:E,'PRICE LIST'!J:J)} -> 6999 | S149: 1
A150: {=XLOOKUP(C150,INV!D:D,INV!I:I)} -> CX515-SAN | B150: Gold Devi Pendant 24g San | C150: TC0003205500 | D150: CONX | E150: {=XLOOKUP(C150,INV!A:A,INV!K:K)} -> 6999 | F150: GOLD | H150: {=XLOOKUP(C150,AIR!C:C,AIR!E:E)} -> 1.98 | I150: =CEILING(G150,S150) -> 0 | J150: =CEILING(H150,S150) -> 2 | K150: {=I150*XLOOKUP(C150,'PRICE LIST'!E:E,'PRICE LIST'!J:J)} -> 0 | L150: {=J150*XLOOKUP(C150,'PRICE LIST'!E:E,'PRICE LIST'!J:J)} -> 0 | P150: =Q150*J150 -> 13998 | Q150: {=E150-XLOOKUP(C150,'PRICE LIST'!E:E,'PRICE LIST'!J:J)} -> 6999 | S150: 1
A151: {=XLOOKUP(C151,INV!D:D,INV!I:I)} -> CX824 | B151: Linga-Bhairavi-Kumkum-Silver-Panel | C151: TC0011716900 | D151: CONX | E151: {=XLOOKUP(C151,INV!A:A,INV!K:K)} -> 2555 | F151: SILVER | H151: {=XLOOKUP(C151,AIR!C:C,AIR!E:E)} -> 0 | I151: =CEILING(G151,S151) -> 0 | J151: =CEILING(H151,S151) -> 0 | K151: {=I151*XLOOKUP(C151,'PRICE LIST'!E:E,'PRICE LIST'!J:J)} -> 0 | L151: {=J151*XLOOKUP(C151,'PRICE LIST'!E:E,'PRICE LIST'!J:J)} -> 0 | M151: {=XLOOKUP(C151,SEA!B:B,SEA!R:R)} -> #N/A | P151: =Q151*J151 -> 0 | Q151: {=E151-XLOOKUP(C151,'PRICE LIST'!E:E,'PRICE LIST'!J:J)} -> 2555 | S151: 1
A152: {=XLOOKUP(C152,INV!D:D,INV!I:I)} -> CX825 | B152: Linga-Bhairavi-Turmeric-Silver-Panel | C152: TC0011717000 | D152: CONX | E152: {=XLOOKUP(C152,INV!A:A,INV!K:K)} -> 2555 | F152: SILVER | H152: {=XLOOKUP(C152,AIR!C:C,AIR!E:E)} -> 0 | I152: =CEILING(G152,S152) -> 0 | J152: =CEILING(H152,S152) -> 0 | K152: {=I152*XLOOKUP(C152,'PRICE LIST'!E:E,'PRICE LIST'!J:J)} -> 0 | L152: {=J152*XLOOKUP(C152,'PRICE LIST'!E:E,'PRICE LIST'!J:J)} -> 0 | M152: {=XLOOKUP(C152,SEA!B:B,SEA!R:R)} -> #N/A | P152: =Q152*J152 -> 0 | Q152: {=E152-XLOOKUP(C152,'PRICE LIST'!E:E,'PRICE LIST'!J:J)} -> 2555 | S152: 1
A153: {=XLOOKUP(C153,INV!D:D,INV!I:I)} -> CX511-BLK | B153: Gold Devi Pendant 16g Blk | C153: TC0003005500 | D153: CONX | E153: {=XLOOKUP(C153,INV!A:A,INV!K:K)} -> 4666 | F153: GOLD | H153: {=XLOOKUP(C153,AIR!C:C,AIR!E:E)} -> 1 | I153: =CEILING(G153,S153) -> 0 | J153: =CEILING(H153,S153) -> 1 | K153: {=I153*XLOOKUP(C153,'PRICE LIST'!E:E,'PRICE LIST'!J:J)} -> 0 | L153: {=J153*XLOOKUP(C153,'PRICE LIST'!E:E,'PRICE LIST'!J:J)} -> 0 | P153: =Q153*J153 -> 4666 | Q153: {=E153-XLOOKUP(C153,'PRICE LIST'!E:E,'PRICE LIST'!J:J)} -> 4666 | S153: 1
A154: {=XLOOKUP(C154,INV!D:D,INV!I:I)} -> CX511-SAN | B154: Gold Devi Pendant 16g San | C154: TC0003205200 | D154: CONX | E154: {=XLOOKUP(C154,INV!A:A,INV!K:K)} -> 4666 | F154: GOLD | H154: {=XLOOKUP(C154,AIR!C:C,AIR!E:E)} -> 0 | I154: =CEILING(G154,S154) -> 0 | J154: =CEILING(H154,S154) -> 0 | K154: {=I154*XLOOKUP(C154,'PRICE LIST'!E:E,'PRICE LIST'!J:J)} -> 0 | L154: {=J154*XLOOKUP(C154,'PRICE LIST'!E:E,'PRICE LIST'!J:J)} -> 0 | P154: =Q154*J154 -> 0 | Q154: {=E154-XLOOKUP(C154,'PRICE LIST'!E:E,'PRICE LIST'!J:J)} -> 4666 | S154: 1
A155: {=XLOOKUP(C155,INV!D:D,INV!I:I)} -> CX510-BLK | B155: Gold Devi Pendant 8g Blk | C155: TC0003005200 | D155: CONX | E155: {=XLOOKUP(C155,INV!A:A,INV!K:K)} -> 2333 | F155: GOLD | H155: {=XLOOKUP(C155,AIR!C:C,AIR!E:E)} -> 2 | I155: =CEILING(G155,S155) -> 0 | J155: =CEILING(H155,S155) -> 2 | K155: {=I155*XLOOKUP(C155,'PRICE LIST'!E:E,'PRICE LIST'!J:J)} -> 0 | L155: {=J155*XLOOKUP(C155,'PRICE LIST'!E:E,'PRICE LIST'!J:J)} -> 0 | P155: =Q155*J155 -> 4666 | Q155: {=E155-XLOOKUP(C155,'PRICE LIST'!E:E,'PRICE LIST'!J:J)} -> 2333 | S155: 1
A156: {=XLOOKUP(C156,INV!D:D,INV!I:I)} -> CX603-L | B156: Gold Snake Ring (L) | C156: TC0007900400 | D156: CONX | E156: {=XLOOKUP(C156,INV!A:A,INV!K:K)} -> 2333 | F156: GOLD | H156: {=XLOOKUP(C156,AIR!C:C,AIR!E:E)} -> 0 | I156: =CEILING(G156,S156) -> 0 | J156: =CEILING(H156,S156) -> 0 | K156: {=I156*XLOOKUP(C156,'PRICE LIST'!E:E,'PRICE LIST'!J:J)} -> 0 | L156: {=J156*XLOOKUP(C156,'PRICE LIST'!E:E,'PRICE LIST'!J:J)} -> 0 | P156: =Q156*J156 -> 0 | Q156: {=E156-XLOOKUP(C156,'PRICE LIST'!E:E,'PRICE LIST'!J:J)} -> 2333 | S156: 1
A157: {=XLOOKUP(C157,INV!D:D,INV!I:I)} -> CX508 | B157: Metallic Devi Pendant | C157: TC0003500009 | D157: CONX | E157: {=XLOOKUP(C157,INV!A:A,INV!K:K)} -> 199 | H157: {=XLOOKUP(C157,AIR!C:C,AIR!E:E)} -> 0 | I157: =CEILING(G157,S157) -> 0 | J157: =CEILING(H157,S157) -> 0 | K157: {=I157*XLOOKUP(C157,'PRICE LIST'!E:E,'PRICE LIST'!J:J)} -> 0 | L157: {=J157*XLOOKUP(C157,'PRICE LIST'!E:E,'PRICE LIST'!J:J)} -> 0 | M157: {=XLOOKUP(C157,SEA!B:B,SEA!R:R)} -> #N/A | P157: =Q157*J157 -> 0 | Q157: {=E157-XLOOKUP(C157,'PRICE LIST'!E:E,'PRICE LIST'!J:J)} -> 199 | S157: 1
A158: {=XLOOKUP(C158,INV!D:D,INV!I:I)} -> CX506 | B158: Silver Devi Pendant (M) | C158: TC0003400309 | D158: CONX | E158: {=XLOOKUP(C158,INV!A:A,INV!K:K)} -> 122 | F158: SILVER | H158: {=XLOOKUP(C158,AIR!C:C,AIR!E:E)} -> 0 | I158: =CEILING(G158,S158) -> 0 | J158: =CEILING(H158,S158) -> 0 | K158: {=I158*XLOOKUP(C158,'PRICE LIST'!E:E,'PRICE LIST'!J:J)} -> 0 | L158: {=J158*XLOOKUP(C158,'PRICE LIST'!E:E,'PRICE LIST'!J:J)} -> 0 | M158: {=XLOOKUP(C158,SEA!B:B,SEA!R:R)} -> #N/A | P158: =Q158*J158 -> 0 | Q158: {=E158-XLOOKUP(C158,'PRICE LIST'!E:E,'PRICE LIST'!J:J)} -> 122 | S158: 1
A159: {=XLOOKUP(C159,INV!D:D,INV!I:I)} -> CX205 | B159: Adiyogi rudraksha with silver chain | C159: CA0118300000 | D159: CONX | E159: {=XLOOKUP(C159,INV!A:A,INV!K:K)} -> 112 | F159: SILVER | H159: {=XLOOKUP(C159,AIR!C:C,AIR!E:E)} -> 4 | I159: =CEILING(G159,S159) -> 0 | J159: =CEILING(H159,S159) -> 4 | K159: {=I159*XLOOKUP(C159,'PRICE LIST'!E:E,'PRICE LIST'!J:J)} -> 0 | L159: {=J159*XLOOKUP(C159,'PRICE LIST'!E:E,'PRICE LIST'!J:J)} -> 0 | M159: {=XLOOKUP(C159,SEA!B:B,SEA!R:R)} -> #N/A | P159: =Q159*J159 -> 448 | Q159: {=E159-XLOOKUP(C159,'PRICE LIST'!E:E,'PRICE LIST'!J:J)} -> 112 | S159: 1
A160: {=XLOOKUP(C160,INV!D:D,INV!I:I)} -> CX505 | B160: Silver Devi Pendant (S) | C160: TC0003400209 | D160: CONX | E160: {=XLOOKUP(C160,INV!A:A,INV!K:K)} -> 111 | F160: SILVER | H160: {=XLOOKUP(C160,AIR!C:C,AIR!E:E)} -> 0 | I160: =CEILING(G160,S160) -> 0 | J160: =CEILING(H160,S160) -> 0 | K160: {=I160*XLOOKUP(C160,'PRICE LIST'!E:E,'PRICE LIST'!J:J)} -> 0 | L160: {=J160*XLOOKUP(C160,'PRICE LIST'!E:E,'PRICE LIST'!J:J)} -> 0 | M160: {=XLOOKUP(C160,SEA!B:B,SEA!R:R)} -> #N/A | P160: =Q160*J160 -> 0 | Q160: {=E160-XLOOKUP(C160,'PRICE LIST'!E:E,'PRICE LIST'!J:J)} -> 111 | S160: 1
...

Sheet UNIQUE
A1: NAME | B1: SKU | C1: CAT | D1: ORDER | E1: MON SALES | F1: INV ON HAND | G1: MONTHS ON HAND | H1: MIN MOH | I1: QTY ORDER | J1: ROUND | K1: CASE
A2: Devi-Camphor | B2: HO0072400000 | C2: TEMPLE | D2: 12 | E2: {=XLOOKUP(B2,SALES!A:A,SALES!E:E)/12} -> 464.25 | F2: {=XLOOKUP(B2,INV!A:A,INV!G:G)} -> 3722 | G2: =F2/E2 -> 8.0172321 | H2: 9 | I2: =D2*E2 -> 5571 | J2: =CEILING(I2,K2) -> 5580 | K2: 60
A3: Camphor-Bhuta-Shuddhi-3-month-supply | B3: YS0007500000 | C3: YOGA STORE | D3: =IF(G3<H3,12,0) -> 12 | E3: {=XLOOKUP(B3,SALES!A:A,SALES!E:E)/12} -> 199 | F3: {=XLOOKUP(B3,INV!A:A,INV!G:G)} -> 1386 | G3: =F3/E3 -> 6.9648241 | H3: 9 | I3: =D3*E3 -> 2388 | J3: =CEILING(I3,K3) -> 2400 | K3: 100
A4: Herbal-Toothpaste | B4: BC0000706002 | C4: BODY CARE | D4: 24 | E4: 100 | F4: {=XLOOKUP(B4,INV!A:A,INV!G:G)} -> 0 | G4: =F4/E4 -> 0 | H4: 9 | I4: =D4*E4 -> 2400 | J4: =CEILING(I4,K4) -> 0
A5: Herbal-Toothpaste | B5: BC0000706502 | C5: BODY CARE | D5: 24 | E5: {=XLOOKUP(B5,SALES!A:A,SALES!E:E)/12} -> 335.66667 | F5: {=XLOOKUP(B5,INV!A:A,INV!G:G)} -> 510 | G5: =F5/E5 -> 1.5193644 | H5: 9 | I5: =D5*E5 -> 8056 | J5: =CEILING(I5,K5) -> 0
A14: WHEN ORDERING CAMPHOR WE MUST CHECK WITH TEMPLE TEAM IF THEY ALSO WANT TO ORDER THE BIG ROUND CAMPHOR ALONG WITH US
A15: THE INDIAN SKU FOR THAT IS 0119730

Sheet BLOOM
A1: NAME | B1: SKU | C1: CAT | D1: QTY SEA ROUND | E1: QTY AIR ROUND | F1: MON SALES | G1: MOH | H1: MIN MOH | I1: SEA | J1: QTY SEA | K1: AIR | L1: QTY AIR | M1: CASE SIZE
A2: Saffron & Sandalwood Certified Organic Refreshing Shower Gel - 30ml (Bloom) | B2: BC0002403002 | C2: BODY CARE | D2: =CEILING(J2,M2) -> #N/A | E2: =CEILING(L2,M2) -> #N/A | F2: {=XLOOKUP(B2,SALES!A:A,SALES!E:E)/12} -> 46.166667 | G2: {=XLOOKUP(B2,'EXP INV'!Q:Q,'EXP INV'!R:R)} -> #N/A | H2: 8 | I2: =IF(G2<H2,10,0) -> #N/A | J2: =I2*F2 -> #N/A | K2: =IF(G2-5<0,3,0) -> #N/A | L2: =K2*F2 -> #N/A | M2: 32
A3: Saffron & Sandalwood Certified Organic Refreshing Shower Gel - 200ml (Bloom) - Cosmos Organic certified by Ecocert Greenlife | B3: BC0002403302 | C3: BODY CARE | D3: =CEILING(J3,M3) -> #N/A | E3: =CEILING(L3,M3) -> #N/A | F3: {=XLOOKUP(B3,SALES!A:A,SALES!E:E)/12} -> 66.916667 | G3: {=XLOOKUP(B3,'EXP INV'!Q:Q,'EXP INV'!R:R)} -> #N/A | H3: 8 | I3: =IF(G3<H3,10,0) -> #N/A | J3: =I3*F3 -> #N/A | K3: =IF(G3-5<0,3,0) -> #N/A | L3: =K3*F3 -> #N/A | M3: 24
A4: Hibiscus & Aloe Vera Organic Moisturizing Body Lotion - 30ml (Bloom) | B4: BC0002603002 | C4: BODY CARE | D4: =CEILING(J4,M4) -> #N/A | E4: =CEILING(L4,M4) -> #N/A | F4: {=XLOOKUP(B4,SALES!A:A,SALES!E:E)/12} -> 20.25 | G4: {=XLOOKUP(B4,'EXP INV'!Q:Q,'EXP INV'!R:R)} -> #N/A | H4: 8 | I4: =IF(G4<H4,10,0) -> #N/A | J4: =I4*F4 -> #N/A | K4: =IF(G4-5<0,3,0) -> #N/A | L4: =K4*F4 -> #N/A | M4: 32
A5: Hibiscus & Aloe Vera Organic Moisturizing Body Lotion - 100ml (Bloom) | B5: BC0002603102 | C5: BODY CARE | D5: =CEILING(J5,M5) -> #N/A | E5: =CEILING(L5,M5) -> #N/A | F5: {=XLOOKUP(B5,SALES!A:A,SALES!E:E)/12} -> 40.916667 | G5: {=XLOOKUP(B5,'EXP INV'!Q:Q,'EXP INV'!R:R)} -> #N/A | H5: 8 | I5: =IF(G5<H5,10,0) -> #N/A | J5: =I5*F5 -> #N/A | K5: =IF(G5-5<0,3,0) -> #N/A | L5: =K5*F5 -> #N/A | M5: 24
A6: US Bloom 24 Hours Organic Body Lotion (Extra Dry Skin) (100 ml) | B6: BC0002703102 | C6: BODY CARE | D6: =CEILING(J6,M6) -> #N/A | E6: =CEILING(L6,M6) -> #N/A | F6: {=XLOOKUP(B6,SALES!A:A,SALES!E:E)/12} -> 29.833333 | G6: {=XLOOKUP(B6,'EXP INV'!Q:Q,'EXP INV'!R:R)} -> #N/A | H6: 8 | I6: =IF(G6<H6,10,0) -> #N/A | J6: =I6*F6 -> #N/A | K6: =IF(G6-5<0,3,0) -> #N/A | L6: =K6*F6 -> #N/A | M6: 24
A7: US Bloom Refreshing & Age Defence Shower Gel (200 ml) | B7: BC0002803302 | C7: BODY CARE | D7: =CEILING(J7,M7) -> #N/A | E7: =CEILING(L7,M7) -> #N/A | F7: {=XLOOKUP(B7,SALES!A:A,SALES!E:E)/12} -> 14.416667 | G7: {=XLOOKUP(B7,'EXP INV'!Q:Q,'EXP INV'!R:R)} -> #N/A | H7: 8 | I7: =IF(G7<H7,10,0) -> #N/A | J7: =I7*F7 -> #N/A | K7: =IF(G7-5<0,3,0) -> #N/A | L7: =K7*F7 -> #N/A | M7: 24
A8: Neem & Tulsi Certified Organic Cleansing Face Wash - 30ml (Bloom) | B8: BC0002903002 | C8: BODY CARE | D8: =CEILING(J8,M8) -> #N/A | E8: =CEILING(L8,M8) -> #N/A | F8: {=XLOOKUP(B8,SALES!A:A,SALES!E:E)/12} -> 17 | G8: {=XLOOKUP(B8,'EXP INV'!Q:Q,'EXP INV'!R:R)} -> #N/A | H8: 8 | I8: =IF(G8<H8,10,0) -> #N/A | J8: =I8*F8 -> #N/A | K8: =IF(G8-5<0,3,0) -> #N/A | L8: =K8*F8 -> #N/A | M8: 32
A9: Neem & Tulsi Certified Organic Cleansing Face Wash - 100ml (Bloom) | B9: BC0002903102 | C9: BODY CARE | D9: =CEILING(J9,M9) -> #N/A | E9: =CEILING(L9,M9) -> #N/A | F9: {=XLOOKUP(B9,SALES!A:A,SALES!E:E)/12} -> 44.833333 | G9: {=XLOOKUP(B9,'EXP INV'!Q:Q,'EXP INV'!R:R)} -> #N/A | H9: 8 | I9: =IF(G9<H9,10,0) -> #N/A | J9: =I9*F9 -> #N/A | K9: =IF(G9-5<0,3,0) -> #N/A | L9: =K9*F9 -> #N/A | M9: 24
A10: Sandalwood and Turmeric Face Wash 30ml (Bloom) | B10: BC0003003002 | C10: BODY CARE | D10: =CEILING(J10,M10) -> #N/A | E10: =CEILING(L10,M10) -> #N/A | F10: {=XLOOKUP(B10,SALES!A:A,SALES!E:E)/12} -> 24.166667 | G10: {=XLOOKUP(B10,'EXP INV'!Q:Q,'EXP INV'!R:R)} -> #N/A | H10: 8 | I10: =IF(G10<H10,10,0) -> #N/A | J10: =I10*F10 -> #N/A | K10: =IF(G10-5<0,3,0) -> #N/A | L10: =K10*F10 -> #N/A | M10: 32
A11: Sandalwood and Turmeric Face Wash 100 ml (Bloom) | B11: BC0003003102 | C11: BODY CARE | D11: =CEILING(J11,M11) -> #N/A | E11: =CEILING(L11,M11) -> #N/A | F11: {=XLOOKUP(B11,SALES!A:A,SALES!E:E)/12} -> 40.333333 | G11: {=XLOOKUP(B11,'EXP INV'!Q:Q,'EXP INV'!R:R)} -> #N/A | H11: 8 | I11: =IF(G11<H11,10,0) -> #N/A | J11: =I11*F11 -> #N/A | K11: =IF(G11-5<0,3,0) -> #N/A | L11: =K11*F11 -> #N/A | M11: 24
A12: Shikakai & Jatamansi Certified Organic Strengthening Shampoo - 30ml (Bloom) | B12: BC0003503002 | C12: BODY CARE | D12: =CEILING(J12,M12) -> #N/A | E12: =CEILING(L12,M12) -> #N/A | F12: {=XLOOKUP(B12,SALES!A:A,SALES!E:E)/12} -> 28.5 | G12: {=XLOOKUP(B12,'EXP INV'!Q:Q,'EXP INV'!R:R)} -> #N/A | H12: 8 | I12: =IF(G12<H12,10,0) -> #N/A | J12: =I12*F12 -> #N/A | K12: =IF(G12-5<0,3,0) -> #N/A | L12: =K12*F12 -> #N/A | M12: 32
A13: Shikakai & Jatamansi Certified Organic Strengthening Shampoo - 200ml (Bloom) | B13: BC0003503302 | C13: BODY CARE | D13: =CEILING(J13,M13) -> #N/A | E13: =CEILING(L13,M13) -> #N/A | F13: {=XLOOKUP(B13,SALES!A:A,SALES!E:E)/12} -> 83.666667 | G13: {=XLOOKUP(B13,'EXP INV'!Q:Q,'EXP INV'!R:R)} -> #N/A | H13: 8 | I13: =IF(G13<H13,10,0) -> #N/A | J13: =I13*F13 -> #N/A | K13: =IF(G13-5<0,3,0) -> #N/A | L13: =K13*F13 -> #N/A | M13: 24
... A18: US Bloom Extra Nourishment & Protection Organic Shampoo (200 ml) | B18: BC0004203302 | C18: BODY CARE | D18: =CEILING(J18,M18) -> #N/A | E18: =CEILING(L18,M18) -> #N/A | F18: {=XLOOKUP(B18,SALES!A:A,SALES!E:E)/12} -> 22.333333 | G18: {=XLOOKUP(B18,'EXP INV'!Q:Q,'EXP INV'!R:R)} -> #N/A | H18: 8 | I18: =IF(G18<H18,10,0) -> #N/A | J18: =I18*F18 -> #N/A | K18: =IF(G18-5<0,3,0) -> #N/A | L18: =K18*F18 -> #N/A | M18: 24

Sheet AIR
A1: # | B1: NAME | C1: SKU | D1: CAT | E1: ORDER | F1: CAT | G1: MONTHLY SALES | H1: INV ON HAND | I1: MONTHS ON HAND | J1: MIN MOH | K1: ROUND | L1: CASE
A2: 1 | B2: Bhoomi-Bhuta-Shuddhi-3-month-supply | C2: YS0008305502 | D2: YOGA STORE | E2: =IF(J2-I2>0,(J2-I2)*G2,0) -> 820.66667 | F2: BHOOMI | G2: {=XLOOKUP(C2,SALES!A:A,SALES!E:E)/12} -> 205.33333 | H2: {=XLOOKUP(C2,INV!A:A,INV!G:G)} -> 206 | I2: =H2/G2 -> 1.0032468 | J2: 5 | K2: =ceiling(E2,L2) -> 840 | L2: 60
A3: 2 | B3: Gold Devi Pendant 16g Blk | C3: TC0003005500 | D3: CONX | E3: =IF((J3-I3)>0,(J3-I3)*G3,0) -> 1 | F3: GOLD | G3: {=XLOOKUP(C3,SALES!A:A,SALES!E:E)/12} -> 0.16666667 | H3: {=XLOOKUP(C3,INV!A:A,INV!G:G)} -> 0 | I3: =H3/G3 -> 0 | J3: 6 | K3: =CEILING(E3,1) -> 1 | L3: 1
A4: 3 | B4: Gold Devi Pendant 16g Red | C4: TC0003105500 | D4: CONX | E4: =IF((J4-I4)>0,(J4-I4)*G4,0) -> 2 | F4: GOLD | G4: {=XLOOKUP(C4,SALES!A:A,SALES!E:E)/12} -> 0.33333333 | H4: {=XLOOKUP(C4,INV!A:A,INV!G:G)} -> 0 | I4: =H4/G4 -> 0 | J4: 6 | K4: =CEILING(E4,1) -> 2 | L4: 1
A5: 4 | B5: Gold Devi Pendant 16g San | C5: TC0003205200 | D5: CONX | E5: =IF((J5-I5)>0,(J5-I5)*G5,0) -> 0 | F5: GOLD | G5: {=XLOOKUP(C5,SALES!A:A,SALES!E:E)/12} -> 0.33333333 | H5: {=XLOOKUP(C5,INV!A:A,INV!G:G)} -> 5 | I5: =H5/G5 -> 15 | J5: 6 | K5: =CEILING(E5,1) -> 0 | L5: 1
A6: 5 | B6: Gold Devi Pendant 24g Red | C6: TC0003105700 | D6: CONX | E6: =IF((J6-I6)>0,(J6-I6)*G6,0) -> 1.98 | F6: GOLD | G6: 0.33 | H6: {=XLOOKUP(C6,INV!A:A,INV!G:G)} -> 0 | I6: =H6/G6 -> 0 | J6: 6 | K6: =CEILING(E6,1) -> 2 | L6: 1
A7: 6 | B7: Gold Devi Pendant 24g San | C7: TC0003205500 | D7: CONX | E7: =IF((J7-I7)>0,(J7-I7)*G7,0) -> 1.98 | F7: GOLD | G7: 0.33 | H7: {=XLOOKUP(C7,INV!A:A,INV!G:G)} -> 0 | I7: =H7/G7 -> 0 | J7: 6 | K7: =CEILING(E7,1) -> 2 | L7: 1
A8: 7 | B8: Gold Devi Pendant 4g Blk | C8: TC0003005100 | D8: CONX | E8: =IF((J8-I8)>0,(J8-I8)*G8,0) -> 7.5 | F8: GOLD | G8: {=XLOOKUP(C8,SALES!A:A,SALES!E:E)/12} -> 1.25 | H8: {=XLOOKUP(C8,INV!A:A,INV!G:G)} -> 0 | I8: =H8/G8 -> 0 | J8: 6 | K8: =CEILING(E8,1) -> 8 | L8: 1
A9: 8 | B9: Gold Devi Pendant 4g Red | C9: TC0003105100 | D9: CONX | E9: =IF((J9-I9)>0,(J9-I9)*G9,0) -> 13 | F9: GOLD | G9: {=XLOOKUP(C9,SALES!A:A,SALES!E:E)/12} -> 2.1666667 | H9: {=XLOOKUP(C9,INV!A:A,INV!G:G)} -> 0 | I9: =H9/G9 -> 0 | J9: 6 | K9: =CEILING(E9,1) -> 13 | L9: 1
A10: 9 | B10: Gold Devi Pendant 4g San | C10: TC0003205700 | D10: CONX | E10: =IF((J10-I10)>0,(J10-I10)*G10,0) -> 9.5 | F10: GOLD | G10: {=XLOOKUP(C10,SALES!A:A,SALES!E:E)/12} -> 1.5833333 | H10: {=XLOOKUP(C10,INV!A:A,INV!G:G)} -> 0 | I10: =H10/G10 -> 0 | J10: 6 | K10: =CEILING(E10,1) -> 10 | L10: 1
A11: 10 | B11: Gold Devi Pendant 8g Blk | C11: TC0003005200 | D11: CONX | E11: =IF((J11-I11)>0,(J11-I11)*G11,0) -> 2 | F11: GOLD | G11: {=XLOOKUP(C11,SALES!A:A,SALES!E:E)/12} -> 0.5 | H11: {=XLOOKUP(C11,INV!A:A,INV!G:G)} -> 1 | I11: =H11/G11 -> 2 | J11: 6 | K11: =CEILING(E11,1) -> 2 | L11: 1
A12: 11 | B12: Gold Devi Pendant 8g Pln | C12: TC0002905200 | D12: CONX | E12: =IF((J12-I12)>0,(J12-I12)*G12,0) -> 6.5 | F12: GOLD | G12: {=XLOOKUP(C12,SALES!A:A,SALES!E:E)/12} -> 1.0833333 | H12: {=XLOOKUP(C12,INV!A:A,INV!G:G)} -> 0 | I12: =H12/G12 -> 0 | J12: 6 | K12: =CEILING(E12,1) -> 7 | L12: 1
A13: 12 | B13: Gold Devi Pendant 8g Red | C13: TC0003105200 | D13: CONX | E13: =IF((J13-I13)>0,(J13-I13)*G13,0) -> 4.5 | F13: GOLD | G13: {=XLOOKUP(C13,SALES!A:A,SALES!E:E)/12} -> 0.58333333 | H13: {=XLOOKUP(C13,INV!A:A,INV!G:G)} -> -1 | I13: =H13/G13 -> -1.7142857 | J13: 6 | K13: =CEILING(E13,1) -> 5 | L13: 1
A14: 13 | B14: Gold Devi Pendant 8g San | C14: TC0003205100 | D14: CONX | E14: =IF((J14-I14)>0,(J14-I14)*G14,0) -> 2 | F14: GOLD | G14: {=XLOOKUP(C14,SALES!A:A,SALES!E:E)/12} -> 0.33333333 | H14: {=XLOOKUP(C14,INV!A:A,INV!G:G)} -> 0 | I14: =H14/G14 -> 0 | J14: 6 | K14: =CEILING(E14,1) -> 2 | L14: 1
A15: 14 | B15: Gold Snake Ring (L) | C15: TC0007900400 | D15: CONX | E15: =IF((J15-I15)>0,(J15-I15)*G15,0) -> 0 | F15: GOLD | G15: {=XLOOKUP(C15,SALES!A:A,SALES!E:E)/12} -> 0.91666667 | H15: {=XLOOKUP(C15,INV!A:A,INV!G:G)} -> 8 | I15: =H15/G15 -> 8.7272727 | J15: 6 | K15: =CEILING(E15,1) -> 0 | L15: 1
A16: 15 | B16: Gold Snake Ring (M) | C16: TC0007900300 | D16: CONX | E16: =IF((J16-I16)>0,(J16-I16)*G16,0) -> 6.5 | F16: GOLD | G16: {=XLOOKUP(C16,SALES!A:A,SALES!E:E)/12} -> 1.0833333 | H16: {=XLOOKUP(C16,INV!A:A,INV!G:G)} -> 0 | I16: =H16/G16 -> 0 | J16: 6 | K16: =CEILING(E16,1) -> 7 | L16: 1
A17: 16 | B17: Gold Snake Ring (S) | C17: TC0007900200 | D17: CONX | E17: =IF((J17-I17)>0,(J17-I17)*G17,0) -> 9.5 | F17: GOLD | G17: {=XLOOKUP(C17,SALES!A:A,SALES!E:E)/12} -> 1.5833333 | H17: {=XLOOKUP(C17,INV!A:A,INV!G:G)} -> 0 | I17: =H17/G17 -> 0 | J17: 6 | K17: =CEILING(E17,1) -> 10 | L17: 1
A18: 17 | B18: Adiyogi-Ear-Rings-Silver | C18: CA0023000009 | D18: JEWELRY | E18: =IF((J18-I18)>0,(J18-I18)*G18,0) -> 0 | F18: SILVER | G18: {=XLOOKUP(C18,SALES!A:A,SALES!E:E)/12} -> 13.916667 | H18: {=XLOOKUP(C18,INV!A:A,INV!G:G)} -> 253 | I18: =H18/G18 -> 18.179641 | J18: 6 | K18: =CEILING(E18,1) -> 0 | L18: 1
A19: 18 | B19: Linga-Bhairavi-Chain-Silver | C19: CA0036000009 | D19: TEMPLE | E19: =IF((J19-I19)>0,(J19-I19)*G19,0) -> 0 | F19: SILVER | G19: {=XLOOKUP(C19,SALES!A:A,SALES!E:E)/12} -> 15.75 | H19: {=XLOOKUP(C19,INV!A:A,INV!G:G)} -> 247 | I19: =H19/G19 -> 15.68254 | J19: 6 | K19: =CEILING(E19,1) -> 0 | L19: 1
... A23: 22 | B23: Pure Silver (999) Aum Namahshivaya silver cuff | C23: CA0120000000 | D23: JEWELRY | E23: =IF((J23-I23)>0,(J23-I23)*G23,0) -> 0 | F23: SILVER | G23: {=XLOOKUP(C23,SALES!A:A,SALES!E:E)/12} -> 2.5833333 | H23: {=XLOOKUP(C23,INV!A:A,INV!G:G)} -> 142 | I23: =H23/G23 -> 54.967742 | J23: 6 | K23: =CEILING(E23,1) -> 0 | L23: 1
A24: 23 | B24: Antique hammered silver cuff | C24: CA0191600009 | D24: JEWELRY | E24: =IF((J24-I24)>0,(J24-I24)*G24,0) -> 0 | F24: SILVER | G24: 2 | H24: {=XLOOKUP(C24,INV!A:A,INV!G:G)} -> 46 | I24: =H24/G24 -> 23 | J24: 6 | K24: =CEILING(E24,1) -> 0 | L24: 1
A25: 24 | B25: Silver Sarpa earring | C25: CA0191900009 | D25: JEWELRY | E25: =IF((J25-I25)>0,(J25-I25)*G25,0) -> 35 | F25: SILVER | G25: 11 | H25: {=XLOOKUP(C25,INV!A:A,INV!G:G)} -> 31 | I25: =H25/G25 -> 2.8181818 | J25: 6 | K25: =CEILING(E25,1) -> 35 | L25: 1
A26: 25 | B26: Silver Devi Pendant (S) | C26: TC0003400209 | D26: CONX | E26: =IF((J26-I26)>0,(J26-I26)*G26,0) -> 0 | F26: SILVER | G26: {=XLOOKUP(C26,SALES!A:A,SALES!E:E)/12} -> 18.75 | H26: {=XLOOKUP(C26,INV!A:A,INV!G:G)} -> 633 | I26: =H26/G26 -> 33.76 | J26: 9 | K26: =CEILING(E26,1) -> 0 | L26: 1
A27: 26 | B27: Silver Devi Pendant (M) | C27: TC0003400309 | D27: CONX | E27: =IF((J27-I27)>0,(J27-I27)*G27,0) -> 0 | F27: SILVER | G27: {=XLOOKUP(C27,SALES!A:A,SALES!E:E)/12} -> 8.75 | H27: {=XLOOKUP(C27,INV!A:A,INV!G:G)} -> 494 | I27: =H27/G27 -> 56.457143 | J27: 9 | K27: =CEILING(E27,1) -> 0 | L27: 1
A28: 27 | B28: Linga-Bhairavi-Kumkum-Silver-Panel | C28: TC0011716900 | D28: CONX | E28: =IF((J28-I28)>0,(J28-I28)*G28,0) -> 0 | F28: SILVER | G28: {=XLOOKUP(C28,SALES!A:A,SALES!E:E)/12} -> 0.25 | H28: {=XLOOKUP(C28,INV!A:A,INV!G:G)} -> 20 | I28: =H28/G28 -> 80 | J28: 6 | K28: =CEILING(E28,1) -> 0 | L28: 1
A29: 28 | B29: Linga-Bhairavi-Turmeric-Silver-Panel | C29: TC0011717000 | D29: CONX | E29: =IF((J29-I29)>0,(J29-I29)*G29,0) -> 0 | F29: SILVER | G29: {=XLOOKUP(C29,SALES!A:A,SALES!E:E)/12} -> 0.33333333 | H29: {=XLOOKUP(C29,INV!A:A,INV!G:G)} -> 27 | I29: =H29/G29 -> 81 | J29: 6 | K29: =CEILING(E29,1) -> 0 | L29: 1
A30: 29 | B30: Metallic Devi Pendant | C30: TC0003500009 | D30: CONX | E30: =IF((J30-I30)>0,(J30-I30)*G30,0) -> 0 | F30: SILVER | G30: {=XLOOKUP(C30,SALES!A:A,SALES!E:E)/12} -> 24 | H30: {=XLOOKUP(C30,INV!A:A,INV!G:G)} -> 446 | I30: =H30/G30 -> 18.583333 | J30: 9 | K30: =CEILING(E30,1) -> 0 | L30: 1
A31: 30 | B31: Silver Snake Ring (S) | C31: TC0002200209 | D31: CONX | E31: =IF(I31<J31,12*G31,0) -> 0 | F31: SILVER | G31: =SUM('SN CALCS'!E15:E18) -> 4.8333333 | H31: {=xlookup(C31,INV!A:A,INV!G:G)+sum('SN CALCS'!F15:F18)} -> 187 | I31: =H31/G31 -> 38.689655 | J31: 6 | K31: =CEILING(E31,1) -> 0 | L31: 1
A32: 31 | B32: Silver Snake Ring (M) | C32: TC0002200309 | D32: CONX | E32: =IF(I32<J32,12*G32,0) -> 0 | F32: SILVER | G32: =SUM('SN CALCS'!E19:E20) -> 13.333333 | H32: {=xlookup(C32,INV!A:A,INV!G:G)+sum('SN CALCS'!F19:F20)} -> 483 | I32: =H32/G32 -> 36.225 | J32: 6 | K32: =CEILING(E32,1) -> 0 | L32: 1
A33: 32 | B33: Silver Snake Ring (L) | C33: TC0002200409 | D33: CONX | E33: =IF(I33<J33,12*G33,0) -> 0 | F33: SILVER | G33: =SUM('SN CALCS'!E21:E22) -> 19.333333 | H33: {=xlookup(C33,INV!A:A,INV!G:G)+sum('SN CALCS'!F21:F22)} -> 376 | I33: =H33/G33 -> 19.448276 | J33: 6 | K33: =CEILING(E33,1) -> 0 | L33: 1
A34: 33 | B34: Silver Snake Ring (XL) | C34: TC0002200509 | D34: CONX | E34: =IF(I34<J34,12*G34,0) -> 0 | F34: SILVER | G34: =SUM('SN CALCS'!E23:E24) -> 13.666667 | H34: {=xlookup(C34,INV!A:A,INV!G:G)+sum('SN CALCS'!F23:F24)} -> 417 | I34: =H34/G34 -> 30.512195 | J34: 6 | K34: =CEILING(E34,1) -> 0 | L34: 1
A35: 34 | B35: Silver Snake Ring (XXL) | C35: TC0002200609 | D35: CONX | E35: =IF(I35<J35,12*G35,0) -> 0 | F35: SILVER | G35: =SUM('SN CALCS'!E25:E27) -> 3.8333333 | H35: {=xlookup(C35,INV!A:A,INV!G:G)+SUM('SN CALCS'!F25:F27)} -> 219 | I35: =H35/G35 -> 57.130435 | J35: 6 | K35: =CEILING(E35,1) -> 0 | L35: 1

Sheet SEA
A1: Product/Name | B1: GLOBAL SKU | C1: CATEGORY | D1: ORDER LIST ? | E1: NOTES | F1: MON SALES | G1: INV OH | H1: MOH | I1: QTY REQ | J1: MTHS REQ | K1: OH MTH 1 | L1: OH MTH 2 | M1: OH MTH 3 | N1: OH MTH 4 | O1: OH MTH 5 | P1: OH MTH 6 | Q1: SEA QTY | R1: AIR SHIP? | S1: AIR QTY | T1: SEA SHIP | U1: AIR SHIP | V1: +1 MOH INC | W1: +2 MOH INC | X1: +3 MOH INC | Y1: +4 MOH INC | Z1: +5 MOH INC | AA1: +6 MOH INC
A2: Sanjeevini Health Mix 17.6oz | B2: NF0006106902 | C2: NATURAL FOOD | D2: {=XLOOKUP(B2,'ORDER LIST'!C:C,'ORDER LIST'!B:B)} -> Sanjeevini Health Mix 17.6oz | F2: {=XLOOKUP(B2,SALES!A:A,SALES!C:C)} -> 457.66667 | G2: =F2*H2 -> #N/A | H2: {=XLOOKUP(B2,'EXP INV'!Q:Q,'EXP INV'!R:R)} -> #N/A | I2: =F2*J2 -> 3661.3333 | J2: 8 | K2: =IF((H2-1+V2)<0,0,H2-1+V2) -> #N/A | L2: =IF((K2-1+W2)<0,0,K2-1+W2) -> #N/A | M2: =IF((L2-1+X2)<0,0,L2-1+X2) -> #N/A | N2: =IF((M2-1+Y2)<0,0,M2-1+Y2) -> #N/A | O2: =IF((N2-1+Z2)<0,0,N2-1+Z2) -> #N/A | P2: =IF((O2-1+AA2)<0,0,O2-1+AA2) -> #N/A | Q2: =T2*F2 -> #N/A | R2: X | S2: =U2*F2 -> #N/A | T2: =IF(P2<J2,J2-P2,0) -> #N/A | U2: =IF(N2<3,3-N2,0) -> #N/A | V2: {=iferror(XLOOKUP(B2,'INC INV'!AJ:AJ,'INC INV'!AL:AL)/F2,0)} -> 0 | W2: {=IFERROR(XLOOKUP(B2,'INC INV'!AP:AP,'INC INV'!AR:AR)/F2,0)} -> 0 | X2: {=IFERROR(XLOOKUP(B2,'INC INV'!AV:AV,'INC INV'!AX:AX)/F2,0)} -> 0 | Y2: {=IFERROR(XLOOKUP(B2,'INC INV'!BB:BB,'INC INV'!BD:BD)/F2,0)} -> 3.6970138 | Z2: {=IFERROR(XLOOKUP(B2,'INC INV'!BH:BH,'INC INV'!BJ:BJ)/F2,0)} -> 0 | AA2: {=IFERROR(XLOOKUP(B2,'INC INV'!BN:BN,'INC INV'!BP:BP)/F2,0)} -> 0
A3: Instant Sanjeevini 21oz | B3: NF0006207002 | C3: NATURAL FOOD | D3: {=XLOOKUP(B3,'ORDER LIST'!C:C,'ORDER LIST'!B:B)} -> Instant Sanjeevini 21oz | F3: {=XLOOKUP(B3,SALES!A:A,SALES!C:C)} -> 235.5 | G3: =F3*H3 -> #N/A | H3: {=XLOOKUP(B3,'EXP INV'!Q:Q,'EXP INV'!R:R)} -> #N/A | I3: =F3*J3 -> 1884 | J3: 8 | K3: =IF((H3-1+V3)<0,0,H3-1+V3) -> #N/A | L3: =IF((K3-1+W3)<0,0,K3-1+W3) -> #N/A | M3: =IF((L3-1+X3)<0,0,L3-1+X3) -> #N/A | N3: =IF((M3-1+Y3)<0,0,M3-1+Y3) -> #N/A | O3: =IF((N3-1+Z3)<0,0,N3-1+Z3) -> #N/A | P3: =IF((O3-1+AA3)<0,0,O3-1+AA3) -> #N/A | Q3: =T3*F3 -> #N/A | R3: X | S3: =U3*F3 -> #N/A | T3: =IF(P3<J3,J3-P3,0) -> #N/A | U3: =IF(N3<3,3-N3,0) -> #N/A | V3: {=iferror(XLOOKUP(B3,'INC INV'!AJ:AJ,'INC INV'!AL:AL)/F3,0)} -> 0 | W3: {=IFERROR(XLOOKUP(B3,'INC INV'!AP:AP,'INC INV'!AR:AR)/F3,0)} -> 0 | X3: {=IFERROR(XLOOKUP(B3,'INC INV'!AV:AV,'INC INV'!AX:AX)/F3,0)} -> 0 | Y3: {=IFERROR(XLOOKUP(B3,'INC INV'!BB:BB,'INC INV'!BD:BD)/F3,0)} -> 0.58598726 | Z3: {=IFERROR(XLOOKUP(B3,'INC INV'!BH:BH,'INC INV'!BJ:BJ)/F3,0)} -> 0 | AA3: {=IFERROR(XLOOKUP(B3,'INC INV'!BN:BN,'INC INV'!BP:BP)/F3,0)} -> 0
A4: Devi-Car-Hanging | B4: ME0018900000 | C4: ACCESSORY | F4: {=XLOOKUP(B4,SALES!A:A,SALES!C:C)} -> 67.25 | G4: {=XLOOKUP(B4,INV!A:A,INV!G:G)} -> 11 | H4: =IF(G4/F4<0,0,G4/F4) -> 0.16356877 | I4: =F4*J4 -> 403.5 | J4: 6 | K4: =IF((H4-1+V4)<0,0,H4-1+V4) -> 0 | L4: =IF((K4-1+W4)<0,0,K4-1+W4) -> 2.1821561 | M4: =IF((L4-1+X4)<0,0,L4-1+X4) -> 1.1821561 | N4: =IF((M4-1+Y4)<0,0,M4-1+Y4) -> 5.5204461 | O4: =IF((N4-1+Z4)<0,0,N4-1+Z4) -> 5.0408922 | P4: =IF((O4-1+AA4)<0,0,O4-1+AA4) -> 4.0408922 | Q4: =T4*F4 -> 131.75 | S4: =U4*F4 -> 0 | T4: =IF(P4<J4,J4-P4,0) -> 1.9591078 | U4: =IF(N4<3,3-N4,0) -> 0 | V4: {=iferror(XLOOKUP(B4,'INC INV'!AJ:AJ,'INC INV'!AL:AL)/F4,0)} -> 0 | W4: {=IFERROR(XLOOKUP(B4,'INC INV'!AP:AP,'INC INV'!AR:AR)/F4,0)} -> 3.1821561 | X4: {=IFERROR(XLOOKUP(B4,'INC INV'!AV:AV,'INC INV'!AX:AX)/F4,0)} -> 0 | Y4: {=IFERROR(XLOOKUP(B4,'INC INV'!BB:BB,'INC INV'!BD:BD)/F4,0)} -> 5.33829 | Z4: {=IFERROR(XLOOKUP(B4,'INC INV'!BH:BH,'INC INV'!BJ:BJ)/F4,0)} -> 0.5204461 | AA4: {=IFERROR(XLOOKUP(B4,'INC INV'!BN:BN,'INC INV'!BP:BP)/F4,0)} -> 0
A5: Adiyogi miniature 2" car stand - Black | B5: ME0037600000 | C5: ACCESSORY | F5: {=XLOOKUP(B5,SALES!A:A,SALES!C:C)} -> 50.416667 | G5: {=XLOOKUP(B5,INV!A:A,INV!G:G)} -> 0 | H5: =IF(G5/F5<0,0,G5/F5) -> 0 | I5: =F5*J5 -> 302.5 | J5: 6 | K5: =IF((H5-1+V5)<0,0,H5-1+V5) -> 0 | L5: =IF((K5-1+W5)<0,0,K5-1+W5) -> 1.8165289 | M5: =IF((L5-1+X5)<0,0,L5-1+X5) -> 0.81652893 | N5: =IF((M5-1+Y5)<0,0,M5-1+Y5) -> 5.4495868 | O5: =IF((N5-1+Z5)<0,0,N5-1+Z5) -> 5.0446281 | P5: =IF((O5-1+AA5)<0,0,O5-1+AA5) -> 4.0446281 | Q5: =T5*F5 -> 98.583333 | S5: =U5*F5 -> 0 | T5: =IF(P5<J5,J5-P5,0) -> 1.9553719 | U5: =IF(N5<3,3-N5,0) -> 0 | V5: {=iferror(XLOOKUP(B5,'INC INV'!AJ:AJ,'INC INV'!AL:AL)/F5,0)} -> 0 | W5: {=IFERROR(XLOOKUP(B5,'INC INV'!AP:AP,'INC INV'!AR:AR)/F5,0)} -> 2.8165289 | X5: {=IFERROR(XLOOKUP(B5,'INC INV'!AV:AV,'INC INV'!AX:AX)/F5,0)} -> 0 | Y5: {=IFERROR(XLOOKUP(B5,'INC INV'!BB:BB,'INC INV'!BD:BD)/F5,0)} -> 5.6330579 | Z5: {=IFERROR(XLOOKUP(B5,'INC INV'!BH:BH,'INC INV'!BJ:BJ)/F5,0)} -> 0.59504132 | AA5: {=IFERROR(XLOOKUP(B5,'INC INV'!BN:BN,'INC INV'!BP:BP)/F5,0)} -> 0
A6: Jasmine Orient Solid Perfume | B6: BC0001005100 | C6: BODY CARE | D6: {=XLOOKUP(B6,'ORDER LIST'!C:C,'ORDER LIST'!B:B)} -> Jasmine Orient Solid Perfume | F6: {=XLOOKUP(B6,SALES!A:A,SALES!C:C)} -> 82.5 | G6: {=XLOOKUP(B6,INV!A:A,INV!G:G)} -> 1 | H6: =IF(G6/F6<0,0,G6/F6) -> 0.012121212 | I6: =F6*J6 -> 660 | J6: 8 | K6: =IF((H6-1+V6)<0,0,H6-1+V6) -> 0 | L6: =IF((K6-1+W6)<0,0,K6-1+W6) -> 9.3757576 | M6: =IF((L6-1+X6)<0,0,L6-1+X6) -> 8.3757576 | N6: =IF((M6-1+Y6)<0,0,M6-1+Y6) -> 9.169697 | O6: =IF((N6-1+Z6)<0,0,N6-1+Z6) -> 8.169697 | P6: =IF((O6-1+AA6)<0,0,O6-1+AA6) -> 7.169697 | Q6: =T6*F6 -> 68.5 | S6: =U6*F6 -> 0 | T6: =IF(P6<J6,J6-P6,0) -> 0.83030303 | U6: =IF(N6<3,3-N6,0) -> 0 | V6: {=iferror(XLOOKUP(B6,'INC INV'!AJ:AJ,'INC INV'!AL:AL)/F6,0)} -> 0 | W6: {=IFERROR(XLOOKUP(B6,'INC INV'!AP:AP,'INC INV'!AR:AR)/F6,0)} -> 10.375758 | X6: {=IFERROR(XLOOKUP(B6,'INC INV'!AV:AV,'INC INV'!AX:AX)/F6,0)} -> 0 | Y6: {=IFERROR(XLOOKUP(B6,'INC INV'!BB:BB,'INC INV'!BD:BD)/F6,0)} -> 1.7939394 | Z6: {=IFERROR(XLOOKUP(B6,'INC INV'!BH:BH,'INC INV'!BJ:BJ)/F6,0)} -> 0 | AA6: {=IFERROR(XLOOKUP(B6,'INC INV'!BN:BN,'INC INV'!BP:BP)/F6,0)} -> 0
A7: Copper Devi Pendant | B7: TC0003300409 | C7: CONX | E7: L, HOLDING OFF ORDERING BECAUSE WE HAVE SO MUCH STOCK OF THE S AND M, M IS DISCONTINUED | F7: 30 | G7: {=XLOOKUP(B7,INV!A:A,INV!G:G)} -> 0 | H7: =IF(G7/F7<0,0,G7/F7) -> 0 | I7: =F7*J7 -> 300 | J7: 10 | K7: =IF((H7-1+V7)<0,0,H7-1+V7) -> 0 | L7: =IF((K7-1+W7)<0,0,K7-1+W7) -> 0 | M7: =IF((L7-1+X7)<0,0,L7-1+X7) -> 0 | N7: =IF((M7-1+Y7)<0,0,M7-1+Y7) -> 0 | O7: =IF((N7-1+Z7)<0,0,N7-1+Z7) -> 9 | P7: =IF((O7-1+AA7)<0,0,O7-1+AA7) -> 8 | Q7: =T7*F7 -> 60 | S7: =U7*F7 -> 90 | T7: =IF(P7<J7,J7-P7,0) -> 2 | U7: =IF(N7<3,3-N7,0) -> 3 | V7: {=iferror(XLOOKUP(B7,'INC INV'!AJ:AJ,'INC INV'!AL:AL)/F7,0)} -> 0 | W7: {=IFERROR(XLOOKUP(B7,'INC INV'!AP:AP,'INC INV'!AR:AR)/F7,0)} -> 0 | X7: {=IFERROR(XLOOKUP(B7,'INC INV'!AV:AV,'INC INV'!AX:AX)/F7,0)} -> 0 | Y7: {=IFERROR(XLOOKUP(B7,'INC INV'!BB:BB,'INC INV'!BD:BD)/F7,0)} -> 0.033333333 | Z7: {=IFERROR(XLOOKUP(B7,'INC INV'!BH:BH,'INC INV'!BJ:BJ)/F7,0)} -> 10 | AA7: {=IFERROR(XLOOKUP(B7,'INC INV'!BN:BN,'INC INV'!BP:BP)/F7,0)} -> 0
A8: Instant Sanjeevini 20 kg Bag | B8: NF0006220902 | C8: NATURAL FOOD | F8: 6 | G8: {=XLOOKUP(B8,INV!A:A,INV!G:G)} -> 0 | H8: =IF(G8/F8<0,0,G8/F8) -> 0 | I8: =F8*J8 -> 48 | J8: 8 | K8: =IF((H8-1+V8)<0,0,H8-1+V8) -> 0 | L8: =IF((K8-1+W8)<0,0,K8-1+W8) -> 0 | M8: =IF((L8-1+X8)<0,0,L8-1+X8) -> 0 | N8: =IF((M8-1+Y8)<0,0,M8-1+Y8) -> 0 | O8: =IF((N8-1+Z8)<0,0,N8-1+Z8) -> 0 | P8: =IF((O8-1+AA8)<0,0,O8-1+AA8) -> 0 | Q8: =T8*F8 -> 48 | S8: =U8*F8 -> 18 | T8: =IF(P8<J8,J8-P8,0) -> 8 | U8: =IF(N8<3,3-N8,0) -> 3 | V8: {=iferror(XLOOKUP(B8,'INC INV'!AJ:AJ,'INC INV'!AL:AL)/F8,0)} -> 0 | W8: {=IFERROR(XLOOKUP(B8,'INC INV'!AP:AP,'INC INV'!AR:AR)/F8,0)} -> 0 | X8: {=IFERROR(XLOOKUP(B8,'INC INV'!AV:AV,'INC INV'!AX:AX)/F8,0)} -> 0 | Y8: {=IFERROR(XLOOKUP(B8,'INC INV'!BB:BB,'INC INV'!BD:BD)/F8,0)} -> 0 | Z8: {=IFERROR(XLOOKUP(B8,'INC INV'!BH:BH,'INC INV'!BJ:BJ)/F8,0)} -> 0 | AA8: {=IFERROR(XLOOKUP(B8,'INC INV'!BN:BN,'INC INV'!BP:BP)/F8,0)} -> 0
A9: Relax Solid Perfume | B9: BC0001205100 | C9: BODY CARE | D9: {=XLOOKUP(B9,'ORDER LIST'!C:C,'ORDER LIST'!B:B)} -> Relax Solid Perfume | F9: {=XLOOKUP(B9,SALES!A:A,SALES!C:C)} -> 41.75 | G9: {=XLOOKUP(B9,INV!A:A,INV!G:G)} -> -3 | H9: =IF(G9/F9<0,0,G9/F9) -> 0 | I9: =F9*J9 -> 334 | J9: 8 | K9: =IF((H9-1+V9)<0,0,H9-1+V9) -> 0 | L9: =IF((K9-1+W9)<0,0,K9-1+W9) -> 10.065868 | M9: =IF((L9-1+X9)<0,0,L9-1+X9) -> 9.0658683 | N9: =IF((M9-1+Y9)<0,0,M9-1+Y9) -> 9.1676647 | O9: =IF((N9-1+Z9)<0,0,N9-1+Z9) -> 8.1676647 | P9: =IF((O9-1+AA9)<0,0,O9-1+AA9) -> 7.1676647 | Q9: =T9*F9 -> 34.75 | S9: =U9*F9 -> 0 | T9: =IF(P9<J9,J9-P9,0) -> 0.83233533 | U9: =IF(N9<3,3-N9,0) -> 0 | V9: {=iferror(XLOOKUP(B9,'INC INV'!AJ:AJ,'INC INV'!AL:AL)/F9,0)} -> 0 | W9: {=IFERROR(XLOOKUP(B9,'INC INV'!AP:AP,'INC INV'!AR:AR)/F9,0)} -> 11.065868 | X9: {=IFERROR(XLOOKUP(B9,'INC INV'!AV:AV,'INC INV'!AX:AX)/F9,0)} -> 0 | Y9: {=IFERROR(XLOOKUP(B9,'INC INV'!BB:BB,'INC INV'!BD:BD)/F9,0)} -> 1.1017964 | Z9: {=IFERROR(XLOOKUP(B9,'INC INV'!BH:BH,'INC INV'!BJ:BJ)/F9,0)} -> 0 | AA9: {=IFERROR(XLOOKUP(B9,'INC INV'!BN:BN,'INC INV'!BP:BP)/F9,0)} -> 0
A10: Adiyogi Bucket Hat - Navy Blue L | B10: CA0154800400 | C10: ACCESSORY | F10: 15 | G10: 0 | H10: =IF(G10/F10<0,0,G10/F10) -> 0 | I10: =F10*J10 -> 90 | J10: 6 | K10: =IF((H10-1+V10)<0,0,H10-1+V10) -> 0 | L10: =IF((K10-1+W10)<0,0,K10-1+W10) -> 0 | M10: =IF((L10-1+X10)<0,0,L10-1+X10) -> 0 | N10: =IF((M10-1+Y10)<0,0,M10-1+Y10) -> 0 | O10: =IF((N10-1+Z10)<0,0,N10-1+Z10) -> 5 | P10: =IF((O10-1+AA10)<0,0,O10-1+AA10) -> 4 | Q10: =T10*F10 -> 30 | S10: =U10*F10 -> 45 | T10: =IF(P10<J10,J10-P10,0) -> 2 | U10: =IF(N10<3,3-N10,0) -> 3 | V10: {=iferror(XLOOKUP(B10,'INC INV'!AJ:AJ,'INC INV'!AL:AL)/F10,0)} -> 0 | W10: {=IFERROR(XLOOKUP(B10,'INC INV'!AP:AP,'INC INV'!AR:AR)/F10,0)} -> 0 | X10: {=IFERROR(XLOOKUP(B10,'INC INV'!AV:AV,'INC INV'!AX:AX)/F10,0)} -> 0 | Y10: {=IFERROR(XLOOKUP(B10,'INC INV'!BB:BB,'INC INV'!BD:BD)/F10,0)} -> 0 | Z10: {=IFERROR(XLOOKUP(B10,'INC INV'!BH:BH,'INC INV'!BJ:BJ)/F10,0)} -> 6 | AA10: {=IFERROR(XLOOKUP(B10,'INC INV'!BN:BN,'INC INV'!BP:BP)/F10,0)} -> 0
A11: Adiyogi Bucket Hat - Beige L | B11: CA0154900400 | C11: ACCESSORY | F11: 15 | G11: 0 | H11: =IF(G11/F11<0,0,G11/F11) -> 0 | I11: =F11*J11 -> 90 | J11: 6 | K11: =IF((H11-1+V11)<0,0,H11-1+V11) -> 0 | L11: =IF((K11-1+W11)<0,0,K11-1+W11) -> 0 | M11: =IF((L11-1+X11)<0,0,L11-1+X11) -> 0 | N11: =IF((M11-1+Y11)<0,0,M11-1+Y11) -> 0 | O11: =IF((N11-1+Z11)<0,0,N11-1+Z11) -> 5 | P11: =IF((O11-1+AA11)<0,0,O11-1+AA11) -> 4 | Q11: =T11*F11 -> 30 | S11: =U11*F11 -> 45 | T11: =IF(P11<J11,J11-P11,0) -> 2 | U11: =IF(N11<3,3-N11,0) -> 3 | V11: {=iferror(XLOOKUP(B11,'INC INV'!AJ:AJ,'INC INV'!AL:AL)/F11,0)} -> 0 | W11: {=IFERROR(XLOOKUP(B11,'INC INV'!AP:AP,'INC INV'!AR:AR)/F11,0)} -> 0 | X11: {=IFERROR(XLOOKUP(B11,'INC INV'!AV:AV,'INC INV'!AX:AX)/F11,0)} -> 0 | Y11: {=IFERROR(XLOOKUP(B11,'INC INV'!BB:BB,'INC INV'!BD:BD)/F11,0)} -> 0 | Z11: {=IFERROR(XLOOKUP(B11,'INC INV'!BH:BH,'INC INV'!BJ:BJ)/F11,0)} -> 6 | AA11: {=IFERROR(XLOOKUP(B11,'INC INV'!BN:BN,'INC INV'!BP:BP)/F11,0)} -> 0
A12: Devi Journal (Tree free Banana Paper) | B12: HO0108200000 | C12: ACCESSORY | F12: 15 | G12: 0 | H12: =IF(G12/F12<0,0,G12/F12) -> 0 | I12: =F12*J12 -> 90 | J12: 6 | K12: =IF((H12-1+V12)<0,0,H12-1+V12) -> 0 | L12: =IF((K12-1+W12)<0,0,K12-1+W12) -> 0 | M12: =IF((L12-1+X12)<0,0,L12-1+X12) -> 0 | N12: =IF((M12-1+Y12)<0,0,M12-1+Y12) -> 5 | O12: =IF((N12-1+Z12)<0,0,N12-1+Z12) -> 5 | P12: =IF((O12-1+AA12)<0,0,O12-1+AA12) -> 4 | Q12: =T12*F12 -> 30 | S12: =U12*F12 -> 0 | T12: =IF(P12<J12,J12-P12,0) -> 2 | U12: =IF(N12<3,3-N12,0) -> 0 | V12: {=iferror(XLOOKUP(B12,'INC INV'!AJ:AJ,'INC INV'!AL:AL)/F12,0)} -> 0 | W12: {=IFERROR(XLOOKUP(B12,'INC INV'!AP:AP,'INC INV'!AR:AR)/F12,0)} -> 0 | X12: {=IFERROR(XLOOKUP(B12,'INC INV'!AV:AV,'INC INV'!AX:AX)/F12,0)} -> 0 | Y12: {=IFERROR(XLOOKUP(B12,'INC INV'!BB:BB,'INC INV'!BD:BD)/F12,0)} -> 6 | Z12: {=IFERROR(XLOOKUP(B12,'INC INV'!BH:BH,'INC INV'!BJ:BJ)/F12,0)} -> 1 | AA12: {=IFERROR(XLOOKUP(B12,'INC INV'!BN:BN,'INC INV'!BP:BP)/F12,0)} -> 0
A13: Copper Mug with Handle, 414 ml | B13: YS0002300002 | C13: COPPER | F13: 15 | G13: 0 | H13: =IF(G13/F13<0,0,G13/F13) -> 0 | I13: =F13*J13 -> 120 | J13: 8 | K13: =IF((H13-1+V13)<0,0,H13-1+V13) -> 0 | L13: =IF((K13-1+W13)<0,0,K13-1+W13) -> 0 | M13: =IF((L13-1+X13)<0,0,L13-1+X13) -> 0 | N13: =IF((M13-1+Y13)<0,0,M13-1+Y13) -> 7 | O13: =IF((N13-1+Z13)<0,0,N13-1+Z13) -> 7 | P13: =IF((O13-1+AA13)<0,0,O13-1+AA13) -> 6 | Q13: =T13*F13 -> 30 | S13: =U13*F13 -> 0 | T13: =IF(P13<J13,J13-P13,0) -> 2 | U13: =IF(N13<3,3-N13,0) -> 0 | V13: {=iferror(XLOOKUP(B13,'INC INV'!AJ:AJ,'INC INV'!AL:AL)/F13,0)} -> 0 | W13: {=IFERROR(XLOOKUP(B13,'INC INV'!AP:AP,'INC INV'!AR:AR)/F13,0)} -> 0 | X13: {=IFERROR(XLOOKUP(B13,'INC INV'!AV:AV,'INC INV'!AX:AX)/F13,0)} -> 0 | Y13: {=IFERROR(XLOOKUP(B13,'INC INV'!BB:BB,'INC INV'!BD:BD)/F13,0)} -> 8 | Z13: {=IFERROR(XLOOKUP(B13,'INC INV'!BH:BH,'INC INV'!BJ:BJ)/F13,0)} -> 1 | AA13: {=IFERROR(XLOOKUP(B13,'INC INV'!BN:BN,'INC INV'!BP:BP)/F13,0)} -> 0
A14: Traditional Copper Drinkware Pot Style 2 | B14: YS0018200000 | C14: COPPER | F14: 15 | G14: 0 | H14: =IF(G14/F14<0,0,G14/F14) -> 0 | I14: =F14*J14 -> 120 | J14: 8 | K14: =IF((H14-1+V14)<0,0,H14-1+V14) -> 0 | L14: =IF((K14-1+W14)<0,0,K14-1+W14) -> 0 | M14: =IF((L14-1+X14)<0,0,L14-1+X14) -> 0 | N14: =IF((M14-1+Y14)<0,0,M14-1+Y14) -> 7 | O14: =IF((N14-1+Z14)<0,0,N14-1+Z14) -> 7 | P14: =IF((O14-1+AA14)<0,0,O14-1+AA14) -> 6 | Q14: =T14*F14 -> 30 | S14: =U14*F14 -> 0 | T14: =IF(P14<J14,J14-P14,0) -> 2 | U14: =IF(N14<3,3-N14,0) -> 0 | V14: {=iferror(XLOOKUP(B14,'INC INV'!AJ:AJ,'INC INV'!AL:AL)/F14,0)} -> 0 | W14: {=IFERROR(XLOOKUP(B14,'INC INV'!AP:AP,'INC INV'!AR:AR)/F14,0)} -> 0 | X14: {=IFERROR(XLOOKUP(B14,'INC INV'!AV:AV,'INC INV'!AX:AX)/F14,0)} -> 0 | Y14: {=IFERROR(XLOOKUP(B14,'INC INV'!BB:BB,'INC INV'!BD:BD)/F14,0)} -> 8 | Z14: {=IFERROR(XLOOKUP(B14,'INC INV'!BH:BH,'INC INV'!BJ:BJ)/F14,0)} -> 1 | AA14: {=IFERROR(XLOOKUP(B14,'INC INV'!BN:BN,'INC INV'!BP:BP)/F14,0)} -> 0
A15: Copper Sipper Bottle - 700 Ml | B15: YS0018400000 | C15: COPPER | F15: 15 | G15: 0 | H15: =IF(G15/F15<0,0,G15/F15) -> 0 | I15: =F15*J15 -> 120 | J15: 8 | K15: =IF((H15-1+V15)<0,0,H15-1+V15) -> 0 | L15: =IF((K15-1+W15)<0,0,K15-1+W15) -> 0 | M15: =IF((L15-1+X15)<0,0,L15-1+X15) -> 0 | N15: =IF((M15-1+Y15)<0,0,M15-1+Y15) -> 7 | O15: =IF((N15-1+Z15)<0,0,N15-1+Z15) -> 7 | P15: =IF((O15-1+AA15)<0,0,O15-1+AA15) -> 6 | Q15: =T15*F15 -> 30 | S15: =U15*F15 -> 0 | T15: =IF(P15<J15,J15-P15,0) -> 2 | U15: =IF(N15<3,3-N15,0) -> 0 | V15: {=iferror(XLOOKUP(B15,'INC INV'!AJ:AJ,'INC INV'!AL:AL)/F15,0)} -> 0 | W15: {=IFERROR(XLOOKUP(B15,'INC INV'!AP:AP,'INC INV'!AR:AR)/F15,0)} -> 0 | X15: {=IFERROR(XLOOKUP(B15,'INC INV'!AV:AV,'INC INV'!AX:AX)/F15,0)} -> 0 | Y15: {=IFERROR(XLOOKUP(B15,'INC INV'!BB:BB,'INC INV'!BD:BD)/F15,0)} -> 8 | Z15: {=IFERROR(XLOOKUP(B15,'INC INV'!BH:BH,'INC INV'!BJ:BJ)/F15,0)} -> 1 | AA15: {=IFERROR(XLOOKUP(B15,'INC INV'!BN:BN,'INC INV'!BP:BP)/F15,0)} -> 0
A16: Copper Water Bottle 350 ml (Hammered) | B16: YS0018900000 | C16: COPPER | F16: 15 | G16: 0 | H16: =IF(G16/F16<0,0,G16/F16) -> 0 | I16: =F16*J16 -> 120 | J16: 8 | K16: =IF((H16-1+V16)<0,0,H16-1+V16) -> 0 | L16: =IF((K16-1+W16)<0,0,K16-1+W16) -> 0 | M16: =IF((L16-1+X16)<0,0,L16-1+X16) -> 0 | N16: =IF((M16-1+Y16)<0,0,M16-1+Y16) -> 7 | O16: =IF((N16-1+Z16)<0,0,N16-1+Z16) -> 7 | P16: =IF((O16-1+AA16)<0,0,O16-1+AA16) -> 6 | Q16: =T16*F16 -> 30 | S16: =U16*F16 -> 0 | T16: =IF(P16<J16,J16-P16,0) -> 2 | U16: =IF(N16<3,3-N16,0) -> 0 | V16: {=iferror(XLOOKUP(B16,'INC INV'!AJ:AJ,'INC INV'!AL:AL)/F16,0)} -> 0 | W16: {=IFERROR(XLOOKUP(B16,'INC INV'!AP:AP,'INC INV'!AR:AR)/F16,0)} -> 0 | X16: {=IFERROR(XLOOKUP(B16,'INC INV'!AV:AV,'INC INV'!AX:AX)/F16,0)} -> 0 | Y16: {=IFERROR(XLOOKUP(B16,'INC INV'!BB:BB,'INC INV'!BD:BD)/F16,0)} -> 8 | Z16: {=IFERROR(XLOOKUP(B16,'INC INV'!BH:BH,'INC INV'!BJ:BJ)/F16,0)} -> 1 | AA16: {=IFERROR(XLOOKUP(B16,'INC INV'!BN:BN,'INC INV'!BP:BP)/F16,0)} -> 0
A17: Copper Vibhuti Box (Small) - Padam | B17: HO0108417000 | C17: TEMPLE | F17: 15 | G17: {=XLOOKUP(B17,INV!A:A,INV!G:G)} -> 0 | H17: =IF(G17/F17<0,0,G17/F17) -> 0 | I17: =F17*J17 -> 120 | J17: 8 | K17: =IF((H17-1+V17)<0,0,H17-1+V17) -> 0 | L17: =IF((K17-1+W17)<0,0,K17-1+W17) -> 0 | M17: =IF((L17-1+X17)<0,0,L17-1+X17) -> 0 | N17: =IF((M17-1+Y17)<0,0,M17-1+Y17) -> 7 | O17: =IF((N17-1+Z17)<0,0,N17-1+Z17) -> 7 | P17: =IF((O17-1+AA17)<0,0,O17-1+AA17) -> 6 | Q17: =T17*F17 -> 30 | S17: =U17*F17 -> 0 | T17: =IF(P17<J17,J17-P17,0) -> 2 | U17: =IF(N17<3,3-N17,0) -> 0 | V17: {=iferror(XLOOKUP(B17,'INC INV'!AJ:AJ,'INC INV'!AL:AL)/F17,0)} -> 0 | W17: {=IFERROR(XLOOKUP(B17,'INC INV'!AP:AP,'INC INV'!AR:AR)/F17,0)} -> 0 | X17: {=IFERROR(XLOOKUP(B17,'INC INV'!AV:AV,'INC INV'!AX:AX)/F17,0)} -> 0 | Y17: {=IFERROR(XLOOKUP(B17,'INC INV'!BB:BB,'INC INV'!BD:BD)/F17,0)} -> 8 | Z17: {=IFERROR(XLOOKUP(B17,'INC INV'!BH:BH,'INC INV'!BJ:BJ)/F17,0)} -> 1 | AA17: {=IFERROR(XLOOKUP(B17,'INC INV'!BN:BN,'INC INV'!BP:BP)/F17,0)} -> 0
A18: Copper Vibhuti Box (Tall) - Trigun | B18: HO0108617000 | C18: TEMPLE | F18: 15 | G18: {=XLOOKUP(B18,INV!A:A,INV!G:G)} -> 0 | H18: =IF(G18/F18<0,0,G18/F18) -> 0 | I18: =F18*J18 -> 120 | J18: 8 | K18: =IF((H18-1+V18)<0,0,H18-1+V18) -> 0 | L18: =IF((K18-1+W18)<0,0,K18-1+W18) -> 0 | M18: =IF((L18-1+X18)<0,0,L18-1+X18) -> 0 | N18: =IF((M18-1+Y18)<0,0,M18-1+Y18) -> 7 | O18: =IF((N18-1+Z18)<0,0,N18-1+Z18) -> 7 | P18: =IF((O18-1+AA18)<0,0,O18-1+AA18) -> 6 | Q18: =T18*F18 -> 30 | S18: =U18*F18 -> 0 | T18: =IF(P18<J18,J18-P18,0) -> 2 | U18: =IF(N18<3,3-N18,0) -> 0 | V18: {=iferror(XLOOKUP(B18,'INC INV'!AJ:AJ,'INC INV'!AL:AL)/F18,0)} -> 0 | W18: {=IFERROR(XLOOKUP(B18,'INC INV'!AP:AP,'INC INV'!AR:AR)/F18,0)} -> 0 | X18: {=IFERROR(XLOOKUP(B18,'INC INV'!AV:AV,'INC INV'!AX:AX)/F18,0)} -> 0 | Y18: {=IFERROR(XLOOKUP(B18,'INC INV'!BB:BB,'INC INV'!BD:BD)/F18,0)} -> 8 | Z18: {=IFERROR(XLOOKUP(B18,'INC INV'!BH:BH,'INC INV'!BJ:BJ)/F18,0)} -> 1 | AA18: {=IFERROR(XLOOKUP(B18,'INC INV'!BN:BN,'INC INV'!BP:BP)/F18,0)} -> 0
A19: Adiyogi Galactic - Printed Notebook | B19: HO0088917200 | C19: ACCESSORY | F19: 10 | G19: 0 | H19: =IF(G19/F19<0,0,G19/F19) -> 0 | I19: =F19*J19 -> 60 | J19: 6 | K19: =IF((H19-1+V19)<0,0,H19-1+V19) -> 0 | L19: =IF((K19-1+W19)<0,0,K19-1+W19) -> 0 | M19: =IF((L19-1+X19)<0,0,L19-1+X19) -> 0 | N19: =IF((M19-1+Y19)<0,0,M19-1+Y19) -> 5 | O19: =IF((N19-1+Z19)<0,0,N19-1+Z19) -> 5 | P19: =IF((O19-1+AA19)<0,0,O19-1+AA19) -> 4 | Q19: =T19*F19 -> 20 | S19: =U19*F19 -> 0 | T19: =IF(P19<J19,J19-P19,0) -> 2 | U19: =IF(N19<3,3-N19,0) -> 0 | V19: {=iferror(XLOOKUP(B19,'INC INV'!AJ:AJ,'INC INV'!AL:AL)/F19,0)} -> 0 | W19: {=IFERROR(XLOOKUP(B19,'INC INV'!AP:AP,'INC INV'!AR:AR)/F19,0)} -> 0 | X19: {=IFERROR(XLOOKUP(B19,'INC INV'!AV:AV,'INC INV'!AX:AX)/F19,0)} -> 0 | Y19: {=IFERROR(XLOOKUP(B19,'INC INV'!BB:BB,'INC INV'!BD:BD)/F19,0)} -> 6 | Z19: {=IFERROR(XLOOKUP(B19,'INC INV'!BH:BH,'INC INV'!BJ:BJ)/F19,0)} -> 1 | AA19: {=IFERROR(XLOOKUP(B19,'INC INV'!BN:BN,'INC INV'!BP:BP)/F19,0)} -> 0
A20: Adiyogi Glow-in-the-Dark Keychain (hues of slendour) | B20: HO0125900000 | C20: ACCESSORY | F20: 10 | G20: 0 | H20: =IF(G20/F20<0,0,G20/F20) -> 0 | I20: =F20*J20 -> 60 | J20: 6 | K20: =IF((H20-1+V20)<0,0,H20-1+V20) -> 0 | L20: =IF((K20-1+W20)<0,0,K20-1+W20) -> 0 | M20: =IF((L20-1+X20)<0,0,L20-1+X20) -> 0 | N20: =IF((M20-1+Y20)<0,0,M20-1+Y20) -> 5 | O20: =IF((N20-1+Z20)<0,0,N20-1+Z20) -> 5 | P20: =IF((O20-1+AA20)<0,0,O20-1+AA20) -> 4 | Q20: =T20*F20 -> 20 | S20: =U20*F20 -> 0 | T20: =IF(P20<J20,J20-P20,0) -> 2 | U20: =IF(N20<3,3-N20,0) -> 0 | V20: {=iferror(XLOOKUP(B20,'INC INV'!AJ:AJ,'INC INV'!AL:AL)/F20,0)} -> 0 | W20: {=IFERROR(XLOOKUP(B20,'INC INV'!AP:AP,'INC INV'!AR:AR)/F20,0)} -> 0 | X20: {=IFERROR(XLOOKUP(B20,'INC INV'!AV:AV,'INC INV'!AX:AX)/F20,0)} -> 0 | Y20: {=IFERROR(XLOOKUP(B20,'INC INV'!BB:BB,'INC INV'!BD:BD)/F20,0)} -> 6 | Z20: {=IFERROR(XLOOKUP(B20,'INC INV'!BH:BH,'INC INV'!BJ:BJ)/F20,0)} -> 1 | AA20: {=IFERROR(XLOOKUP(B20,'INC INV'!BN:BN,'INC INV'!BP:BP)/F20,0)} -> 0
A21: Linga Bhairavi Glow-in-the-Dark Keychain | B21: HO0126100000 | C21: ACCESSORY | F21: 10 | G21: 0 | H21: =IF(G21/F21<0,0,G21/F21) -> 0 | I21: =F21*J21 -> 60 | J21: 6 | K21: =IF((H21-1+V21)<0,0,H21-1+V21) -> 0 | L21: =IF((K21-1+W21)<0,0,K21-1+W21) -> 0 | M21: =IF((L21-1+X21)<0,0,L21-1+X21) -> 0 | N21: =IF((M21-1+Y21)<0,0,M21-1+Y21) -> 5 | O21: =IF((N21-1+Z21)<0,0,N21-1+Z21) -> 5 | P21: =IF((O21-1+AA21)<0,0,O21-1+AA21) -> 4 | Q21: =T21*F21 -> 20 | S21: =U21*F21 -> 0 | T21: =IF(P21<J21,J21-P21,0) -> 2 | U21: =IF(N21<3,3-N21,0) -> 0 | V21: {=iferror(XLOOKUP(B21,'INC INV'!AJ:AJ,'INC INV'!AL:AL)/F21,0)} -> 0 | W21: {=IFERROR(XLOOKUP(B21,'INC INV'!AP:AP,'INC INV'!AR:AR)/F21,0)} -> 0 | X21: {=IFERROR(XLOOKUP(B21,'INC INV'!AV:AV,'INC INV'!AX:AX)/F21,0)} -> 0 | Y21: {=IFERROR(XLOOKUP(B21,'INC INV'!BB:BB,'INC INV'!BD:BD)/F21,0)} -> 6 | Z21: {=IFERROR(XLOOKUP(B21,'INC INV'!BH:BH,'INC INV'!BJ:BJ)/F21,0)} -> 1 | AA21: {=IFERROR(XLOOKUP(B21,'INC INV'!BN:BN,'INC INV'!BP:BP)/F21,0)} -> 0
A22: Flowers of Isha Incense Gift Set | B22: CO0007600000 | C22: INCENSE | F22: 10 | G22: {=XLOOKUP(B22,INV!A:A,INV!G:G)} -> 0 | H22: =IF(G22/F22<0,0,G22/F22) -> 0 | I22: =F22*J22 -> 80 | J22: 8 | K22: =IF((H22-1+V22)<0,0,H22-1+V22) -> 0 | L22: =IF((K22-1+W22)<0,0,K22-1+W22) -> 0 | M22: =IF((L22-1+X22)<0,0,L22-1+X22) -> 0 | N22: =IF((M22-1+Y22)<0,0,M22-1+Y22) -> 7 | O22: =IF((N22-1+Z22)<0,0,N22-1+Z22) -> 7 | P22: =IF((O22-1+AA22)<0,0,O22-1+AA22) -> 6 | Q22: =T22*F22 -> 20 | S22: =U22*F22 -> 0 | T22: =IF(P22<J22,J22-P22,0) -> 2 | U22: =IF(N22<3,3-N22,0) -> 0 | V22: {=iferror(XLOOKUP(B22,'INC INV'!AJ:AJ,'INC INV'!AL:AL)/F22,0)} -> 0 | W22: {=IFERROR(XLOOKUP(B22,'INC INV'!AP:AP,'INC INV'!AR:AR)/F22,0)} -> 0 | X22: {=IFERROR(XLOOKUP(B22,'INC INV'!AV:AV,'INC INV'!AX:AX)/F22,0)} -> 0 | Y22: {=IFERROR(XLOOKUP(B22,'INC INV'!BB:BB,'INC INV'!BD:BD)/F22,0)} -> 8 | Z22: {=IFERROR(XLOOKUP(B22,'INC INV'!BH:BH,'INC INV'!BJ:BJ)/F22,0)} -> 1 | AA22: {=IFERROR(XLOOKUP(B22,'INC INV'!BN:BN,'INC INV'!BP:BP)/F22,0)} -> 0
A23: Royal Oud Solid Perfume | B23: BC0001305100 | C23: BODY CARE | D23: {=XLOOKUP(B23,'ORDER LIST'!C:C,'ORDER LIST'!B:B)} -> Royal Oud Solid Perfume | F23: {=XLOOKUP(B23,SALES!A:A,SALES!C:C)} -> 56.916667 | G23: {=XLOOKUP(B23,INV!A:A,INV!G:G)} -> 1 | H23: =IF(G23/F23<0,0,G23/F23) -> 0.017569546 | I23: =F23*J23 -> 455.33333 | J23: 8 | K23: =IF((H23-1+V23)<0,0,H23-1+V23) -> 0 | L23: =IF((K23-1+W23)<0,0,K23-1+W23) -> 10.947291 | M23: =IF((L23-1+X23)<0,0,L23-1+X23) -> 9.9472914 | N23: =IF((M23-1+Y23)<0,0,M23-1+Y23) -> 9.6500732 | O23: =IF((N23-1+Z23)<0,0,N23-1+Z23) -> 8.6500732 | P23: =IF((O23-1+AA23)<0,0,O23-1+AA23) -> 7.6500732 | Q23: =T23*F23 -> 19.916667 | S23: =U23*F23 -> 0 | T23: =IF(P23<J23,J23-P23,0) -> 0.34992679 | U23: =IF(N23<3,3-N23,0) -> 0 | V23: {=iferror(XLOOKUP(B23,'INC INV'!AJ:AJ,'INC INV'!AL:AL)/F23,0)} -> 0 | W23: {=IFERROR(XLOOKUP(B23,'INC INV'!AP:AP,'INC INV'!AR:AR)/F23,0)} -> 11.947291 | X23: {=IFERROR(XLOOKUP(B23,'INC INV'!AV:AV,'INC INV'!AX:AX)/F23,0)} -> 0 | Y23: {=IFERROR(XLOOKUP(B23,'INC INV'!BB:BB,'INC INV'!BD:BD)/F23,0)} -> 0.70278184 | Z23: {=IFERROR(XLOOKUP(B23,'INC INV'!BH:BH,'INC INV'!BJ:BJ)/F23,0)} -> 0 | AA23: {=IFERROR(XLOOKUP(B23,'INC INV'!BN:BN,'INC INV'!BP:BP)/F23,0)} -> 0
A24: Devi I/ Red Photo Hor | B24: ME0019909900 | C24: PHOTO | E24: {=XLOOKUP(B24,'PRICE LIST'!E:E,#REF!)} -> #N/A | F24: {=XLOOKUP(B24,SALES!A:A,SALES!C:C)} -> 4.5 | G24: {=XLOOKUP(B24,INV!A:A,INV!G:G)} -> 0 | H24: =IF(G24/F24<0,0,G24/F24) -> 0 | I24: =F24*J24 -> 36 | J24: 8 | K24: =IF((H24-1+V24)<0,0,H24-1+V24) -> 0 | L24: =IF((K24-1+W24)<0,0,K24-1+W24) -> 0 | M24: =IF((L24-1+X24)<0,0,L24-1+X24) -> 0 | N24: =IF((M24-1+Y24)<0,0,M24-1+Y24) -> 6.1111111 | O24: =IF((N24-1+Z24)<0,0,N24-1+Z24) -> 5.1111111 | P24: =IF((O24-1+AA24)<0,0,O24-1+AA24) -> 4.1111111 | Q24: =T24*F24 -> 17.5 | S24: =U24*F24 -> 0 | T24: =IF(P24<J24,J24-P24,0) -> 3.8888889 | U24: =IF(N24<3,3-N24,0) -> 0 | V24: {=iferror(XLOOKUP(B24,'INC INV'!AJ:AJ,'INC INV'!AL:AL)/F24,0)} -> 0 | W24: {=IFERROR(XLOOKUP(B24,'INC INV'!AP:AP,'INC INV'!AR:AR)/F24,0)} -> 0 | X24: {=IFERROR(XLOOKUP(B24,'INC INV'!AV:AV,'INC INV'!AX:AX)/F24,0)} -> 0 | Y24: {=IFERROR(XLOOKUP(B24,'INC INV'!BB:BB,'INC INV'!BD:BD)/F24,0)} -> 7.1111111 | Z24: {=IFERROR(XLOOKUP(B24,'INC INV'!BH:BH,'INC INV'!BJ:BJ)/F24,0)} -> 0 | AA24: {=IFERROR(XLOOKUP(B24,'INC INV'!BN:BN,'INC INV'!BP:BP)/F24,0)} -> 0
A25: Aum Namah Shivaya - Hammered Copper cuff | B25: CA0120500000 | C25: JEWELRY | F25: {=XLOOKUP(B25,SALES!A:A,SALES!C:C)} -> 10.583333 | G25: {=XLOOKUP(B25,INV!A:A,INV!G:G)} -> 0 | H25: =IF(G25/F25<0,0,G25/F25) -> 0 | I25: =F25*J25 -> 84.666667 | J25: 8 | K25: =IF((H25-1+V25)<0,0,H25-1+V25) -> 0 | L25: =IF((K25-1+W25)<0,0,K25-1+W25) -> 0 | M25: =IF((L25-1+X25)<0,0,L25-1+X25) -> 0 | N25: =IF((M25-1+Y25)<0,0,M25-1+Y25) -> 6.9370079 | O25: =IF((N25-1+Z25)<0,0,N25-1+Z25) -> 7.3543307 | P25: =IF((O25-1+AA25)<0,0,O25-1+AA25) -> 6.3543307 | Q25: =T25*F25 -> 17.416667 | S25: =U25*F25 -> 0 | T25: =IF(P25<J25,J25-P25,0) -> 1.6456693 | U25: =IF(N25<3,3-N25,0) -> 0 | V25: {=iferror(XLOOKUP(B25,'INC INV'!AJ:AJ,'INC INV'!AL:AL)/F25,0)} -> 0 | W25: {=IFERROR(XLOOKUP(B25,'INC INV'!AP:AP,'INC INV'!AR:AR)/F25,0)} -> 0 | X25: {=IFERROR(XLOOKUP(B25,'INC INV'!AV:AV,'INC INV'!AX:AX)/F25,0)} -> 0 | Y25: {=IFERROR(XLOOKUP(B25,'INC INV'!BB:BB,'INC INV'!BD:BD)/F25,0)} -> 7.9370079 | Z25: {=IFERROR(XLOOKUP(B25,'INC INV'!BH:BH,'INC INV'!BJ:BJ)/F25,0)} -> 1.4173228 | AA25: {=IFERROR(XLOOKUP(B25,'INC INV'!BN:BN,'INC INV'!BP:BP)/F25,0)} -> 0
A26: Devi Samarpanam Incense Gift Set | B26: CO0007700000 | C26: INCENSE | F26: {=XLOOKUP(B26,SALES!A:A,SALES!C:C)} -> 8.8333333 | G26: {=XLOOKUP(B26,INV!A:A,INV!G:G)} -> 0 | H26: =IF(G26/F26<0,0,G26/F26) -> 0 | I26: =F26*J26 -> 70.666667 | J26: 8 | K26: =IF((H26-1+V26)<0,0,H26-1+V26) -> 0 | L26: =IF((K26-1+W26)<0,0,K26-1+W26) -> 2.0566038 | M26: =IF((L26-1+X26)<0,0,L26-1+X26) -> 1.0566038 | N26: =IF((M26-1+Y26)<0,0,M26-1+Y26) -> 8.0943396 | O26: =IF((N26-1+Z26)<0,0,N26-1+Z26) -> 7.0943396 | P26: =IF((O26-1+AA26)<0,0,O26-1+AA26) -> 6.0943396 | Q26: =T26*F26 -> 16.833333 | S26: =U26*F26 -> 0 | T26: =IF(P26<J26,J26-P26,0) -> 1.9056604 | U26: =IF(N26<3,3-N26,0) -> 0 | V26: {=iferror(XLOOKUP(B26,'INC INV'!AJ:AJ,'INC INV'!AL:AL)/F26,0)} -> 0 | W26: {=IFERROR(XLOOKUP(B26,'INC INV'!AP:AP,'INC INV'!AR:AR)/F26,0)} -> 3.0566038 | X26: {=IFERROR(XLOOKUP(B26,'INC INV'!AV:AV,'INC INV'!AX:AX)/F26,0)} -> 0 | Y26: {=IFERROR(XLOOKUP(B26,'INC INV'!BB:BB,'INC INV'!BD:BD)/F26,0)} -> 8.0377358 | Z26: {=IFERROR(XLOOKUP(B26,'INC INV'!BH:BH,'INC INV'!BJ:BJ)/F26,0)} -> 0 | AA26: {=IFERROR(XLOOKUP(B26,'INC INV'!BN:BN,'INC INV'!BP:BP)/F26,0)} -> 0
A27: Car-Stand-Photo | B27: ME0016300000 | C27: ACCESSORY | D27: {=XLOOKUP(B27,'ORDER LIST'!C:C,'ORDER LIST'!B:B)} -> Car-Stand-Photo | F27: {=XLOOKUP(B27,SALES!A:A,SALES!C:C)} -> 6.9166667 | G27: {=XLOOKUP(B27,INV!A:A,INV!G:G)} -> 0 | H27: =IF(G27/F27<0,0,G27/F27) -> 0 | I27: =F27*J27 -> 41.5 | J27: 6 | K27: =IF((H27-1+V27)<0,0,H27-1+V27) -> 0 | L27: =IF((K27-1+W27)<0,0,K27-1+W27) -> 7.6746988 | M27: =IF((L27-1+X27)<0,0,L27-1+X27) -> 6.6746988 | N27: =IF((M27-1+Y27)<0,0,M27-1+Y27) -> 5.6746988 | O27: =IF((N27-1+Z27)<0,0,N27-1+Z27) -> 4.6746988 | P27: =IF((O27-1+AA27)<0,0,O27-1+AA27) -> 3.6746988 | Q27: =T27*F27 -> 16.083333 | S27: =U27*F27 -> 0 | T27: =IF(P27<J27,J27-P27,0) -> 2.3253012 | U27: =IF(N27<3,3-N27,0) -> 0 | V27: {=iferror(XLOOKUP(B27,'INC INV'!AJ:AJ,'INC INV'!AL:AL)/F27,0)} -> 0 | W27: {=IFERROR(XLOOKUP(B27,'INC INV'!AP:AP,'INC INV'!AR:AR)/F27,0)} -> 8.6746988 | X27: {=IFERROR(XLOOKUP(B27,'INC INV'!AV:AV,'INC INV'!AX:AX)/F27,0)} -> 0 | Y27: {=IFERROR(XLOOKUP(B27,'INC INV'!BB:BB,'INC INV'!BD:BD)/F27,0)} -> 0 | Z27: {=IFERROR(XLOOKUP(B27,'INC INV'!BH:BH,'INC INV'!BJ:BJ)/F27,0)} -> 0 | AA27: {=IFERROR(XLOOKUP(B27,'INC INV'!BN:BN,'INC INV'!BP:BP)/F27,0)} -> 0
A28: Brass Fumer with Tongs | B28: HO0021900000 | C28: INCENSE | F28: {=XLOOKUP(B28,SALES!A:A,SALES!C:C)} -> 4.1666667 | G28: {=XLOOKUP(B28,INV!A:A,INV!G:G)} -> 0 | H28: =IF(G28/F28<0,0,G28/F28) -> 0 | I28: =F28*J28 -> 33.333333 | J28: 8 | K28: =IF((H28-1+V28)<0,0,H28-1+V28) -> 0 | L28: =IF((K28-1+W28)<0,0,K28-1+W28) -> 0 | M28: =IF((L28-1+X28)<0,0,L28-1+X28) -> 0 | N28: =IF((M28-1+Y28)<0,0,M28-1+Y28) -> 6.68 | O28: =IF((N28-1+Z28)<0,0,N28-1+Z28) -> 5.68 | P28: =IF((O28-1+AA28)<0,0,O28-1+AA28) -> 4.68 | Q28: =T28*F28 -> 13.833333 | S28: =U28*F28 -> 0 | T28: =IF(P28<J28,J28-P28,0) -> 3.32 | U28: =IF(N28<3,3-N28,0) -> 0 | V28: {=iferror(XLOOKUP(B28,'INC INV'!AJ:AJ,'INC INV'!AL:AL)/F28,0)} -> 0 | W28: {=IFERROR(XLOOKUP(B28,'INC INV'!AP:AP,'INC INV'!AR:AR)/F28,0)} -> 0 | X28: {=IFERROR(XLOOKUP(B28,'INC INV'!AV:AV,'INC INV'!AX:AX)/F28,0)} -> 0 | Y28: {=IFERROR(XLOOKUP(B28,'INC INV'!BB:BB,'INC INV'!BD:BD)/F28,0)} -> 7.68 | Z28: {=IFERROR(XLOOKUP(B28,'INC INV'!BH:BH,'INC INV'!BJ:BJ)/F28,0)} -> 0 | AA28: {=IFERROR(XLOOKUP(B28,'INC INV'!BN:BN,'INC INV'!BP:BP)/F28,0)} -> 0
A29: Devi w/Bangles Red Hor | B29: ME0019911300 | C29: PHOTO | E29: {=XLOOKUP(B29,'PRICE LIST'!E:E,#REF!)} -> #N/A | F29: {=XLOOKUP(B29,SALES!A:A,SALES!C:C)} -> 2.5 | G29: {=XLOOKUP(B29,INV!A:A,INV!G:G)} -> 2 | H29: =IF(G29/F29<0,0,G29/F29) -> 0.8 | I29: =F29*J29 -> 20 | J29: 8 | K29: =IF((H29-1+V29)<0,0,H29-1+V29) -> 0 | L29: =IF((K29-1+W29)<0,0,K29-1+W29) -> 0 | M29: =IF((L29-1+X29)<0,0,L29-1+X29) -> 0 | N29: =IF((M29-1+Y29)<0,0,M29-1+Y29) -> 7 | O29: =IF((N29-1+Z29)<0,0,N29-1+Z29) -> 6 | P29: =IF((O29-1+AA29)<0,0,O29-1+AA29) -> 5 | Q29: =T29*F29 -> 7.5 | S29: =U29*F29 -> 0 | T29: =IF(P29<J29,J29-P29,0) -> 3 | U29: =IF(N29<3,3-N29,0) -> 0 | V29: {=iferror(XLOOKUP(B29,'INC INV'!AJ:AJ,'INC INV'!AL:AL)/F29,0)} -> 0 | W29: {=IFERROR(XLOOKUP(B29,'INC INV'!AP:AP,'INC INV'!AR:AR)/F29,0)} -> 0 | X29: {=IFERROR(XLOOKUP(B29,'INC INV'!AV:AV,'INC INV'!AX:AX)/F29,0)} -> 0 | Y29: {=IFERROR(XLOOKUP(B29,'INC INV'!BB:BB,'INC INV'!BD:BD)/F29,0)} -> 8 | Z29: {=IFERROR(XLOOKUP(B29,'INC INV'!BH:BH,'INC INV'!BJ:BJ)/F29,0)} -> 0 | AA29: {=IFERROR(XLOOKUP(B29,'INC INV'!BN:BN,'INC INV'!BP:BP)/F29,0)} -> 0
A30: Devi w/Bangles Yellow Ver | B30: ME0020011400 | C30: PHOTO | E30: {=XLOOKUP(B30,'PRICE LIST'!E:E,#REF!)} -> #N/A | F30: {=XLOOKUP(B30,SALES!A:A,SALES!C:C)} -> 2 | G30: {=XLOOKUP(B30,INV!A:A,INV!G:G)} -> 2 | H30: =IF(G30/F30<0,0,G30/F30) -> 1 | I30: =F30*J30 -> 16 | J30: 8 | K30: =IF((H30-1+V30)<0,0,H30-1+V30) -> 0 | L30: =IF((K30-1+W30)<0,0,K30-1+W30) -> 0 | M30: =IF((L30-1+X30)<0,0,L30-1+X30) -> 0 | N30: =IF((M30-1+Y30)<0,0,M30-1+Y30) -> 7 | O30: =IF((N30-1+Z30)<0,0,N30-1+Z30) -> 6 | P30: =IF((O30-1+AA30)<0,0,O30-1+AA30) -> 5 | Q30: =T30*F30 -> 6 | S30: =U30*F30 -> 0 | T30: =IF(P30<J30,J30-P30,0) -> 3 | U30: =IF(N30<3,3-N30,0) -> 0 | V30: {=iferror(XLOOKUP(B30,'INC INV'!AJ:AJ,'INC INV'!AL:AL)/F30,0)} -> 0 | W30: {=IFERROR(XLOOKUP(B30,'INC INV'!AP:AP,'INC INV'!AR:AR)/F30,0)} -> 0 | X30: {=IFERROR(XLOOKUP(B30,'INC INV'!AV:AV,'INC INV'!AX:AX)/F30,0)} -> 0 | Y30: {=IFERROR(XLOOKUP(B30,'INC INV'!BB:BB,'INC INV'!BD:BD)/F30,0)} -> 8 | Z30: {=IFERROR(XLOOKUP(B30,'INC INV'!BH:BH,'INC INV'!BJ:BJ)/F30,0)} -> 0 | AA30: {=IFERROR(XLOOKUP(B30,'INC INV'!BN:BN,'INC INV'!BP:BP)/F30,0)} -> 0
A31: Devi I/Red Photo Ver | B31: ME0019913400 | C31: PHOTO | E31: {=XLOOKUP(B31,'PRICE LIST'!E:E,#REF!)} -> #N/A | F31: {=XLOOKUP(B31,SALES!A:A,SALES!C:C)} -> 1.25 | G31: {=XLOOKUP(B31,INV!A:A,INV!G:G)} -> 0 | H31: =IF(G31/F31<0,0,G31/F31) -> 0 | I31: =F31*J31 -> 10 | J31: 8 | K31: =IF((H31-1+V31)<0,0,H31-1+V31) -> 0 | L31: =IF((K31-1+W31)<0,0,K31-1+W31) -> 0 | M31: =IF((L31-1+X31)<0,0,L31-1+X31) -> 0 | N31: =IF((M31-1+Y31)<0,0,M31-1+Y31) -> 7 | O31: =IF((N31-1+Z31)<0,0,N31-1+Z31) -> 6 | P31: =IF((O31-1+AA31)<0,0,O31-1+AA31) -> 5 | Q31: =T31*F31 -> 3.75 | S31: =U31*F31 -> 0 | T31: =IF(P31<J31,J31-P31,0) -> 3 | U31: =IF(N31<3,3-N31,0) -> 0 | V31: {=iferror(XLOOKUP(B31,'INC INV'!AJ:AJ,'INC INV'!AL:AL)/F31,0)} -> 0 | W31: {=IFERROR(XLOOKUP(B31,'INC INV'!AP:AP,'INC INV'!AR:AR)/F31,0)} -> 0 | X31: {=IFERROR(XLOOKUP(B31,'INC INV'!AV:AV,'INC INV'!AX:AX)/F31,0)} -> 0 | Y31: {=IFERROR(XLOOKUP(B31,'INC INV'!BB:BB,'INC INV'!BD:BD)/F31,0)} -> 8 | Z31: {=IFERROR(XLOOKUP(B31,'INC INV'!BH:BH,'INC INV'!BJ:BJ)/F31,0)} -> 0 | AA31: {=IFERROR(XLOOKUP(B31,'INC INV'!BN:BN,'INC INV'!BP:BP)/F31,0)} -> 0
A32: Lotus-Leaf-Table-L | B32: TC0005217100 | C32: TEMPLE | E32: WAREHOUSE SPACE | F32: {=XLOOKUP(B32,SALES!A:A,SALES!C:C)} -> 3.1666667 | G32: {=XLOOKUP(B32,INV!A:A,INV!G:G)} -> 0 | H32: =IF(G32/F32<0,0,G32/F32) -> 0 | I32: =F32*J32 -> 25.333333 | J32: 8 | K32: =IF((H32-1+V32)<0,0,H32-1+V32) -> 0 | L32: =IF((K32-1+W32)<0,0,K32-1+W32) -> 0 | M32: =IF((L32-1+X32)<0,0,L32-1+X32) -> 0 | N32: =IF((M32-1+Y32)<0,0,M32-1+Y32) -> 3.1052632 | O32: =IF((N32-1+Z32)<0,0,N32-1+Z32) -> 8.4210526 | P32: =IF((O32-1+AA32)<0,0,O32-1+AA32) -> 7.4210526 | Q32: =T32*F32 -> 1.8333333 | S32: =U32*F32 -> 0 | T32: =IF(P32<J32,J32-P32,0) -> 0.57894737 | U32: =IF(N32<3,3-N32,0) -> 0 | V32: {=iferror(XLOOKUP(B32,'INC INV'!AJ:AJ,'INC INV'!AL:AL)/F32,0)} -> 0 | W32: {=IFERROR(XLOOKUP(B32,'INC INV'!AP:AP,'INC INV'!AR:AR)/F32,0)} -> 0 | X32: {=IFERROR(XLOOKUP(B32,'INC INV'!AV:AV,'INC INV'!AX:AX)/F32,0)} -> 0 | Y32: {=IFERROR(XLOOKUP(B32,'INC INV'!BB:BB,'INC INV'!BD:BD)/F32,0)} -> 4.1052632 | Z32: {=IFERROR(XLOOKUP(B32,'INC INV'!BH:BH,'INC INV'!BJ:BJ)/F32,0)} -> 6.3157895 | AA32: {=IFERROR(XLOOKUP(B32,'INC INV'!BN:BN,'INC INV'!BP:BP)/F32,0)} -> 0
A33: English Mystics Musings Hard | B33: ME0004801500 | C33: BOOK | F33: {=XLOOKUP(B33,SALES!A:A,SALES!C:C)} -> 1.5833333 | G33: {=XLOOKUP(B33,INV!A:A,INV!G:G)} -> 0 | H33: =IF(G33/F33<0,0,G33/F33) -> 0 | I33: =F33*J33 -> 12.666667 | J33: 8 | K33: =IF((H33-1+V33)<0,0,H33-1+V33) -> 0 | L33: =IF((K33-1+W33)<0,0,K33-1+W33) -> 0 | M33: =IF((L33-1+X33)<0,0,L33-1+X33) -> 0 | N33: =IF((M33-1+Y33)<0,0,M33-1+Y33) -> 0 | O33: =IF((N33-1+Z33)<0,0,N33-1+Z33) -> 8.4736842 | P33: =IF((O33-1+AA33)<0,0,O33-1+AA33) -> 7.4736842 | Q33: =T33*F33 -> 0.83333333 | S33: =U33*F33 -> 4.75 | T33: =IF(P33<J33,J33-P33,0) -> 0.52631579 | U33: =IF(N33<3,3-N33,0) -> 3 | V33: {=iferror(XLOOKUP(B33,'INC INV'!AJ:AJ,'INC INV'!AL:AL)/F33,0)} -> 0 | W33: {=IFERROR(XLOOKUP(B33,'INC INV'!AP:AP,'INC INV'!AR:AR)/F33,0)} -> 0 | X33: {=IFERROR(XLOOKUP(B33,'INC INV'!AV:AV,'INC INV'!AX:AX)/F33,0)} -> 0 | Y33: {=IFERROR(XLOOKUP(B33,'INC INV'!BB:BB,'INC INV'!BD:BD)/F33,0)} -> 0.63157895 | Z33: {=IFERROR(XLOOKUP(B33,'INC INV'!BH:BH,'INC INV'!BJ:BJ)/F33,0)} -> 9.4736842 | AA33: {=IFERROR(XLOOKUP(B33,'INC INV'!BN:BN,'INC INV'!BP:BP)/F33,0)} -> 0
A34: Sannidhi-Vibuthi​ | B34: PR0001200000 | C34: CONX | D34: {=XLOOKUP(B34,'ORDER LIST'!C:C,'ORDER LIST'!B:B)} -> Sannidhi-Vibuthi​ | F34: {=XLOOKUP(B34,SALES!A:A,SALES!C:C)} -> 3.6666667 | G34: {=XLOOKUP(B34,INV!A:A,INV!G:G)} -> 0 | H34: =IF(G34/F34<0,0,G34/F34) -> 0 | I34: =F34*J34 -> 36.666667 | J34: 10 | K34: =IF((H34-1+V34)<0,0,H34-1+V34) -> 0 | L34: =IF((K34-1+W34)<0,0,K34-1+W34) -> 0 | M34: =IF((L34-1+X34)<0,0,L34-1+X34) -> 3.0909091 | N34: =IF((M34-1+Y34)<0,0,M34-1+Y34) -> 2.0909091 | O34: =IF((N34-1+Z34)<0,0,N34-1+Z34) -> 12 | P34: =IF((O34-1+AA34)<0,0,O34-1+AA34) -> 11 | Q34: =T34*F34 -> 0 | S34: =U34*F34 -> 3.3333333 | T34: =IF(P34<J34,J34-P34,0) -> 0 | U34: =IF(N34<3,3-N34,0) -> 0.90909091 | V34: {=iferror(XLOOKUP(B34,'INC INV'!AJ:AJ,'INC INV'!AL:AL)/F34,0)} -> 0 | W34: {=IFERROR(XLOOKUP(B34,'INC INV'!AP:AP,'INC INV'!AR:AR)/F34,0)} -> 0 | X34: {=IFERROR(XLOOKUP(B34,'INC INV'!AV:AV,'INC INV'!AX:AX)/F34,0)} -> 4.0909091 | Y34: {=IFERROR(XLOOKUP(B34,'INC INV'!BB:BB,'INC INV'!BD:BD)/F34,0)} -> 0 | Z34: {=IFERROR(XLOOKUP(B34,'INC INV'!BH:BH,'INC INV'!BJ:BJ)/F34,0)} -> 10.909091 | AA34: {=IFERROR(XLOOKUP(B34,'INC INV'!BN:BN,'INC INV'!BP:BP)/F34,0)} -> 0
A35: Copper Mug with Handle, 414 ml | B35: YS0002300002 | C35: COPPER | E35: NEEDED A MUG | F35: 15 | G35: 0 | H35: =IF(G35/F35<0,0,G35/F35) -> 0 | I35: =F35*J35 -> 90 | J35: 6 | K35: =IF((H35-1+V35)<0,0,H35-1+V35) -> 0 | L35: =IF((K35-1+W35)<0,0,K35-1+W35) -> 0 | M35: =IF((L35-1+X35)<0,0,L35-1+X35) -> 0 | N35: =IF((M35-1+Y35)<0,0,M35-1+Y35) -> 7 | O35: =IF((N35-1+Z35)<0,0,N35-1+Z35) -> 7 | P35: =IF((O35-1+AA35)<0,0,O35-1+AA35) -> 6 | Q35: =T35*F35 -> 0 | S35: =U35*F35 -> 0 | T35: =IF(P35<J35,J35-P35,0) -> 0 | U35: =IF(N35<3,3-N35,0) -> 0 | V35: {=iferror(XLOOKUP(B35,'INC INV'!AJ:AJ,'INC INV'!AL:AL)/F35,0)} -> 0 | W35: {=IFERROR(XLOOKUP(B35,'INC INV'!AP:AP,'INC INV'!AR:AR)/F35,0)} -> 0 | X35: {=IFERROR(XLOOKUP(B35,'INC INV'!AV:AV,'INC INV'!AX:AX)/F35,0)} -> 0 | Y35: {=IFERROR(XLOOKUP(B35,'INC INV'!BB:BB,'INC INV'!BD:BD)/F35,0)} -> 8 | Z35: {=IFERROR(XLOOKUP(B35,'INC INV'!BH:BH,'INC INV'!BJ:BJ)/F35,0)} -> 1 | AA35: {=IFERROR(XLOOKUP(B35,'INC INV'!BN:BN,'INC INV'!BP:BP)/F35,0)} -> 0
A36: Cotton Orange Carpet 6ft x 4ft | B36: YS0019800000 | C36: YOGA STORE | D36: {=XLOOKUP(B36,'ORDER LIST'!C:C,'ORDER LIST'!B:B)} -> Cotton Orange Carpet 6ft x 4ft | E36: WAREHOUSE SPACE | G36: {=XLOOKUP(B36,INV!A:A,INV!G:G)} -> 0 | I36: =F36*J36 -> 0 | J36: 8 | K36: =IF((H36-1+V36)<0,0,H36-1+V36) -> 0 | L36: =IF((K36-1+W36)<0,0,K36-1+W36) -> 0 | M36: =IF((L36-1+X36)<0,0,L36-1+X36) -> 0 | N36: =IF((M36-1+Y36)<0,0,M36-1+Y36) -> 0 | O36: =IF((N36-1+Z36)<0,0,N36-1+Z36) -> 0 | P36: =IF((O36-1+AA36)<0,0,O36-1+AA36) -> 0 | Q36: =T36*F36 -> 0 | S36: =U36*F36 -> 0 | T36: =IF(P36<J36,J36-P36,0) -> 8 | U36: =IF(N36<3,3-N36,0) -> 3 | V36: {=iferror(XLOOKUP(B36,'INC INV'!AJ:AJ,'INC INV'!AL:AL)/F36,0)} -> 0 | W36: {=IFERROR(XLOOKUP(B36,'INC INV'!AP:AP,'INC INV'!AR:AR)/F36,0)} -> 0 | X36: {=IFERROR(XLOOKUP(B36,'INC INV'!AV:AV,'INC INV'!AX:AX)/F36,0)} -> 0 | Y36: {=IFERROR(XLOOKUP(B36,'INC INV'!BB:BB,'INC INV'!BD:BD)/F36,0)} -> 0 | Z36: {=IFERROR(XLOOKUP(B36,'INC INV'!BH:BH,'INC INV'!BJ:BJ)/F36,0)} -> 0 | AA36: {=IFERROR(XLOOKUP(B36,'INC INV'!BN:BN,'INC INV'!BP:BP)/F36,0)} -> 0
A37: Adiyogi Statue metal - 4 inch - Antique brass | B37: TC0007517900 | C37: TEMPLE | F37: {=XLOOKUP(B37,SALES!A:A,SALES!C:C)} -> 10.583333 | G37: {=XLOOKUP(B37,INV!A:A,INV!G:G)} -> 9 | H37: =IF(G37/F37<0,0,G37/F37) -> 0.8503937 | I37: =F37*J37 -> 84.666667 | J37: 8 | K37: =IF((H37-1+V37)<0,0,H37-1+V37) -> 0.039370079 | L37: =IF((K37-1+W37)<0,0,K37-1+W37) -> 0 | M37: =IF((L37-1+X37)<0,0,L37-1+X37) -> 0 | N37: =IF((M37-1+Y37)<0,0,M37-1+Y37) -> 6.3700787 | O37: =IF((N37-1+Z37)<0,0,N37-1+Z37) -> 7.2598425 | P37: =IF((O37-1+AA37)<0,0,O37-1+AA37) -> 6.2598425 | Q37: =T37*F37 -> 18.416667 | S37: =U37*F37 -> 0 | T37: =IF(P37<J37,J37-P37,0) -> 1.7401575 | U37: =IF(N37<3,3-N37,0) -> 0 | V37: {=iferror(XLOOKUP(B37,'INC INV'!AJ:AJ,'INC INV'!AL:AL)/F37,0)} -> 0.18897638 | W37: {=IFERROR(XLOOKUP(B37,'INC INV'!AP:AP,'INC INV'!AR:AR)/F37,0)} -> 0 | X37: {=IFERROR(XLOOKUP(B37,'INC INV'!AV:AV,'INC INV'!AX:AX)/F37,0)} -> 0 | Y37: {=IFERROR(XLOOKUP(B37,'INC INV'!BB:BB,'INC INV'!BD:BD)/F37,0)} -> 7.3700787 | Z37: {=IFERROR(XLOOKUP(B37,'INC INV'!BH:BH,'INC INV'!BJ:BJ)/F37,0)} -> 1.8897638 | AA37: {=IFERROR(XLOOKUP(B37,'INC INV'!BN:BN,'INC INV'!BP:BP)/F37,0)} -> 0
A38: Devi w/Bangles Black Ver | B38: ME0020210000 | C38: PHOTO | E38: {=XLOOKUP(B38,'PRICE LIST'!E:E,#REF!)} -> #N/A | F38: {=XLOOKUP(B38,SALES!A:A,SALES!C:C)} -> 3.0833333 | G38: {=XLOOKUP(B38,INV!A:A,INV!G:G)} -> 4 | H38: =IF(G38/F38<0,0,G38/F38) -> 1.2972973 | I38: =F38*J38 -> 24.666667 | J38: 8 | K38: =IF((H38-1+V38)<0,0,H38-1+V38) -> 0.2972973 | L38: =IF((K38-1+W38)<0,0,K38-1+W38) -> 0 | M38: =IF((L38-1+X38)<0,0,L38-1+X38) -> 0 | N38: =IF((M38-1+Y38)<0,0,M38-1+Y38) -> 6.4594595 | O38: =IF((N38-1+Z38)<0,0,N38-1+Z38) -> 5.4594595 | P38: =IF((O38-1+AA38)<0,0,O38-1+AA38) -> 4.4594595 | Q38: =T38*F38 -> 10.916667 | S38: =U38*F38 -> 0 | T38: =IF(P38<J38,J38-P38,0) -> 3.5405405 | U38: =IF(N38<3,3-N38,0) -> 0 | V38: {=iferror(XLOOKUP(B38,'INC INV'!AJ:AJ,'INC INV'!AL:AL)/F38,0)} -> 0 | W38: {=IFERROR(XLOOKUP(B38,'INC INV'!AP:AP,'INC INV'!AR:AR)/F38,0)} -> 0 | X38: {=IFERROR(XLOOKUP(B38,'INC INV'!AV:AV,'INC INV'!AX:AX)/F38,0)} -> 0 | Y38: {=IFERROR(XLOOKUP(B38,'INC INV'!BB:BB,'INC INV'!BD:BD)/F38,0)} -> 7.4594595 | Z38: {=IFERROR(XLOOKUP(B38,'INC INV'!BH:BH,'INC INV'!BJ:BJ)/F38,0)} -> 0 | AA38: {=IFERROR(XLOOKUP(B38,'INC INV'!BN:BN,'INC INV'!BP:BP)/F38,0)} -> 0
A39: Brass-Plate-GuruPooja | B39: HO0072000400 | C39: TEMPLE | D39: {=XLOOKUP(B39,'ORDER LIST'!C:C,'ORDER LIST'!B:B)} -> Brass-Plate-GuruPooja | E39: L | F39: {=XLOOKUP(B39,SALES!A:A,SALES!C:C)} -> 39.916667 | G39: {=XLOOKUP(B39,INV!A:A,INV!G:G)} -> 30 | H39: =IF(G39/F39<0,0,G39/F39) -> 0.75156576 | I39: =F39*J39 -> 319.33333 | J39: 8 | K39: =IF((H39-1+V39)<0,0,H39-1+V39) -> 0.37787056 | L39: =IF((K39-1+W39)<0,0,K39-1+W39) -> 3.9123173 | M39: =IF((L39-1+X39)<0,0,L39-1+X39) -> 2.9123173 | N39: =IF((M39-1+Y39)<0,0,M39-1+Y39) -> 8.2004175 | O39: =IF((N39-1+Z39)<0,0,N39-1+Z39) -> 7.2004175 | P39: =IF((O39-1+AA39)<0,0,O39-1+AA39) -> 6.2004175 | Q39: =T39*F39 -> 71.833333 | S39: =U39*F39 -> 0 | T39: =IF(P39<J39,J39-P39,0) -> 1.7995825 | U39: =IF(N39<3,3-N39,0) -> 0 | V39: {=iferror(XLOOKUP(B39,'INC INV'!AJ:AJ,'INC INV'!AL:AL)/F39,0)} -> 0.6263048 | W39: {=IFERROR(XLOOKUP(B39,'INC INV'!AP:AP,'INC INV'!AR:AR)/F39,0)} -> 4.5344468 | X39: {=IFERROR(XLOOKUP(B39,'INC INV'!AV:AV,'INC INV'!AX:AX)/F39,0)} -> 0 | Y39: {=IFERROR(XLOOKUP(B39,'INC INV'!BB:BB,'INC INV'!BD:BD)/F39,0)} -> 6.2881002 | Z39: {=IFERROR(XLOOKUP(B39,'INC INV'!BH:BH,'INC INV'!BJ:BJ)/F39,0)} -> 0 | AA39: {=IFERROR(XLOOKUP(B39,'INC INV'!BN:BN,'INC INV'!BP:BP)/F39,0)} -> 0
A40: Adiyogi miniature 2.5" - Antique brass | B40: TC0007518000 | C40: TEMPLE | F40: {=XLOOKUP(B40,SALES!A:A,SALES!C:C)} -> 17.333333 | G40: {=XLOOKUP(B40,INV!A:A,INV!G:G)} -> 23 | H40: =IF(G40/F40<0,0,G40/F40) -> 1.3269231 | I40: =F40*J40 -> 138.66667 | J40: 8 | K40: =IF((H40-1+V40)<0,0,H40-1+V40) -> 0.44230769 | L40: =IF((K40-1+W40)<0,0,K40-1+W40) -> 0 | M40: =IF((L40-1+X40)<0,0,L40-1+X40) -> 0 | N40: =IF((M40-1+Y40)<0,0,M40-1+Y40) -> 1.7115385 | O40: =IF((N40-1+Z40)<0,0,N40-1+Z40) -> 7.0576923 | P40: =IF((O40-1+AA40)<0,0,O40-1+AA40) -> 6.0576923 | Q40: =T40*F40 -> 33.666667 | S40: =U40*F40 -> 22.333333 | T40: =IF(P40<J40,J40-P40,0) -> 1.9423077 | U40: =IF(N40<3,3-N40,0) -> 1.2884615 | V40: {=iferror(XLOOKUP(B40,'INC INV'!AJ:AJ,'INC INV'!AL:AL)/F40,0)} -> 0.11538462 | W40: {=IFERROR(XLOOKUP(B40,'INC INV'!AP:AP,'INC INV'!AR:AR)/F40,0)} -> 0 | X40: {=IFERROR(XLOOKUP(B40,'INC INV'!AV:AV,'INC INV'!AX:AX)/F40,0)} -> 0 | Y40: {=IFERROR(XLOOKUP(B40,'INC INV'!BB:BB,'INC INV'!BD:BD)/F40,0)} -> 2.7115385 | Z40: {=IFERROR(XLOOKUP(B40,'INC INV'!BH:BH,'INC INV'!BJ:BJ)/F40,0)} -> 6.3461538 | AA40: {=IFERROR(XLOOKUP(B40,'INC INV'!BN:BN,'INC INV'!BP:BP)/F40,0)} -> 0
A41: English More than a Life English (BK 115) | B41: ME0000501500 | C41: BOOK | F41: {=XLOOKUP(B41,SALES!A:A,SALES!C:C)} -> 12.833333 | G41: {=XLOOKUP(B41,INV!A:A,INV!G:G)} -> 19 | H41: =IF(G41/F41<0,0,G41/F41) -> 1.4805195 | I41: =F41*J41 -> 102.66667 | J41: 8 | K41: =IF((H41-1+V41)<0,0,H41-1+V41) -> 0.48051948 | L41: =IF((K41-1+W41)<0,0,K41-1+W41) -> 1.4285714 | M41: =IF((L41-1+X41)<0,0,L41-1+X41) -> 0.42857143 | N41: =IF((M41-1+Y41)<0,0,M41-1+Y41) -> 6.7532468 | O41: =IF((N41-1+Z41)<0,0,N41-1+Z41) -> 7.7012987 | P41: =IF((O41-1+AA41)<0,0,O41-1+AA41) -> 6.7012987 | Q41: =T41*F41 -> 16.666667 | S41: =U41*F41 -> 0 | T41: =IF(P41<J41,J41-P41,0) -> 1.2987013 | U41: =IF(N41<3,3-N41,0) -> 0 | V41: {=iferror(XLOOKUP(B41,'INC INV'!AJ:AJ,'INC INV'!AL:AL)/F41,0)} -> 0 | W41: {=IFERROR(XLOOKUP(B41,'INC INV'!AP:AP,'INC INV'!AR:AR)/F41,0)} -> 1.9480519 | X41: {=IFERROR(XLOOKUP(B41,'INC INV'!AV:AV,'INC INV'!AX:AX)/F41,0)} -> 0 | Y41: {=IFERROR(XLOOKUP(B41,'INC INV'!BB:BB,'INC INV'!BD:BD)/F41,0)} -> 7.3246753 | Z41: {=IFERROR(XLOOKUP(B41,'INC INV'!BH:BH,'INC INV'!BJ:BJ)/F41,0)} -> 1.9480519 | AA41: {=IFERROR(XLOOKUP(B41,'INC INV'!BN:BN,'INC INV'!BP:BP)/F41,0)} -> 0
A42: English Ambition to Vision and Greed is God | B42: ME0004401500 | C42: BOOK | F42: {=XLOOKUP(B42,SALES!A:A,SALES!C:C)} -> 16.416667 | G42: {=XLOOKUP(B42,INV!A:A,INV!G:G)} -> 25 | H42: =IF(G42/F42<0,0,G42/F42) -> 1.5228426 | I42: =F42*J42 -> 131.33333 | J42: 8 | K42: =IF((H42-1+V42)<0,0,H42-1+V42) -> 0.52284264 | L42: =IF((K42-1+W42)<0,0,K42-1+W42) -> 1.3502538 | M42: =IF((L42-1+X42)<0,0,L42-1+X42) -> 0.35025381 | N42: =IF((M42-1+Y42)<0,0,M42-1+Y42) -> 6.1116751 | O42: =IF((N42-1+Z42)<0,0,N42-1+Z42) -> 7.5482233 | P42: =IF((O42-1+AA42)<0,0,O42-1+AA42) -> 6.5482233 | Q42: =T42*F42 -> 23.833333 | S42: =U42*F42 -> 0 | T42: =IF(P42<J42,J42-P42,0) -> 1.4517767 | U42: =IF(N42<3,3-N42,0) -> 0 | V42: {=iferror(XLOOKUP(B42,'INC INV'!AJ:AJ,'INC INV'!AL:AL)/F42,0)} -> 0 | W42: {=IFERROR(XLOOKUP(B42,'INC INV'!AP:AP,'INC INV'!AR:AR)/F42,0)} -> 1.8274112 | X42: {=IFERROR(XLOOKUP(B42,'INC INV'!AV:AV,'INC INV'!AX:AX)/F42,0)} -> 0 | Y42: {=IFERROR(XLOOKUP(B42,'INC INV'!BB:BB,'INC INV'!BD:BD)/F42,0)} -> 6.7614213 | Z42: {=IFERROR(XLOOKUP(B42,'INC INV'!BH:BH,'INC INV'!BJ:BJ)/F42,0)} -> 2.4365482 | AA42: {=IFERROR(XLOOKUP(B42,'INC INV'!BN:BN,'INC INV'!BP:BP)/F42,0)} -> 0
A43: US Isha Loban (Incense Blend) | B43: HO0107100002 | C43: INCENSE | D43: {=XLOOKUP(B43,'ORDER LIST'!C:C,'ORDER LIST'!B:B)} -> US Isha Loban (Incense Blend) | F43: 10 | G43: {=XLOOKUP(B43,INV!A:A,INV!G:G)} -> 11 | H43: =IF(G43/F43<0,0,G43/F43) -> 1.1 | I43: =F43*J43 -> 80 | J43: 8 | K43: =IF((H43-1+V43)<0,0,H43-1+V43) -> 0.6 | L43: =IF((K43-1+W43)<0,0,K43-1+W43) -> 11.1 | M43: =IF((L43-1+X43)<0,0,L43-1+X43) -> 10.1 | N43: =IF((M43-1+Y43)<0,0,M43-1+Y43) -> 9.1 | O43: =IF((N43-1+Z43)<0,0,N43-1+Z43) -> 8.1 | P43: =IF((O43-1+AA43)<0,0,O43-1+AA43) -> 7.1 | Q43: =T43*F43 -> 9 | S43: =U43*F43 -> 0 | T43: =IF(P43<J43,J43-P43,0) -> 0.9 | U43: =IF(N43<3,3-N43,0) -> 0 | V43: {=iferror(XLOOKUP(B43,'INC INV'!AJ:AJ,'INC INV'!AL:AL)/F43,0)} -> 0.5 | W43: {=IFERROR(XLOOKUP(B43,'INC INV'!AP:AP,'INC INV'!AR:AR)/F43,0)} -> 11.5 | X43: {=IFERROR(XLOOKUP(B43,'INC INV'!AV:AV,'INC INV'!AX:AX)/F43,0)} -> 0 | Y43: {=IFERROR(XLOOKUP(B43,'INC INV'!BB:BB,'INC INV'!BD:BD)/F43,0)} -> 0 | Z43: {=IFERROR(XLOOKUP(B43,'INC INV'!BH:BH,'INC INV'!BJ:BJ)/F43,0)} -> 0 | AA43: {=IFERROR(XLOOKUP(B43,'INC INV'!BN:BN,'INC INV'!BP:BP)/F43,0)} -> 0
A44: Isha-Vibhuti | B44: TC0002500000 | C44: CONX | D44: {=XLOOKUP(B44,'ORDER LIST'!C:C,'ORDER LIST'!B:B)} -> Isha-Vibhuti | F44: {=XLOOKUP(B44,SALES!A:A,SALES!C:C)} -> 250.66667 | G44: {=XLOOKUP(B44,INV!A:A,INV!G:G)} -> 430 | H44: =IF(G44/F44<0,0,G44/F44) -> 1.7154255 | I44: =F44*J44 -> 2506.6667 | J44: 10 | K44: =IF((H44-1+V44)<0,0,H44-1+V44) -> 0.71542553 | L44: =IF((K44-1+W44)<0,0,K44-1+W44) -> 0 | M44: =IF((L44-1+X44)<0,0,L44-1+X44) -> 0 | N44: =IF((M44-1+Y44)<0,0,M44-1+Y44) -> 0 | O44: =IF((N44-1+Z44)<0,0,N44-1+Z44) -> 9.0132979 | P44: =IF((O44-1+AA44)<0,0,O44-1+AA44) -> 8.0132979 | Q44: =T44*F44 -> 498 | R44: X | S44: =U44*F44 -> 752 | T44: =IF(P44<J44,J44-P44,0) -> 1.9867021 | U44: =IF(N44<3,3-N44,0) -> 3 | V44: {=iferror(XLOOKUP(B44,'INC INV'!AJ:AJ,'INC INV'!AL:AL)/F44,0)} -> 0 | W44: {=IFERROR(XLOOKUP(B44,'INC INV'!AP:AP,'INC INV'!AR:AR)/F44,0)} -> 0 | X44: {=IFERROR(XLOOKUP(B44,'INC INV'!AV:AV,'INC INV'!AX:AX)/F44,0)} -> 0 | Y44: {=IFERROR(XLOOKUP(B44,'INC INV'!BB:BB,'INC INV'!BD:BD)/F44,0)} -> 0 | Z44: {=IFERROR(XLOOKUP(B44,'INC INV'!BH:BH,'INC INV'!BJ:BJ)/F44,0)} -> 10.013298 | AA44: {=IFERROR(XLOOKUP(B44,'INC INV'!BN:BN,'INC INV'!BP:BP)/F44,0)} -> 0
A45: Arthi-Stand-12x3x2.5 | B45: HO0072200000 | C45: TEMPLE | F45: {=XLOOKUP(B45,SALES!A:A,SALES!C:C)} -> 31.916667 | G45: {=XLOOKUP(B45,INV!A:A,INV!G:G)} -> 0 | H45: =IF(G45/F45<0,0,G45/F45) -> 0 | I45: =F45*J45 -> 255.33333 | J45: 8 | K45: =IF((H45-1+V45)<0,0,H45-1+V45) -> 0.84856397 | L45: =IF((K45-1+W45)<0,0,K45-1+W45) -> 0.78851175 | M45: =IF((L45-1+X45)<0,0,L45-1+X45) -> 0 | N45: =IF((M45-1+Y45)<0,0,M45-1+Y45) -> 4.7650131 | O45: =IF((N45-1+Z45)<0,0,N45-1+Z45) -> 7.0548303 | P45: =IF((O45-1+AA45)<0,0,O45-1+AA45) -> 6.0548303 | Q45: =T45*F45 -> 62.083333 | S45: =U45*F45 -> 0 | T45: =IF(P45<J45,J45-P45,0) -> 1.9451697 | U45: =IF(N45<3,3-N45,0) -> 0 | V45: {=iferror(XLOOKUP(B45,'INC INV'!AJ:AJ,'INC INV'!AL:AL)/F45,0)} -> 1.848564 | W45: {=IFERROR(XLOOKUP(B45,'INC INV'!AP:AP,'INC INV'!AR:AR)/F45,0)} -> 0.93994778 | X45: {=IFERROR(XLOOKUP(B45,'INC INV'!AV:AV,'INC INV'!AX:AX)/F45,0)} -> 0 | Y45: {=IFERROR(XLOOKUP(B45,'INC INV'!BB:BB,'INC INV'!BD:BD)/F45,0)} -> 5.7650131 | Z45: {=IFERROR(XLOOKUP(B45,'INC INV'!BH:BH,'INC INV'!BJ:BJ)/F45,0)} -> 3.2898172 | AA45: {=IFERROR(XLOOKUP(B45,'INC INV'!BN:BN,'INC INV'!BP:BP)/F45,0)} -> 0
A46: DB203 Dhyanalinga Photo (8x12) | B46: ME0017510100 | C46: PHOTO | D46: {=XLOOKUP(B46,'ORDER LIST'!C:C,'ORDER LIST'!B:B)} -> DB203 Dhyanalinga Photo (8x12) | E46: {=XLOOKUP(B46,'PRICE LIST'!E:E,#REF!)} -> #N/A | F46: 8 | G46: {=XLOOKUP(B46,INV!A:A,INV!G:G)} -> 15 | H46: =IF(G46/F46<0,0,G46/F46) -> 1.875 | I46: =F46*J46 -> 64 | J46: 8 | K46: =IF((H46-1+V46)<0,0,H46-1+V46) -> 0.875 | L46: =IF((K46-1+W46)<0,0,K46-1+W46) -> 6.125 | M46: =IF((L46-1+X46)<0,0,L46-1+X46) -> 5.125 | N46: =IF((M46-1+Y46)<0,0,M46-1+Y46) -> 6.875 | O46: =IF((N46-1+Z46)<0,0,N46-1+Z46) -> 8.375 | P46: =IF((O46-1+AA46)<0,0,O46-1+AA46) -> 7.375 | Q46: =T46*F46 -> 5 | S46: =U46*F46 -> 0 | T46: =IF(P46<J46,J46-P46,0) -> 0.625 | U46: =IF(N46<3,3-N46,0) -> 0 | V46: {=iferror(XLOOKUP(B46,'INC INV'!AJ:AJ,'INC INV'!AL:AL)/F46,0)} -> 0 | W46: {=IFERROR(XLOOKUP(B46,'INC INV'!AP:AP,'INC INV'!AR:AR)/F46,0)} -> 6.25 | X46: {=IFERROR(XLOOKUP(B46,'INC INV'!AV:AV,'INC INV'!AX:AX)/F46,0)} -> 0 | Y46: {=IFERROR(XLOOKUP(B46,'INC INV'!BB:BB,'INC INV'!BD:BD)/F46,0)} -> 2.75 | Z46: {=IFERROR(XLOOKUP(B46,'INC INV'!BH:BH,'INC INV'!BJ:BJ)/F46,0)} -> 2.5 | AA46: {=IFERROR(XLOOKUP(B46,'INC INV'!BN:BN,'INC INV'!BP:BP)/F46,0)} -> 0
A47: Singing Bowl | B47: HO0008600000 | C47: CRAFT | F47: {=XLOOKUP(B47,SALES!A:A,SALES!C:C)} -> 5.25 | G47: {=XLOOKUP(B47,INV!A:A,INV!G:G)} -> 0 | H47: =IF(G47/F47<0,0,G47/F47) -> 0 | I47: =F47*J47 -> 42 | J47: 8 | K47: =IF((H47-1+V47)<0,0,H47-1+V47) -> 0.9047619 | L47: =IF((K47-1+W47)<0,0,K47-1+W47) -> 0 | M47: =IF((L47-1+X47)<0,0,L47-1+X47) -> 0 | N47: =IF((M47-1+Y47)<0,0,M47-1+Y47) -> 3 | O47: =IF((N47-1+Z47)<0,0,N47-1+Z47) -> 7.7142857 | P47: =IF((O47-1+AA47)<0,0,O47-1+AA47) -> 6.7142857 | Q47: =T47*F47 -> 6.75 | S47: =U47*F47 -> 0 | T47: =IF(P47<J47,J47-P47,0) -> 1.2857143 | U47: =IF(N47<3,3-N47,0) -> 0 | V47: {=iferror(XLOOKUP(B47,'INC INV'!AJ:AJ,'INC INV'!AL:AL)/F47,0)} -> 1.9047619 | W47: {=IFERROR(XLOOKUP(B47,'INC INV'!AP:AP,'INC INV'!AR:AR)/F47,0)} -> 0 | X47: {=IFERROR(XLOOKUP(B47,'INC INV'!AV:AV,'INC INV'!AX:AX)/F47,0)} -> 0 | Y47: {=IFERROR(XLOOKUP(B47,'INC INV'!BB:BB,'INC INV'!BD:BD)/F47,0)} -> 4 | Z47: {=IFERROR(XLOOKUP(B47,'INC INV'!BH:BH,'INC INV'!BJ:BJ)/F47,0)} -> 5.7142857 | AA47: {=IFERROR(XLOOKUP(B47,'INC INV'!BN:BN,'INC INV'!BP:BP)/F47,0)} -> 0
A48: Incense-Cone-Vilvam-20Pcs | B48: HO0025900002 | C48: INCENSE | D48: {=XLOOKUP(B48,'ORDER LIST'!C:C,'ORDER LIST'!B:B)} -> Incense-Cone-Vilvam-20Pcs | F48: {=XLOOKUP(B48,SALES!A:A,SALES!C:C)} -> 73.833333 | G48: {=XLOOKUP(B48,INV!A:A,INV!G:G)} -> 142 | H48: =IF(G48/F48<0,0,G48/F48) -> 1.9232506 | I48: =F48*J48 -> 590.66667 | J48: 8 | K48: =IF((H48-1+V48)<0,0,H48-1+V48) -> 0.92325056 | L48: =IF((K48-1+W48)<0,0,K48-1+W48) -> 5.4492099 | M48: =IF((L48-1+X48)<0,0,L48-1+X48) -> 4.4492099 | N48: =IF((M48-1+Y48)<0,0,M48-1+Y48) -> 8.1354402 | O48: =IF((N48-1+Z48)<0,0,N48-1+Z48) -> 7.6772009 | P48: =IF((O48-1+AA48)<0,0,O48-1+AA48) -> 6.6772009 | Q48: =T48*F48 -> 97.666667 | S48: =U48*F48 -> 0 | T48: =IF(P48<J48,J48-P48,0) -> 1.3227991 | U48: =IF(N48<3,3-N48,0) -> 0 | V48: {=iferror(XLOOKUP(B48,'INC INV'!AJ:AJ,'INC INV'!AL:AL)/F48,0)} -> 0 | W48: {=IFERROR(XLOOKUP(B48,'INC INV'!AP:AP,'INC INV'!AR:AR)/F48,0)} -> 5.5259594 | X48: {=IFERROR(XLOOKUP(B48,'INC INV'!AV:AV,'INC INV'!AX:AX)/F48,0)} -> 0 | Y48: {=IFERROR(XLOOKUP(B48,'INC INV'!BB:BB,'INC INV'!BD:BD)/F48,0)} -> 4.6862302 | Z48: {=IFERROR(XLOOKUP(B48,'INC INV'!BH:BH,'INC INV'!BJ:BJ)/F48,0)} -> 0.54176072 | AA48: {=IFERROR(XLOOKUP(B48,'INC INV'!BN:BN,'INC INV'!BP:BP)/F48,0)} -> 0
A49: Sadhguru Photo 6x4 Sd 101 | B49: ME0025109000 | C49: PHOTO | D49: {=XLOOKUP(B49,'ORDER LIST'!C:C,'ORDER LIST'!B:B)} -> Sadhguru Photo 6x4 Sd 101 | E49: {=XLOOKUP(B49,'PRICE LIST'!E:E,#REF!)} -> #N/A | F49: 10 | G49: {=XLOOKUP(B49,INV!A:A,INV!G:G)} -> 20 | H49: =IF(G49/F49<0,0,G49/F49) -> 2 | I49: =F49*J49 -> 80 | J49: 8 | K49: =IF((H49-1+V49)<0,0,H49-1+V49) -> 1 | L49: =IF((K49-1+W49)<0,0,K49-1+W49) -> 5 | M49: =IF((L49-1+X49)<0,0,L49-1+X49) -> 4 | N49: =IF((M49-1+Y49)<0,0,M49-1+Y49) -> 7 | O49: =IF((N49-1+Z49)<0,0,N49-1+Z49) -> 8 | P49: =IF((O49-1+AA49)<0,0,O49-1+AA49) -> 7 | Q49: =T49*F49 -> 10 | S49: =U49*F49 -> 0 | T49: =IF(P49<J49,J49-P49,0) -> 1 | U49: =IF(N49<3,3-N49,0) -> 0 | V49: {=iferror(XLOOKUP(B49,'INC INV'!AJ:AJ,'INC INV'!AL:AL)/F49,0)} -> 0 | W49: {=IFERROR(XLOOKUP(B49,'INC INV'!AP:AP,'INC INV'!AR:AR)/F49,0)} -> 5 | X49: {=IFERROR(XLOOKUP(B49,'INC INV'!AV:AV,'INC INV'!AX:AX)/F49,0)} -> 0 | Y49: {=IFERROR(XLOOKUP(B49,'INC INV'!BB:BB,'INC INV'!BD:BD)/F49,0)} -> 4 | Z49: {=IFERROR(XLOOKUP(B49,'INC INV'!BH:BH,'INC INV'!BJ:BJ)/F49,0)} -> 2 | AA49: {=IFERROR(XLOOKUP(B49,'INC INV'!BN:BN,'INC INV'!BP:BP)/F49,0)} -> 0
A50: AY301 Adiyogi Photo (4x6) | B50: ME0015608400 | C50: PHOTO | D50: {=XLOOKUP(B50,'ORDER LIST'!C:C,'ORDER LIST'!B:B)} -> AY301 Adiyogi Photo (4x6) | E50: {=XLOOKUP(B50,'PRICE LIST'!E:E,#REF!)} -> #N/A | F50: 10 | G50: {=XLOOKUP(B50,INV!A:A,INV!G:G)} -> 21 | H50: =IF(G50/F50<0,0,G50/F50) -> 2.1 | I50: =F50*J50 -> 80 | J50: 8 | K50: =IF((H50-1+V50)<0,0,H50-1+V50) -> 1.1 | L50: =IF((K50-1+W50)<0,0,K50-1+W50) -> 5.1 | M50: =IF((L50-1+X50)<0,0,L50-1+X50) -> 4.1 | N50: =IF((M50-1+Y50)<0,0,M50-1+Y50) -> 7.1 | O50: =IF((N50-1+Z50)<0,0,N50-1+Z50) -> 8.1 | P50: =IF((O50-1+AA50)<0,0,O50-1+AA50) -> 7.1 | Q50: =T50*F50 -> 9 | S50: =U50*F50 -> 0 | T50: =IF(P50<J50,J50-P50,0) -> 0.9 | U50: =IF(N50<3,3-N50,0) -> 0 | V50: {=iferror(XLOOKUP(B50,'INC INV'!AJ:AJ,'INC INV'!AL:AL)/F50,0)} -> 0 | W50: {=IFERROR(XLOOKUP(B50,'INC INV'!AP:AP,'INC INV'!AR:AR)/F50,0)} -> 5 | X50: {=IFERROR(XLOOKUP(B50,'INC INV'!AV:AV,'INC INV'!AX:AX)/F50,0)} -> 0 | Y50: {=IFERROR(XLOOKUP(B50,'INC INV'!BB:BB,'INC INV'!BD:BD)/F50,0)} -> 4 | Z50: {=IFERROR(XLOOKUP(B50,'INC INV'!BH:BH,'INC INV'!BJ:BJ)/F50,0)} -> 2 | AA50: {=IFERROR(XLOOKUP(B50,'INC INV'!BN:BN,'INC INV'!BP:BP)/F50,0)} -> 0
A51: Organic Dharba Grass Meditation Mat | B51: YS0011700000 | C51: YOGA STORE | D51: {=XLOOKUP(B51,'ORDER LIST'!C:C,'ORDER LIST'!B:B)} -> Organic Dharba Grass Meditation Mat | F51: {=XLOOKUP(B51,SALES!A:A,SALES!C:C)} -> 109.08333 | G51: {=XLOOKUP(B51,INV!A:A,INV!G:G)} -> 268 | H51: =IF(G51/F51<0,0,G51/F51) -> 2.4568373 | I51: =F51*J51 -> 872.66667 | J51: 8 | K51: =IF((H51-1+V51)<0,0,H51-1+V51) -> 1.4568373 | L51: =IF((K51-1+W51)<0,0,K51-1+W51) -> 7.7448434 | M51: =IF((L51-1+X51)<0,0,L51-1+X51) -> 6.7448434 | N51: =IF((M51-1+Y51)<0,0,M51-1+Y51) -> 10.145149 | O51: =IF((N51-1+Z51)<0,0,N51-1+Z51) -> 9.145149 | P51: =IF((O51-1+AA51)<0,0,O51-1+AA51) -> 8.145149 | Q51: =T51*F51 -> 0 | R51: X | S51: =U51*F51 -> 0 | T51: =IF(P51<J51,J51-P51,0) -> 0 | U51: =IF(N51<3,3-N51,0) -> 0 | V51: {=iferror(XLOOKUP(B51,'INC INV'!AJ:AJ,'INC INV'!AL:AL)/F51,0)} -> 0 | W51: {=IFERROR(XLOOKUP(B51,'INC INV'!AP:AP,'INC INV'!AR:AR)/F51,0)} -> 7.2880061 | X51: {=IFERROR(XLOOKUP(B51,'INC INV'!AV:AV,'INC INV'!AX:AX)/F51,0)} -> 0 | Y51: {=IFERROR(XLOOKUP(B51,'INC INV'!BB:BB,'INC INV'!BD:BD)/F51,0)} -> 4.4003056 | Z51: {=IFERROR(XLOOKUP(B51,'INC INV'!BH:BH,'INC INV'!BJ:BJ)/F51,0)} -> 0 | AA51: {=IFERROR(XLOOKUP(B51,'INC INV'!BN:BN,'INC INV'!BP:BP)/F51,0)} -> 0
A52: DA106 Dhyanalinga Photo (20x30) | B52: ME0016713000 | C52: PHOTO | D52: {=XLOOKUP(B52,'ORDER LIST'!C:C,'ORDER LIST'!B:B)} -> DA106 Dhyanalinga Photo (20x30) | E52: WAREHOUSE SPACE | F52: 4 | G52: {=XLOOKUP(B52,INV!A:A,INV!G:G)} -> 0 | H52: =IF(G52/F52<0,0,G52/F52) -> 0 | I52: =F52*J52 -> 32 | J52: 8 | K52: =IF((H52-1+V52)<0,0,H52-1+V52) -> 1.5 | L52: =IF((K52-1+W52)<0,0,K52-1+W52) -> 6.75 | M52: =IF((L52-1+X52)<0,0,L52-1+X52) -> 5.75 | N52: =IF((M52-1+Y52)<0,0,M52-1+Y52) -> 7.5 | O52: =IF((N52-1+Z52)<0,0,N52-1+Z52) -> 6.5 | P52: =IF((O52-1+AA52)<0,0,O52-1+AA52) -> 5.5 | Q52: =T52*F52 -> 10 | S52: =U52*F52 -> 0 | T52: =IF(P52<J52,J52-P52,0) -> 2.5 | U52: =IF(N52<3,3-N52,0) -> 0 | V52: {=iferror(XLOOKUP(B52,'INC INV'!AJ:AJ,'INC INV'!AL:AL)/F52,0)} -> 2.5 | W52: {=IFERROR(XLOOKUP(B52,'INC INV'!AP:AP,'INC INV'!AR:AR)/F52,0)} -> 6.25 | X52: {=IFERROR(XLOOKUP(B52,'INC INV'!AV:AV,'INC INV'!AX:AX)/F52,0)} -> 0 | Y52: {=IFERROR(XLOOKUP(B52,'INC INV'!BB:BB,'INC INV'!BD:BD)/F52,0)} -> 2.75 | Z52: {=IFERROR(XLOOKUP(B52,'INC INV'!BH:BH,'INC INV'!BJ:BJ)/F52,0)} -> 0 | AA52: {=IFERROR(XLOOKUP(B52,'INC INV'!BN:BN,'INC INV'!BP:BP)/F52,0)} -> 0
A53: DB206 Dhyanalinga Photo (16x24) | B53: ME0017512200 | C53: PHOTO | D53: {=XLOOKUP(B53,'ORDER LIST'!C:C,'ORDER LIST'!B:B)} -> DB206 Dhyanalinga Photo (16x24) | E53: WAREHOUSE SPACE | F53: 4 | G53: {=XLOOKUP(B53,INV!A:A,INV!G:G)} -> 0 | H53: =IF(G53/F53<0,0,G53/F53) -> 0 | I53: =F53*J53 -> 32 | J53: 8 | K53: =IF((H53-1+V53)<0,0,H53-1+V53) -> 1.5 | L53: =IF((K53-1+W53)<0,0,K53-1+W53) -> 10.5 | M53: =IF((L53-1+X53)<0,0,L53-1+X53) -> 9.5 | N53: =IF((M53-1+Y53)<0,0,M53-1+Y53) -> 8.5 | O53: =IF((N53-1+Z53)<0,0,N53-1+Z53) -> 7.5 | P53: =IF((O53-1+AA53)<0,0,O53-1+AA53) -> 6.5 | Q53: =T53*F53 -> 6 | S53: =U53*F53 -> 0 | T53: =IF(P53<J53,J53-P53,0) -> 1.5 | U53: =IF(N53<3,3-N53,0) -> 0 | V53: {=iferror(XLOOKUP(B53,'INC INV'!AJ:AJ,'INC INV'!AL:AL)/F53,0)} -> 2.5 | W53: {=IFERROR(XLOOKUP(B53,'INC INV'!AP:AP,'INC INV'!AR:AR)/F53,0)} -> 10 | X53: {=IFERROR(XLOOKUP(B53,'INC INV'!AV:AV,'INC INV'!AX:AX)/F53,0)} -> 0 | Y53: {=IFERROR(XLOOKUP(B53,'INC INV'!BB:BB,'INC INV'!BD:BD)/F53,0)} -> 0 | Z53: {=IFERROR(XLOOKUP(B53,'INC INV'!BH:BH,'INC INV'!BJ:BJ)/F53,0)} -> 0 | AA53: {=IFERROR(XLOOKUP(B53,'INC INV'!BN:BN,'INC INV'!BP:BP)/F53,0)} -> 0
A54: LB905 Linga Bhairavi with Bangles Photo Black Hor (12x18 Hr) | B54: ME0020211300 | C54: PHOTO | D54: {=XLOOKUP(B54,'ORDER LIST'!C:C,'ORDER LIST'!B:B)} -> LB905 Linga Bhairavi with Bangles Photo Black Hor (12x18 Hr) | E54: {=XLOOKUP(B54,'PRICE LIST'!E:E,#REF!)} -> #N/A | F54: 4 | G54: {=XLOOKUP(B54,INV!A:A,INV!G:G)} -> 10 | H54: =IF(G54/F54<0,0,G54/F54) -> 2.5 | I54: =F54*J54 -> 32 | J54: 8 | K54: =IF((H54-1+V54)<0,0,H54-1+V54) -> 1.5 | L54: =IF((K54-1+W54)<0,0,K54-1+W54) -> 10.5 | M54: =IF((L54-1+X54)<0,0,L54-1+X54) -> 9.5 | N54: =IF((M54-1+Y54)<0,0,M54-1+Y54) -> 8.5 | O54: =IF((N54-1+Z54)<0,0,N54-1+Z54) -> 7.5 | P54: =IF((O54-1+AA54)<0,0,O54-1+AA54) -> 6.5 | Q54: =T54*F54 -> 6 | S54: =U54*F54 -> 0 | T54: =IF(P54<J54,J54-P54,0) -> 1.5 | U54: =IF(N54<3,3-N54,0) -> 0 | V54: {=iferror(XLOOKUP(B54,'INC INV'!AJ:AJ,'INC INV'!AL:AL)/F54,0)} -> 0 | W54: {=IFERROR(XLOOKUP(B54,'INC INV'!AP:AP,'INC INV'!AR:AR)/F54,0)} -> 10 | X54: {=IFERROR(XLOOKUP(B54,'INC INV'!AV:AV,'INC INV'!AX:AX)/F54,0)} -> 0 | Y54: {=IFERROR(XLOOKUP(B54,'INC INV'!BB:BB,'INC INV'!BD:BD)/F54,0)} -> 0 | Z54: {=IFERROR(XLOOKUP(B54,'INC INV'!BH:BH,'INC INV'!BJ:BJ)/F54,0)} -> 0 | AA54: {=IFERROR(XLOOKUP(B54,'INC INV'!BN:BN,'INC INV'!BP:BP)/F54,0)} -> 0
A55: Sugnadhim gift set | B55: CO0007900000 | C55: INCENSE | D55: {=XLOOKUP(B55,'ORDER LIST'!C:C,'ORDER LIST'!B:B)} -> Sugnadhim gift set | F55: 10 | G55: {=XLOOKUP(B55,INV!A:A,INV!G:G)} -> 0 | H55: =IF(G55/F55<0,0,G55/F55) -> 0 | I55: =F55*J55 -> 80 | J55: 8 | K55: =IF((H55-1+V55)<0,0,H55-1+V55) -> 1.5 | L55: =IF((K55-1+W55)<0,0,K55-1+W55) -> 18 | M55: =IF((L55-1+X55)<0,0,L55-1+X55) -> 17 | N55: =IF((M55-1+Y55)<0,0,M55-1+Y55) -> 16 | O55: =IF((N55-1+Z55)<0,0,N55-1+Z55) -> 15 | P55: =IF((O55-1+AA55)<0,0,O55-1+AA55) -> 14 | Q55: =T55*F55 -> 0 | S55: =U55*F55 -> 0 | T55: =IF(P55<J55,J55-P55,0) -> 0 | U55: =IF(N55<3,3-N55,0) -> 0 | V55: {=iferror(XLOOKUP(B55,'INC INV'!AJ:AJ,'INC INV'!AL:AL)/F55,0)} -> 2.5 | W55: {=IFERROR(XLOOKUP(B55,'INC INV'!AP:AP,'INC INV'!AR:AR)/F55,0)} -> 17.5 | X55: {=IFERROR(XLOOKUP(B55,'INC INV'!AV:AV,'INC INV'!AX:AX)/F55,0)} -> 0 | Y55: {=IFERROR(XLOOKUP(B55,'INC INV'!BB:BB,'INC INV'!BD:BD)/F55,0)} -> 0 | Z55: {=IFERROR(XLOOKUP(B55,'INC INV'!BH:BH,'INC INV'!BJ:BJ)/F55,0)} -> 0 | AA55: {=IFERROR(XLOOKUP(B55,'INC INV'!BN:BN,'INC INV'!BP:BP)/F55,0)} -> 0
A56: Guru-Puja-Kit-Brass | B56: YS0006400000 | C56: TEMPLE | D56: {=XLOOKUP(B56,'ORDER LIST'!C:C,'ORDER LIST'!B:B)} -> Guru-Puja-Kit-Brass | F56: {=XLOOKUP(B56,SALES!A:A,SALES!C:C)} -> 30.583333 | G56: {=XLOOKUP(B56,INV!A:A,INV!G:G)} -> 77 | H56: =IF(G56/F56<0,0,G56/F56) -> 2.5177112 | I56: =F56*J56 -> 305.83333 | J56: 10 | K56: =IF((H56-1+V56)<0,0,H56-1+V56) -> 1.5177112 | L56: =IF((K56-1+W56)<0,0,K56-1+W56) -> 0.51771117 | M56: =IF((L56-1+X56)<0,0,L56-1+X56) -> 0.66212534 | N56: =IF((M56-1+Y56)<0,0,M56-1+Y56) -> 0.67574932 | O56: =IF((N56-1+Z56)<0,0,N56-1+Z56) -> 8.8310627 | P56: =IF((O56-1+AA56)<0,0,O56-1+AA56) -> 7.8310627 | Q56: =T56*F56 -> 66.333333 | S56: =U56*F56 -> 71.083333 | T56: =IF(P56<J56,J56-P56,0) -> 2.1689373 | U56: =IF(N56<3,3-N56,0) -> 2.3242507 | V56: {=iferror(XLOOKUP(B56,'INC INV'!AJ:AJ,'INC INV'!AL:AL)/F56,0)} -> 0 | W56: {=IFERROR(XLOOKUP(B56,'INC INV'!AP:AP,'INC INV'!AR:AR)/F56,0)} -> 0 | X56: {=IFERROR(XLOOKUP(B56,'INC INV'!AV:AV,'INC INV'!AX:AX)/F56,0)} -> 1.1444142 | Y56: {=IFERROR(XLOOKUP(B56,'INC INV'!BB:BB,'INC INV'!BD:BD)/F56,0)} -> 1.013624 | Z56: {=IFERROR(XLOOKUP(B56,'INC INV'!BH:BH,'INC INV'!BJ:BJ)/F56,0)} -> 9.1553134 | AA56: {=IFERROR(XLOOKUP(B56,'INC INV'!BN:BN,'INC INV'!BP:BP)/F56,0)} -> 0
A57: Adiyogi Statue metal - 4 inch - Antique bronze | B57: TC0007517800 | C57: TEMPLE | F57: {=XLOOKUP(B57,SALES!A:A,SALES!C:C)} -> 11.5 | G57: {=XLOOKUP(B57,INV!A:A,INV!G:G)} -> 31 | H57: =IF(G57/F57<0,0,G57/F57) -> 2.6956522 | I57: =F57*J57 -> 92 | J57: 8 | K57: =IF((H57-1+V57)<0,0,H57-1+V57) -> 1.6956522 | L57: =IF((K57-1+W57)<0,0,K57-1+W57) -> 0.69565217 | M57: =IF((L57-1+X57)<0,0,L57-1+X57) -> 0 | N57: =IF((M57-1+Y57)<0,0,M57-1+Y57) -> 0 | O57: =IF((N57-1+Z57)<0,0,N57-1+Z57) -> 7.2608696 | P57: =IF((O57-1+AA57)<0,0,O57-1+AA57) -> 6.2608696 | Q57: =T57*F57 -> 20 | S57: =U57*F57 -> 34.5 | T57: =IF(P57<J57,J57-P57,0) -> 1.7391304 | U57: =IF(N57<3,3-N57,0) -> 3 | V57: {=iferror(XLOOKUP(B57,'INC INV'!AJ:AJ,'INC INV'!AL:AL)/F57,0)} -> 0 | W57: {=IFERROR(XLOOKUP(B57,'INC INV'!AP:AP,'INC INV'!AR:AR)/F57,0)} -> 0 | X57: {=IFERROR(XLOOKUP(B57,'INC INV'!AV:AV,'INC INV'!AX:AX)/F57,0)} -> 0 | Y57: {=IFERROR(XLOOKUP(B57,'INC INV'!BB:BB,'INC INV'!BD:BD)/F57,0)} -> 0 | Z57: {=IFERROR(XLOOKUP(B57,'INC INV'!BH:BH,'INC INV'!BJ:BJ)/F57,0)} -> 8.2608696 | AA57: {=IFERROR(XLOOKUP(B57,'INC INV'!BN:BN,'INC INV'!BP:BP)/F57,0)} -> 0
A58: Bhairavi-Raksha | B58: TC0002800300 | C58: CONX | D58: {=XLOOKUP(B58,'ORDER LIST'!C:C,'ORDER LIST'!B:B)} -> Bhairavi-Raksha | E58: M | F58: {=XLOOKUP(B58,SALES!A:A,SALES!C:C)} -> 17.916667 | G58: {=XLOOKUP(B58,INV!A:A,INV!G:G)} -> 50 | H58: =IF(G58/F58<0,0,G58/F58) -> 2.7906977 | I58: =F58*J58 -> 179.16667 | J58: 10 | K58: =IF((H58-1+V58)<0,0,H58-1+V58) -> 1.7906977 | L58: =IF((K58-1+W58)<0,0,K58-1+W58) -> 0.79069767 | M58: =IF((L58-1+X58)<0,0,L58-1+X58) -> 0 | N58: =IF((M58-1+Y58)<0,0,M58-1+Y58) -> 5.8093023 | O58: =IF((N58-1+Z58)<0,0,N58-1+Z58) -> 6.4837209 | P58: =IF((O58-1+AA58)<0,0,O58-1+AA58) -> 5.4837209 | Q58: =T58*F58 -> 80.916667 | S58: =U58*F58 -> 0 | T58: =IF(P58<J58,J58-P58,0) -> 4.5162791 | U58: =IF(N58<3,3-N58,0) -> 0 | V58: {=iferror(XLOOKUP(B58,'INC INV'!AJ:AJ,'INC INV'!AL:AL)/F58,0)} -> 0 | W58: {=IFERROR(XLOOKUP(B58,'INC INV'!AP:AP,'INC INV'!AR:AR)/F58,0)} -> 0 | X58: {=IFERROR(XLOOKUP(B58,'INC INV'!AV:AV,'INC INV'!AX:AX)/F58,0)} -> 0 | Y58: {=IFERROR(XLOOKUP(B58,'INC INV'!BB:BB,'INC INV'!BD:BD)/F58,0)} -> 6.8093023 | Z58: {=IFERROR(XLOOKUP(B58,'INC INV'!BH:BH,'INC INV'!BJ:BJ)/F58,0)} -> 1.6744186 | AA58: {=IFERROR(XLOOKUP(B58,'INC INV'!BN:BN,'INC INV'!BP:BP)/F58,0)} -> 0
A59: Sandalwood & Vetiver Solid Perfume | B59: BC0001405100 | C59: BODY CARE | D59: {=XLOOKUP(B59,'ORDER LIST'!C:C,'ORDER LIST'!B:B)} -> Sandalwood & Vetiver Solid Perfume | F59: {=XLOOKUP(B59,SALES!A:A,SALES!C:C)} -> 59.333333 | G59: {=XLOOKUP(B59,INV!A:A,INV!G:G)} -> 168 | H59: =IF(G59/F59<0,0,G59/F59) -> 2.8314607 | I59: =F59*J59 -> 474.66667 | J59: 8 | K59: =IF((H59-1+V59)<0,0,H59-1+V59) -> 1.8314607 | L59: =IF((K59-1+W59)<0,0,K59-1+W59) -> 3.1910112 | M59: =IF((L59-1+X59)<0,0,L59-1+X59) -> 3.1179775 | N59: =IF((M59-1+Y59)<0,0,M59-1+Y59) -> 6.4325843 | O59: =IF((N59-1+Z59)<0,0,N59-1+Z59) -> 9.0561798 | P59: =IF((O59-1+AA59)<0,0,O59-1+AA59) -> 8.0561798 | Q59: =T59*F59 -> 0 | S59: =U59*F59 -> 0 | T59: =IF(P59<J59,J59-P59,0) -> 0 | U59: =IF(N59<3,3-N59,0) -> 0 | V59: {=iferror(XLOOKUP(B59,'INC INV'!AJ:AJ,'INC INV'!AL:AL)/F59,0)} -> 0 | W59: {=IFERROR(XLOOKUP(B59,'INC INV'!AP:AP,'INC INV'!AR:AR)/F59,0)} -> 2.3595506 | X59: {=IFERROR(XLOOKUP(B59,'INC INV'!AV:AV,'INC INV'!AX:AX)/F59,0)} -> 0.92696629 | Y59: {=IFERROR(XLOOKUP(B59,'INC INV'!BB:BB,'INC INV'!BD:BD)/F59,0)} -> 4.3146067 | Z59: {=IFERROR(XLOOKUP(B59,'INC INV'!BH:BH,'INC INV'!BJ:BJ)/F59,0)} -> 3.6235955 | AA59: {=IFERROR(XLOOKUP(B59,'INC INV'!BN:BN,'INC INV'!BP:BP)/F59,0)} -> 0
A60: Pancha Boota Kriya Cushion | B60: YS0010100000 | C60: YOGA STORE | D60: {=XLOOKUP(B60,'ORDER LIST'!C:C,'ORDER LIST'!B:B)} -> #N/A | F60: {=XLOOKUP(B60,SALES!A:A,SALES!C:C)} -> 71.5 | G60: {=XLOOKUP(B60,INV!A:A,INV!G:G)} -> 204 | H60: =IF(G60/F60<0,0,G60/F60) -> 2.8531469 | I60: =F60*J60 -> 572 | J60: 8 | K60: =IF((H60-1+V60)<0,0,H60-1+V60) -> 1.8531469 | L60: =IF((K60-1+W60)<0,0,K60-1+W60) -> 4.0699301 | M60: =IF((L60-1+X60)<0,0,L60-1+X60) -> 3.0699301 | N60: =IF((M60-1+Y60)<0,0,M60-1+Y60) -> 2.0699301 | O60: =IF((N60-1+Z60)<0,0,N60-1+Z60) -> 7.0839161 | P60: =IF((O60-1+AA60)<0,0,O60-1+AA60) -> 6.0839161 | Q60: =T60*F60 -> 137 | R60: X | S60: =U60*F60 -> 66.5 | T60: =IF(P60<J60,J60-P60,0) -> 1.9160839 | U60: =IF(N60<3,3-N60,0) -> 0.93006993 | V60: {=iferror(XLOOKUP(B60,'INC INV'!AJ:AJ,'INC INV'!AL:AL)/F60,0)} -> 0 | W60: {=IFERROR(XLOOKUP(B60,'INC INV'!AP:AP,'INC INV'!AR:AR)/F60,0)} -> 3.2167832 | X60: {=IFERROR(XLOOKUP(B60,'INC INV'!AV:AV,'INC INV'!AX:AX)/F60,0)} -> 0 | Y60: {=IFERROR(XLOOKUP(B60,'INC INV'!BB:BB,'INC INV'!BD:BD)/F60,0)} -> 0 | Z60: {=IFERROR(XLOOKUP(B60,'INC INV'!BH:BH,'INC INV'!BJ:BJ)/F60,0)} -> 6.013986 | AA60: {=IFERROR(XLOOKUP(B60,'INC INV'!BN:BN,'INC INV'!BP:BP)/F60,0)} -> 0
A61: Ojasvini 100g | B61: BC0002006302 | C61: BODY CARE | F61: {=XLOOKUP(B61,SALES!A:A,SALES!C:C)} -> 74.5 | G61: =F61*H61 -> #N/A | H61: {=XLOOKUP(B61,'EXP INV'!Q:Q,'EXP INV'!R:R)} -> #N/A | I61: =F61*J61 -> 596 | J61: 8 | K61: =IF((H61-1+V61)<0,0,H61-1+V61) -> #N/A | L61: =IF((K61-1+W61)<0,0,K61-1+W61) -> #N/A | M61: =IF((L61-1+X61)<0,0,L61-1+X61) -> #N/A | N61: =IF((M61-1+Y61)<0,0,M61-1+Y61) -> #N/A | O61: =IF((N61-1+Z61)<0,0,N61-1+Z61) -> #N/A | P61: =IF((O61-1+AA61)<0,0,O61-1+AA61) -> #N/A | Q61: =T61*F61 -> #N/A | S61: =U61*F61 -> #N/A | T61: =IF(P61<J61,J61-P61,0) -> #N/A | U61: =IF(N61<3,3-N61,0) -> #N/A | V61: {=iferror(XLOOKUP(B61,'INC INV'!AJ:AJ,'INC INV'!AL:AL)/F61,0)} -> 0 | W61: {=IFERROR(XLOOKUP(B61,'INC INV'!AP:AP,'INC INV'!AR:AR)/F61,0)} -> 0 | X61: {=IFERROR(XLOOKUP(B61,'INC INV'!AV:AV,'INC INV'!AX:AX)/F61,0)} -> 0 | Y61: {=IFERROR(XLOOKUP(B61,'INC INV'!BB:BB,'INC INV'!BD:BD)/F61,0)} -> 6.2818792 | Z61: {=IFERROR(XLOOKUP(B61,'INC INV'!BH:BH,'INC INV'!BJ:BJ)/F61,0)} -> 1.5436242 | AA61: {=IFERROR(XLOOKUP(B61,'INC INV'!BN:BN,'INC INV'!BP:BP)/F61,0)} -> 0
A62: AY303 Adiyogi Photo (8x12) | B62: ME0015610100 | C62: PHOTO | D62: {=XLOOKUP(B62,'ORDER LIST'!C:C,'ORDER LIST'!B:B)} -> AY303 Adiyogi Photo (8x12) | E62: {=XLOOKUP(B62,'PRICE LIST'!E:E,#REF!)} -> #N/A | F62: 8 | G62: {=XLOOKUP(B62,INV!A:A,INV!G:G)} -> 24 | H62: =IF(G62/F62<0,0,G62/F62) -> 3 | I62: =F62*J62 -> 64 | J62: 8 | K62: =IF((H62-1+V62)<0,0,H62-1+V62) -> 2 | L62: =IF((K62-1+W62)<0,0,K62-1+W62) -> 6 | M62: =IF((L62-1+X62)<0,0,L62-1+X62) -> 5 | N62: =IF((M62-1+Y62)<0,0,M62-1+Y62) -> 8 | O62: =IF((N62-1+Z62)<0,0,N62-1+Z62) -> 8.875 | P62: =IF((O62-1+AA62)<0,0,O62-1+AA62) -> 7.875 | Q62: =T62*F62 -> 1 | S62: =U62*F62 -> 0 | T62: =IF(P62<J62,J62-P62,0) -> 0.125 | U62: =IF(N62<3,3-N62,0) -> 0 | V62: {=iferror(XLOOKUP(B62,'INC INV'!AJ:AJ,'INC INV'!AL:AL)/F62,0)} -> 0 | W62: {=IFERROR(XLOOKUP(B62,'INC INV'!AP:AP,'INC INV'!AR:AR)/F62,0)} -> 5 | X62: {=IFERROR(XLOOKUP(B62,'INC INV'!AV:AV,'INC INV'!AX:AX)/F62,0)} -> 0 | Y62: {=IFERROR(XLOOKUP(B62,'INC INV'!BB:BB,'INC INV'!BD:BD)/F62,0)} -> 4 | Z62: {=IFERROR(XLOOKUP(B62,'INC INV'!BH:BH,'INC INV'!BJ:BJ)/F62,0)} -> 1.875 | AA62: {=IFERROR(XLOOKUP(B62,'INC INV'!BN:BN,'INC INV'!BP:BP)/F62,0)} -> 0
A63: Trishul | B63: TC0006400000 | C63: TEMPLE | D63: {=XLOOKUP(B63,'ORDER LIST'!C:C,'ORDER LIST'!B:B)} -> Trishul | F63: {=XLOOKUP(B63,SALES!A:A,SALES!C:C)} -> 20.083333 | G63: {=XLOOKUP(B63,INV!A:A,INV!G:G)} -> 62 | H63: =IF(G63/F63<0,0,G63/F63) -> 3.0871369 | I63: =F63*J63 -> 200.83333 | J63: 10 | K63: =IF((H63-1+V63)<0,0,H63-1+V63) -> 2.0871369 | L63: =IF((K63-1+W63)<0,0,K63-1+W63) -> 3.8257261 | M63: =IF((L63-1+X63)<0,0,L63-1+X63) -> 2.8257261 | N63: =IF((M63-1+Y63)<0,0,M63-1+Y63) -> 9.9419087 | O63: =IF((N63-1+Z63)<0,0,N63-1+Z63) -> 8.9419087 | P63: =IF((O63-1+AA63)<0,0,O63-1+AA63) -> 7.9419087 | Q63: =T63*F63 -> 41.333333 | S63: =U63*F63 -> 0 | T63: =IF(P63<J63,J63-P63,0) -> 2.0580913 | U63: =IF(N63<3,3-N63,0) -> 0 | V63: {=iferror(XLOOKUP(B63,'INC INV'!AJ:AJ,'INC INV'!AL:AL)/F63,0)} -> 0 | W63: {=IFERROR(XLOOKUP(B63,'INC INV'!AP:AP,'INC INV'!AR:AR)/F63,0)} -> 2.7385892 | X63: {=IFERROR(XLOOKUP(B63,'INC INV'!AV:AV,'INC INV'!AX:AX)/F63,0)} -> 0 | Y63: {=IFERROR(XLOOKUP(B63,'INC INV'!BB:BB,'INC INV'!BD:BD)/F63,0)} -> 8.1161826 | Z63: {=IFERROR(XLOOKUP(B63,'INC INV'!BH:BH,'INC INV'!BJ:BJ)/F63,0)} -> 0 | AA63: {=IFERROR(XLOOKUP(B63,'INC INV'!BN:BN,'INC INV'!BP:BP)/F63,0)} -> 0
A64: Incense-Cone-Aakash-20Pcs | B64: HO0026700002 | C64: INCENSE | D64: {=XLOOKUP(B64,'ORDER LIST'!C:C,'ORDER LIST'!B:B)} -> Incense-Cone-Aakash-20Pcs | F64: {=XLOOKUP(B64,SALES!A:A,SALES!C:C)} -> 54.666667 | G64: {=XLOOKUP(B64,INV!A:A,INV!G:G)} -> 170 | H64: =IF(G64/F64<0,0,G64/F64) -> 3.1097561 | I64: =F64*J64 -> 437.33333 | J64: 8 | K64: =IF((H64-1+V64)<0,0,H64-1+V64) -> 2.1097561 | L64: =IF((K64-1+W64)<0,0,K64-1+W64) -> 7.5121951 | M64: =IF((L64-1+X64)<0,0,L64-1+X64) -> 6.5121951 | N64: =IF((M64-1+Y64)<0,0,M64-1+Y64) -> 8.3109756 | O64: =IF((N64-1+Z64)<0,0,N64-1+Z64) -> 7.3109756 | P64: =IF((O64-1+AA64)<0,0,O64-1+AA64) -> 6.3109756 | Q64: =T64*F64 -> 92.333333 | S64: =U64*F64 -> 0 | T64: =IF(P64<J64,J64-P64,0) -> 1.6890244 | U64: =IF(N64<3,3-N64,0) -> 0 | V64: {=iferror(XLOOKUP(B64,'INC INV'!AJ:AJ,'INC INV'!AL:AL)/F64,0)} -> 0 | W64: {=IFERROR(XLOOKUP(B64,'INC INV'!AP:AP,'INC INV'!AR:AR)/F64,0)} -> 6.402439 | X64: {=IFERROR(XLOOKUP(B64,'INC INV'!AV:AV,'INC INV'!AX:AX)/F64,0)} -> 0 | Y64: {=IFERROR(XLOOKUP(B64,'INC INV'!BB:BB,'INC INV'!BD:BD)/F64,0)} -> 2.7987805 | Z64: {=IFERROR(XLOOKUP(B64,'INC INV'!BH:BH,'INC INV'!BJ:BJ)/F64,0)} -> 0 | AA64: {=IFERROR(XLOOKUP(B64,'INC INV'!BN:BN,'INC INV'!BP:BP)/F64,0)} -> 0
A65: Jala-Neti-Pot-Isha-Logo | B65: YS0007600000 | C65: YOGA STORE | D65: {=XLOOKUP(B65,'ORDER LIST'!C:C,'ORDER LIST'!B:B)} -> Jala-Neti-Pot-Isha-Logo | F65: {=XLOOKUP(B65,SALES!A:A,SALES!C:C)} -> 44.083333 | G65: {=XLOOKUP(B65,INV!A:A,INV!G:G)} -> 143 | H65: =IF(G65/F65<0,0,G65/F65) -> 3.2438563 | I65: =F65*J65 -> 440.83333 | J65: 10 | K65: =IF((H65-1+V65)<0,0,H65-1+V65) -> 2.2438563 | L65: =IF((K65-1+W65)<0,0,K65-1+W65) -> 2.4914934 | M65: =IF((L65-1+X65)<0,0,L65-1+X65) -> 2.6257089 | N65: =IF((M65-1+Y65)<0,0,M65-1+Y65) -> 7.637051 | O65: =IF((N65-1+Z65)<0,0,N65-1+Z65) -> 12.761815 | P65: =IF((O65-1+AA65)<0,0,O65-1+AA65) -> 11.761815 | Q65: =T65*F65 -> 0 | S65: =U65*F65 -> 0 | T65: =IF(P65<J65,J65-P65,0) -> 0 | U65: =IF(N65<3,3-N65,0) -> 0 | V65: {=iferror(XLOOKUP(B65,'INC INV'!AJ:AJ,'INC INV'!AL:AL)/F65,0)} -> 0 | W65: {=IFERROR(XLOOKUP(B65,'INC INV'!AP:AP,'INC INV'!AR:AR)/F65,0)} -> 1.2476371 | X65: {=IFERROR(XLOOKUP(B65,'INC INV'!AV:AV,'INC INV'!AX:AX)/F65,0)} -> 1.1342155 | Y65: {=IFERROR(XLOOKUP(B65,'INC INV'!BB:BB,'INC INV'!BD:BD)/F65,0)} -> 6.0113422 | Z65: {=IFERROR(XLOOKUP(B65,'INC INV'!BH:BH,'INC INV'!BJ:BJ)/F65,0)} -> 6.1247637 | AA65: {=IFERROR(XLOOKUP(B65,'INC INV'!BN:BN,'INC INV'!BP:BP)/F65,0)} -> 0
A66: Turmeric Powder 100g | B66: HI0000106302 | C66: NATURAL FOOD | D66: {=XLOOKUP(B66,'ORDER LIST'!C:C,'ORDER LIST'!B:B)} -> Turmeric Powder 100g | F66: {=XLOOKUP(B66,SALES!A:A,SALES!C:C)} -> 355.83333 | G66: =F66*H66 -> #N/A | H66: {=XLOOKUP(B66,'EXP INV'!Q:Q,'EXP INV'!R:R)} -> #N/A | I66: =F66*J66 -> 2846.6667 | J66: 8 | K66: =IF((H66-1+V66)<0,0,H66-1+V66) -> #N/A | L66: =IF((K66-1+W66)<0,0,K66-1+W66) -> #N/A | M66: =IF((L66-1+X66)<0,0,L66-1+X66) -> #N/A | N66: =IF((M66-1+Y66)<0,0,M66-1+Y66) -> #N/A | O66: =IF((N66-1+Z66)<0,0,N66-1+Z66) -> #N/A | P66: =IF((O66-1+AA66)<0,0,O66-1+AA66) -> #N/A | Q66: =T66*F66 -> #N/A | S66: =U66*F66 -> #N/A | T66: =IF(P66<J66,J66-P66,0) -> #N/A | U66: =IF(N66<3,3-N66,0) -> #N/A | V66: {=iferror(XLOOKUP(B66,'INC INV'!AJ:AJ,'INC INV'!AL:AL)/F66,0)} -> 0 | W66: {=IFERROR(XLOOKUP(B66,'INC INV'!AP:AP,'INC INV'!AR:AR)/F66,0)} -> 1.6861827 | X66: {=IFERROR(XLOOKUP(B66,'INC INV'!AV:AV,'INC INV'!AX:AX)/F66,0)} -> 0 | Y66: {=IFERROR(XLOOKUP(B66,'INC INV'!BB:BB,'INC INV'!BD:BD)/F66,0)} -> 8.1498829 | Z66: {=IFERROR(XLOOKUP(B66,'INC INV'!BH:BH,'INC INV'!BJ:BJ)/F66,0)} -> 0 | AA66: {=IFERROR(XLOOKUP(B66,'INC INV'!BN:BN,'INC INV'!BP:BP)/F66,0)} -> 0
A67: Adiyogi Shawl Cotton | B67: TC0003716600 | C67: CONX | D67: {=XLOOKUP(B67,'ORDER LIST'!C:C,'ORDER LIST'!B:B)} -> Adiyogi Shawl Cotton | F67: {=XLOOKUP(B67,SALES!A:A,SALES!C:C)} -> 36 | G67: {=XLOOKUP(B67,INV!A:A,INV!G:G)} -> 124 | H67: =IF(G67/F67<0,0,G67/F67) -> 3.4444444 | I67: =F67*J67 -> 360 | J67: 10 | K67: =IF((H67-1+V67)<0,0,H67-1+V67) -> 2.4444444 | L67: =IF((K67-1+W67)<0,0,K67-1+W67) -> 1.7777778 | M67: =IF((L67-1+X67)<0,0,L67-1+X67) -> 2.3055556 | N67: =IF((M67-1+Y67)<0,0,M67-1+Y67) -> 10.361111 | O67: =IF((N67-1+Z67)<0,0,N67-1+Z67) -> 10.75 | P67: =IF((O67-1+AA67)<0,0,O67-1+AA67) -> 9.75 | Q67: =T67*F67 -> 9 | S67: =U67*F67 -> 0 | T67: =IF(P67<J67,J67-P67,0) -> 0.25 | U67: =IF(N67<3,3-N67,0) -> 0 | V67: {=iferror(XLOOKUP(B67,'INC INV'!AJ:AJ,'INC INV'!AL:AL)/F67,0)} -> 0 | W67: {=IFERROR(XLOOKUP(B67,'INC INV'!AP:AP,'INC INV'!AR:AR)/F67,0)} -> 0.33333333 | X67: {=IFERROR(XLOOKUP(B67,'INC INV'!AV:AV,'INC INV'!AX:AX)/F67,0)} -> 1.5277778 | Y67: {=IFERROR(XLOOKUP(B67,'INC INV'!BB:BB,'INC INV'!BD:BD)/F67,0)} -> 9.0555556 | Z67: {=IFERROR(XLOOKUP(B67,'INC INV'!BH:BH,'INC INV'!BJ:BJ)/F67,0)} -> 1.3888889 | AA67: {=IFERROR(XLOOKUP(B67,'INC INV'!BN:BN,'INC INV'!BP:BP)/F67,0)} -> 0
A68: AY406 Adiyogi Photo (16x24) | B68: ME0015712200 | C68: PHOTO | D68: {=XLOOKUP(B68,'ORDER LIST'!C:C,'ORDER LIST'!B:B)} -> AY406 Adiyogi Photo (16x24) | E68: WAREHOUSE SPACE | F68: 4 | G68: {=XLOOKUP(B68,INV!A:A,INV!G:G)} -> 0 | H68: =IF(G68/F68<0,0,G68/F68) -> 0 | I68: =F68*J68 -> 32 | J68: 8 | K68: =IF((H68-1+V68)<0,0,H68-1+V68) -> 2.75 | L68: =IF((K68-1+W68)<0,0,K68-1+W68) -> 8 | M68: =IF((L68-1+X68)<0,0,L68-1+X68) -> 7 | N68: =IF((M68-1+Y68)<0,0,M68-1+Y68) -> 8 | O68: =IF((N68-1+Z68)<0,0,N68-1+Z68) -> 7 | P68: =IF((O68-1+AA68)<0,0,O68-1+AA68) -> 6 | Q68: =T68*F68 -> 8 | S68: =U68*F68 -> 0 | T68: =IF(P68<J68,J68-P68,0) -> 2 | U68: =IF(N68<3,3-N68,0) -> 0 | V68: {=iferror(XLOOKUP(B68,'INC INV'!AJ:AJ,'INC INV'!AL:AL)/F68,0)} -> 3.75 | W68: {=IFERROR(XLOOKUP(B68,'INC INV'!AP:AP,'INC INV'!AR:AR)/F68,0)} -> 6.25 | X68: {=IFERROR(XLOOKUP(B68,'INC INV'!AV:AV,'INC INV'!AX:AX)/F68,0)} -> 0 | Y68: {=IFERROR(XLOOKUP(B68,'INC INV'!BB:BB,'INC INV'!BD:BD)/F68,0)} -> 2 | Z68: {=IFERROR(XLOOKUP(B68,'INC INV'!BH:BH,'INC INV'!BJ:BJ)/F68,0)} -> 0 | AA68: {=IFERROR(XLOOKUP(B68,'INC INV'!BN:BN,'INC INV'!BP:BP)/F68,0)} -> 0
A69: SE905 Sadhguru Photo (12x18) | B69: ME0026511500 | C69: PHOTO | D69: {=XLOOKUP(B69,'ORDER LIST'!C:C,'ORDER LIST'!B:B)} -> SE905 Sadhguru Photo (12x18) | E69: {=XLOOKUP(B69,'PRICE LIST'!E:E,#REF!)} -> #N/A | F69: 4 | G69: {=XLOOKUP(B69,INV!A:A,INV!G:G)} -> 10 | H69: =IF(G69/F69<0,0,G69/F69) -> 2.5 | I69: =F69*J69 -> 32 | J69: 8 | K69: =IF((H69-1+V69)<0,0,H69-1+V69) -> 2.75 | L69: =IF((K69-1+W69)<0,0,K69-1+W69) -> 8 | M69: =IF((L69-1+X69)<0,0,L69-1+X69) -> 7 | N69: =IF((M69-1+Y69)<0,0,M69-1+Y69) -> 8.75 | O69: =IF((N69-1+Z69)<0,0,N69-1+Z69) -> 7.75 | P69: =IF((O69-1+AA69)<0,0,O69-1+AA69) -> 6.75 | Q69: =T69*F69 -> 5 | S69: =U69*F69 -> 0 | T69: =IF(P69<J69,J69-P69,0) -> 1.25 | U69: =IF(N69<3,3-N69,0) -> 0 | V69: {=iferror(XLOOKUP(B69,'INC INV'!AJ:AJ,'INC INV'!AL:AL)/F69,0)} -> 1.25 | W69: {=IFERROR(XLOOKUP(B69,'INC INV'!AP:AP,'INC INV'!AR:AR)/F69,0)} -> 6.25 | X69: {=IFERROR(XLOOKUP(B69,'INC INV'!AV:AV,'INC INV'!AX:AX)/F69,0)} -> 0 | Y69: {=IFERROR(XLOOKUP(B69,'INC INV'!BB:BB,'INC INV'!BD:BD)/F69,0)} -> 2.75 | Z69: {=IFERROR(XLOOKUP(B69,'INC INV'!BH:BH,'INC INV'!BJ:BJ)/F69,0)} -> 0 | AA69: {=IFERROR(XLOOKUP(B69,'INC INV'!BN:BN,'INC INV'!BP:BP)/F69,0)} -> 0
A70: SJ505 Sadhguru Photo (12x18) | B70: ME0029311500 | C70: PHOTO | D70: {=XLOOKUP(B70,'ORDER LIST'!C:C,'ORDER LIST'!B:B)} -> SJ505 Sadhguru Photo (12x18) | E70: {=XLOOKUP(B70,'PRICE LIST'!E:E,#REF!)} -> #N/A | F70: 4 | G70: {=XLOOKUP(B70,INV!A:A,INV!G:G)} -> 10 | H70: =IF(G70/F70<0,0,G70/F70) -> 2.5 | I70: =F70*J70 -> 32 | J70: 8 | K70: =IF((H70-1+V70)<0,0,H70-1+V70) -> 2.75 | L70: =IF((K70-1+W70)<0,0,K70-1+W70) -> 8 | M70: =IF((L70-1+X70)<0,0,L70-1+X70) -> 7 | N70: =IF((M70-1+Y70)<0,0,M70-1+Y70) -> 8.75 | O70: =IF((N70-1+Z70)<0,0,N70-1+Z70) -> 7.75 | P70: =IF((O70-1+AA70)<0,0,O70-1+AA70) -> 6.75 | Q70: =T70*F70 -> 5 | S70: =U70*F70 -> 0 | T70: =IF(P70<J70,J70-P70,0) -> 1.25 | U70: =IF(N70<3,3-N70,0) -> 0 | V70: {=iferror(XLOOKUP(B70,'INC INV'!AJ:AJ,'INC INV'!AL:AL)/F70,0)} -> 1.25 | W70: {=IFERROR(XLOOKUP(B70,'INC INV'!AP:AP,'INC INV'!AR:AR)/F70,0)} -> 6.25 | X70: {=IFERROR(XLOOKUP(B70,'INC INV'!AV:AV,'INC INV'!AX:AX)/F70,0)} -> 0 | Y70: {=IFERROR(XLOOKUP(B70,'INC INV'!BB:BB,'INC INV'!BD:BD)/F70,0)} -> 2.75 | Z70: {=IFERROR(XLOOKUP(B70,'INC INV'!BH:BH,'INC INV'!BJ:BJ)/F70,0)} -> 0 | AA70: {=IFERROR(XLOOKUP(B70,'INC INV'!BN:BN,'INC INV'!BP:BP)/F70,0)} -> 0
A71: English Mystics Musings Soft | B71: ME0004001500 | C71: BOOK | D71: {=XLOOKUP(B71,'ORDER LIST'!C:C,'ORDER LIST'!B:B)} -> English Mystics Musings Soft | F71: {=XLOOKUP(B71,SALES!A:A,SALES!C:C)} -> 40.25 | G71: {=XLOOKUP(B71,INV!A:A,INV!G:G)} -> 152 | H71: =IF(G71/F71<0,0,G71/F71) -> 3.7763975 | I71: =F71*J71 -> 322 | J71: 8 | K71: =IF((H71-1+V71)<0,0,H71-1+V71) -> 2.7763975 | L71: =IF((K71-1+W71)<0,0,K71-1+W71) -> 1.7763975 | M71: =IF((L71-1+X71)<0,0,L71-1+X71) -> 0.77639752 | N71: =IF((M71-1+Y71)<0,0,M71-1+Y71) -> 4.0745342 | O71: =IF((N71-1+Z71)<0,0,N71-1+Z71) -> 5.4347826 | P71: =IF((O71-1+AA71)<0,0,O71-1+AA71) -> 4.4347826 | Q71: =T71*F71 -> 143.5 | S71: =U71*F71 -> 0 | T71: =IF(P71<J71,J71-P71,0) -> 3.5652174 | U71: =IF(N71<3,3-N71,0) -> 0 | V71: {=iferror(XLOOKUP(B71,'INC INV'!AJ:AJ,'INC INV'!AL:AL)/F71,0)} -> 0 | W71: {=IFERROR(XLOOKUP(B71,'INC INV'!AP:AP,'INC INV'!AR:AR)/F71,0)} -> 0 | X71: {=IFERROR(XLOOKUP(B71,'INC INV'!AV:AV,'INC INV'!AX:AX)/F71,0)} -> 0 | Y71: {=IFERROR(XLOOKUP(B71,'INC INV'!BB:BB,'INC INV'!BD:BD)/F71,0)} -> 4.2981366 | Z71: {=IFERROR(XLOOKUP(B71,'INC INV'!BH:BH,'INC INV'!BJ:BJ)/F71,0)} -> 2.3602484 | AA71: {=IFERROR(XLOOKUP(B71,'INC INV'!BN:BN,'INC INV'!BP:BP)/F71,0)} -> 0
A72: SG-Photos-Kailash-8 | B72: ME0027210100 | C72: PHOTO | E72: {=XLOOKUP(B72,'PRICE LIST'!E:E,#REF!)} -> #N/A | F72: {=XLOOKUP(B72,SALES!A:A,SALES!C:C)} -> 2.5 | G72: {=XLOOKUP(B72,INV!A:A,INV!G:G)} -> 10 | H72: =IF(G72/F72<0,0,G72/F72) -> 4 | I72: =F72*J72 -> 20 | J72: 8 | K72: =IF((H72-1+V72)<0,0,H72-1+V72) -> 3 | L72: =IF((K72-1+W72)<0,0,K72-1+W72) -> 2.8 | M72: =IF((L72-1+X72)<0,0,L72-1+X72) -> 1.8 | N72: =IF((M72-1+Y72)<0,0,M72-1+Y72) -> 6.4 | O72: =IF((N72-1+Z72)<0,0,N72-1+Z72) -> 5.4 | P72: =IF((O72-1+AA72)<0,0,O72-1+AA72) -> 4.4 | Q72: =T72*F72 -> 9 | S72: =U72*F72 -> 0 | T72: =IF(P72<J72,J72-P72,0) -> 3.6 | U72: =IF(N72<3,3-N72,0) -> 0 | V72: {=iferror(XLOOKUP(B72,'INC INV'!AJ:AJ,'INC INV'!AL:AL)/F72,0)} -> 0 | W72: {=IFERROR(XLOOKUP(B72,'INC INV'!AP:AP,'INC INV'!AR:AR)/F72,0)} -> 0.8 | X72: {=IFERROR(XLOOKUP(B72,'INC INV'!AV:AV,'INC INV'!AX:AX)/F72,0)} -> 0 | Y72: {=IFERROR(XLOOKUP(B72,'INC INV'!BB:BB,'INC INV'!BD:BD)/F72,0)} -> 5.6 | Z72: {=IFERROR(XLOOKUP(B72,'INC INV'!BH:BH,'INC INV'!BJ:BJ)/F72,0)} -> 0 | AA72: {=IFERROR(XLOOKUP(B72,'INC INV'!BN:BN,'INC INV'!BP:BP)/F72,0)} -> 0
A73: Devi Mukha | B73: TC0017400000 | C73: CONX | D73: {=XLOOKUP(B73,'ORDER LIST'!C:C,'ORDER LIST'!B:B)} -> Devi Mukha | E73: WAREHOUSE SPACE | F73: 1.5 | G73: {=XLOOKUP(B73,INV!A:A,INV!G:G)} -> 0 | H73: =IF(G73/F73<0,0,G73/F73) -> 0 | I73: =F73*J73 -> 15 | J73: 10 | K73: =IF((H73-1+V73)<0,0,H73-1+V73) -> 3 | L73: =IF((K73-1+W73)<0,0,K73-1+W73) -> 12 | M73: =IF((L73-1+X73)<0,0,L73-1+X73) -> 11 | N73: =IF((M73-1+Y73)<0,0,M73-1+Y73) -> 10 | O73: =IF((N73-1+Z73)<0,0,N73-1+Z73) -> 9 | P73: =IF((O73-1+AA73)<0,0,O73-1+AA73) -> 8 | Q73: =T73*F73 -> 3 | S73: =U73*F73 -> 0 | T73: =IF(P73<J73,J73-P73,0) -> 2 | U73: =IF(N73<3,3-N73,0) -> 0 | V73: {=iferror(XLOOKUP(B73,'INC INV'!AJ:AJ,'INC INV'!AL:AL)/F73,0)} -> 4 | W73: {=IFERROR(XLOOKUP(B73,'INC INV'!AP:AP,'INC INV'!AR:AR)/F73,0)} -> 10 | X73: {=IFERROR(XLOOKUP(B73,'INC INV'!AV:AV,'INC INV'!AX:AX)/F73,0)} -> 0 | Y73: {=IFERROR(XLOOKUP(B73,'INC INV'!BB:BB,'INC INV'!BD:BD)/F73,0)} -> 0 | Z73: {=IFERROR(XLOOKUP(B73,'INC INV'!BH:BH,'INC INV'!BJ:BJ)/F73,0)} -> 0 | AA73: {=IFERROR(XLOOKUP(B73,'INC INV'!BN:BN,'INC INV'!BP:BP)/F73,0)} -> 0
A74: Linga Bhairavi Metal Keychain | B74: HO0110400000 | C74: ACCESSORY | D74: {=XLOOKUP(B74,'ORDER LIST'!C:C,'ORDER LIST'!B:B)} -> Linga Bhairavi Metal Keychain | F74: 10 | G74: {=XLOOKUP(B74,INV!A:A,INV!G:G)} -> 40 | H74: =IF(G74/F74<0,0,G74/F74) -> 4 | I74: =F74*J74 -> 60 | J74: 6 | K74: =IF((H74-1+V74)<0,0,H74-1+V74) -> 3 | L74: =IF((K74-1+W74)<0,0,K74-1+W74) -> 27 | M74: =IF((L74-1+X74)<0,0,L74-1+X74) -> 26 | N74: =IF((M74-1+Y74)<0,0,M74-1+Y74) -> 25 | O74: =IF((N74-1+Z74)<0,0,N74-1+Z74) -> 24 | P74: =IF((O74-1+AA74)<0,0,O74-1+AA74) -> 23 | Q74: =T74*F74 -> 0 | S74: =U74*F74 -> 0 | T74: =IF(P74<J74,J74-P74,0) -> 0 | U74: =IF(N74<3,3-N74,0) -> 0 | V74: {=iferror(XLOOKUP(B74,'INC INV'!AJ:AJ,'INC INV'!AL:AL)/F74,0)} -> 0 | W74: {=IFERROR(XLOOKUP(B74,'INC INV'!AP:AP,'INC INV'!AR:AR)/F74,0)} -> 25 | X74: {=IFERROR(XLOOKUP(B74,'INC INV'!AV:AV,'INC INV'!AX:AX)/F74,0)} -> 0 | Y74: {=IFERROR(XLOOKUP(B74,'INC INV'!BB:BB,'INC INV'!BD:BD)/F74,0)} -> 0 | Z74: {=IFERROR(XLOOKUP(B74,'INC INV'!BH:BH,'INC INV'!BJ:BJ)/F74,0)} -> 0 | AA74: {=IFERROR(XLOOKUP(B74,'INC INV'!BN:BN,'INC INV'!BP:BP)/F74,0)} -> 0
A75: Charcoal Tablets for Sambrani/Dhoop | B75: HO0107700000 | C75: INCENSE | D75: {=XLOOKUP(B75,'ORDER LIST'!C:C,'ORDER LIST'!B:B)} -> Charcoal Tablets for Sambrani/Dhoop | F75: 10 | G75: {=XLOOKUP(B75,INV!A:A,INV!G:G)} -> 40 | H75: =IF(G75/F75<0,0,G75/F75) -> 4 | I75: =F75*J75 -> 80 | J75: 8 | K75: =IF((H75-1+V75)<0,0,H75-1+V75) -> 3 | L75: =IF((K75-1+W75)<0,0,K75-1+W75) -> 12 | M75: =IF((L75-1+X75)<0,0,L75-1+X75) -> 11 | N75: =IF((M75-1+Y75)<0,0,M75-1+Y75) -> 10 | O75: =IF((N75-1+Z75)<0,0,N75-1+Z75) -> 9 | P75: =IF((O75-1+AA75)<0,0,O75-1+AA75) -> 8 | Q75: =T75*F75 -> 0 | S75: =U75*F75 -> 0 | T75: =IF(P75<J75,J75-P75,0) -> 0 | U75: =IF(N75<3,3-N75,0) -> 0 | V75: {=iferror(XLOOKUP(B75,'INC INV'!AJ:AJ,'INC INV'!AL:AL)/F75,0)} -> 0 | W75: {=IFERROR(XLOOKUP(B75,'INC INV'!AP:AP,'INC INV'!AR:AR)/F75,0)} -> 10 | X75: {=IFERROR(XLOOKUP(B75,'INC INV'!AV:AV,'INC INV'!AX:AX)/F75,0)} -> 0 | Y75: {=IFERROR(XLOOKUP(B75,'INC INV'!BB:BB,'INC INV'!BD:BD)/F75,0)} -> 0 | Z75: {=IFERROR(XLOOKUP(B75,'INC INV'!BH:BH,'INC INV'!BJ:BJ)/F75,0)} -> 0 | AA75: {=IFERROR(XLOOKUP(B75,'INC INV'!BN:BN,'INC INV'!BP:BP)/F75,0)} -> 0
A76: Adiyogi Arpanam Incense Gift Set | B76: CO0008100002 | C76: INCENSE | D76: {=XLOOKUP(B76,'ORDER LIST'!C:C,'ORDER LIST'!B:B)} -> Adiyogi Arpanam Incense Gift Set | F76: 10 | G76: {=XLOOKUP(B76,INV!A:A,INV!G:G)} -> 10 | H76: =IF(G76/F76<0,0,G76/F76) -> 1 | I76: =F76*J76 -> 80 | J76: 8 | K76: =IF((H76-1+V76)<0,0,H76-1+V76) -> 3 | L76: =IF((K76-1+W76)<0,0,K76-1+W76) -> 34.5 | M76: =IF((L76-1+X76)<0,0,L76-1+X76) -> 33.5 | N76: =IF((M76-1+Y76)<0,0,M76-1+Y76) -> 32.5 | O76: =IF((N76-1+Z76)<0,0,N76-1+Z76) -> 31.5 | P76: =IF((O76-1+AA76)<0,0,O76-1+AA76) -> 30.5 | Q76: =T76*F76 -> 0 | S76: =U76*F76 -> 0 | T76: =IF(P76<J76,J76-P76,0) -> 0 | U76: =IF(N76<3,3-N76,0) -> 0 | V76: {=iferror(XLOOKUP(B76,'INC INV'!AJ:AJ,'INC INV'!AL:AL)/F76,0)} -> 3 | W76: {=IFERROR(XLOOKUP(B76,'INC INV'!AP:AP,'INC INV'!AR:AR)/F76,0)} -> 32.5 | X76: {=IFERROR(XLOOKUP(B76,'INC INV'!AV:AV,'INC INV'!AX:AX)/F76,0)} -> 0 | Y76: {=IFERROR(XLOOKUP(B76,'INC INV'!BB:BB,'INC INV'!BD:BD)/F76,0)} -> 0 | Z76: {=IFERROR(XLOOKUP(B76,'INC INV'!BH:BH,'INC INV'!BJ:BJ)/F76,0)} -> 0 | AA76: {=IFERROR(XLOOKUP(B76,'INC INV'!BN:BN,'INC INV'!BP:BP)/F76,0)} -> 0
A77: Devi Shawl Cotton Gold Writing English | B77: TC0004016600 | C77: CONX | D77: {=XLOOKUP(B77,'ORDER LIST'!C:C,'ORDER LIST'!B:B)} -> Devi Shawl Cotton Gold Writing | F77: 61 | G77: {=XLOOKUP(B77,INV!A:A,INV!G:G)} -> 245 | H77: =IF(G77/F77<0,0,G77/F77) -> 4.0163934 | I77: =F77*J77 -> 610 | J77: 10 | K77: =IF((H77-1+V77)<0,0,H77-1+V77) -> 3.0163934 | L77: =IF((K77-1+W77)<0,0,K77-1+W77) -> 9.7377049 | M77: =IF((L77-1+X77)<0,0,L77-1+X77) -> 8.7377049 | N77: =IF((M77-1+Y77)<0,0,M77-1+Y77) -> 14.213115 | O77: =IF((N77-1+Z77)<0,0,N77-1+Z77) -> 13.213115 | P77: =IF((O77-1+AA77)<0,0,O77-1+AA77) -> 12.213115 | Q77: =T77*F77 -> 0 | S77: =U77*F77 -> 0 | T77: =IF(P77<J77,J77-P77,0) -> 0 | U77: =IF(N77<3,3-N77,0) -> 0 | V77: {=iferror(XLOOKUP(B77,'INC INV'!AJ:AJ,'INC INV'!AL:AL)/F77,0)} -> 0 | W77: {=IFERROR(XLOOKUP(B77,'INC INV'!AP:AP,'INC INV'!AR:AR)/F77,0)} -> 7.7213115 | X77: {=IFERROR(XLOOKUP(B77,'INC INV'!AV:AV,'INC INV'!AX:AX)/F77,0)} -> 0 | Y77: {=IFERROR(XLOOKUP(B77,'INC INV'!BB:BB,'INC INV'!BD:BD)/F77,0)} -> 6.4754098 | Z77: {=IFERROR(XLOOKUP(B77,'INC INV'!BH:BH,'INC INV'!BJ:BJ)/F77,0)} -> 0 | AA77: {=IFERROR(XLOOKUP(B77,'INC INV'!BN:BN,'INC INV'!BP:BP)/F77,0)} -> 0
A78: Kumkum | B78: TC0005700400 | C78: CONX | D78: {=XLOOKUP(B78,'ORDER LIST'!C:C,'ORDER LIST'!B:B)} -> Kumkum | E78: L | F78: {=XLOOKUP(B78,SALES!A:A,SALES!C:C)} -> 127.58333 | G78: {=XLOOKUP(B78,INV!A:A,INV!G:G)} -> 527 | H78: =IF(G78/F78<0,0,G78/F78) -> 4.1306336 | I78: =F78*J78 -> 1275.8333 | J78: 10 | K78: =IF((H78-1+V78)<0,0,H78-1+V78) -> 3.1306336 | L78: =IF((K78-1+W78)<0,0,K78-1+W78) -> 6.0339647 | M78: =IF((L78-1+X78)<0,0,L78-1+X78) -> 5.0339647 | N78: =IF((M78-1+Y78)<0,0,M78-1+Y78) -> 11.370346 | O78: =IF((N78-1+Z78)<0,0,N78-1+Z78) -> 10.370346 | P78: =IF((O78-1+AA78)<0,0,O78-1+AA78) -> 9.3703462 | Q78: =T78*F78 -> 80.333333 | S78: =U78*F78 -> 0 | T78: =IF(P78<J78,J78-P78,0) -> 0.62965382 | U78: =IF(N78<3,3-N78,0) -> 0 | V78: {=iferror(XLOOKUP(B78,'INC INV'!AJ:AJ,'INC INV'!AL:AL)/F78,0)} -> 0 | W78: {=IFERROR(XLOOKUP(B78,'INC INV'!AP:AP,'INC INV'!AR:AR)/F78,0)} -> 3.9033312 | X78: {=IFERROR(XLOOKUP(B78,'INC INV'!AV:AV,'INC INV'!AX:AX)/F78,0)} -> 0 | Y78: {=IFERROR(XLOOKUP(B78,'INC INV'!BB:BB,'INC INV'!BD:BD)/F78,0)} -> 7.3363815 | Z78: {=IFERROR(XLOOKUP(B78,'INC INV'!BH:BH,'INC INV'!BJ:BJ)/F78,0)} -> 0 | AA78: {=IFERROR(XLOOKUP(B78,'INC INV'!BN:BN,'INC INV'!BP:BP)/F78,0)} -> 0
A79: Adiyogi Bucket Hat - Beige M | B79: CA0154900300 | C79: CLOTHING | D79: {=XLOOKUP(B79,'ORDER LIST'!C:C,'ORDER LIST'!B:B)} -> Adiyogi Bucket Hat - Beige M | F79: 10 | G79: {=XLOOKUP(B79,INV!A:A,INV!G:G)} -> 42 | H79: =IF(G79/F79<0,0,G79/F79) -> 4.2 | I79: =F79*J79 -> 60 | J79: 6 | K79: =IF((H79-1+V79)<0,0,H79-1+V79) -> 3.2 | L79: =IF((K79-1+W79)<0,0,K79-1+W79) -> 2.7 | M79: =IF((L79-1+X79)<0,0,L79-1+X79) -> 1.7 | N79: =IF((M79-1+Y79)<0,0,M79-1+Y79) -> 4.2 | O79: =IF((N79-1+Z79)<0,0,N79-1+Z79) -> 3.2 | P79: =IF((O79-1+AA79)<0,0,O79-1+AA79) -> 2.2 | Q79: =T79*F79 -> 38 | S79: =U79*F79 -> 0 | T79: =IF(P79<J79,J79-P79,0) -> 3.8 | U79: =IF(N79<3,3-N79,0) -> 0 | V79: {=iferror(XLOOKUP(B79,'INC INV'!AJ:AJ,'INC INV'!AL:AL)/F79,0)} -> 0 | W79: {=IFERROR(XLOOKUP(B79,'INC INV'!AP:AP,'INC INV'!AR:AR)/F79,0)} -> 0.5 | X79: {=IFERROR(XLOOKUP(B79,'INC INV'!AV:AV,'INC INV'!AX:AX)/F79,0)} -> 0 | Y79: {=IFERROR(XLOOKUP(B79,'INC INV'!BB:BB,'INC INV'!BD:BD)/F79,0)} -> 3.5 | Z79: {=IFERROR(XLOOKUP(B79,'INC INV'!BH:BH,'INC INV'!BJ:BJ)/F79,0)} -> 0 | AA79: {=IFERROR(XLOOKUP(B79,'INC INV'!BN:BN,'INC INV'!BP:BP)/F79,0)} -> 0
A80: Incense-Stick-Vetiver-10 | B80: HO0028617002 | C80: INCENSE | D80: {=XLOOKUP(B80,'ORDER LIST'!C:C,'ORDER LIST'!B:B)} -> Incense-Stick-Vetiver-10 | F80: {=XLOOKUP(B80,SALES!A:A,SALES!C:C)} -> 63.5 | G80: {=XLOOKUP(B80,INV!A:A,INV!G:G)} -> 283 | H80: =IF(G80/F80<0,0,G80/F80) -> 4.4566929 | I80: =F80*J80 -> 508 | J80: 8 | K80: =IF((H80-1+V80)<0,0,H80-1+V80) -> 3.4566929 | L80: =IF((K80-1+W80)<0,0,K80-1+W80) -> 5.9212598 | M80: =IF((L80-1+X80)<0,0,L80-1+X80) -> 4.9212598 | N80: =IF((M80-1+Y80)<0,0,M80-1+Y80) -> 6.7244094 | O80: =IF((N80-1+Z80)<0,0,N80-1+Z80) -> 6.4330709 | P80: =IF((O80-1+AA80)<0,0,O80-1+AA80) -> 5.4330709 | Q80: =T80*F80 -> 163 | S80: =U80*F80 -> 0 | T80: =IF(P80<J80,J80-P80,0) -> 2.5669291 | U80: =IF(N80<3,3-N80,0) -> 0 | V80: {=iferror(XLOOKUP(B80,'INC INV'!AJ:AJ,'INC INV'!AL:AL)/F80,0)} -> 0 | W80: {=IFERROR(XLOOKUP(B80,'INC INV'!AP:AP,'INC INV'!AR:AR)/F80,0)} -> 3.4645669 | X80: {=IFERROR(XLOOKUP(B80,'INC INV'!AV:AV,'INC INV'!AX:AX)/F80,0)} -> 0 | Y80: {=IFERROR(XLOOKUP(B80,'INC INV'!BB:BB,'INC INV'!BD:BD)/F80,0)} -> 2.8031496 | Z80: {=IFERROR(XLOOKUP(B80,'INC INV'!BH:BH,'INC INV'!BJ:BJ)/F80,0)} -> 0.70866142 | AA80: {=IFERROR(XLOOKUP(B80,'INC INV'!BN:BN,'INC INV'!BP:BP)/F80,0)} -> 0
A81: Hammered-Copper-Uruli-Small | B81: HO0080600000 | C81: CRAFT | D81: {=XLOOKUP(B81,'ORDER LIST'!C:C,'ORDER LIST'!B:B)} -> Hammered-Copper-Uruli-Small | F81: 10 | G81: {=XLOOKUP(B81,INV!A:A,INV!G:G)} -> 46 | H81: =IF(G81/F81<0,0,G81/F81) -> 4.6 | I81: =F81*J81 -> 80 | J81: 8 | K81: =IF((H81-1+V81)<0,0,H81-1+V81) -> 3.6 | L81: =IF((K81-1+W81)<0,0,K81-1+W81) -> 6.1 | M81: =IF((L81-1+X81)<0,0,L81-1+X81) -> 5.1 | N81: =IF((M81-1+Y81)<0,0,M81-1+Y81) -> 9.6 | O81: =IF((N81-1+Z81)<0,0,N81-1+Z81) -> 8.6 | P81: =IF((O81-1+AA81)<0,0,O81-1+AA81) -> 7.6 | Q81: =T81*F81 -> 4 | S81: =U81*F81 -> 0 | T81: =IF(P81<J81,J81-P81,0) -> 0.4 | U81: =IF(N81<3,3-N81,0) -> 0 | V81: {=iferror(XLOOKUP(B81,'INC INV'!AJ:AJ,'INC INV'!AL:AL)/F81,0)} -> 0 | W81: {=IFERROR(XLOOKUP(B81,'INC INV'!AP:AP,'INC INV'!AR:AR)/F81,0)} -> 3.5 | X81: {=IFERROR(XLOOKUP(B81,'INC INV'!AV:AV,'INC INV'!AX:AX)/F81,0)} -> 0 | Y81: {=IFERROR(XLOOKUP(B81,'INC INV'!BB:BB,'INC INV'!BD:BD)/F81,0)} -> 5.5 | Z81: {=IFERROR(XLOOKUP(B81,'INC INV'!BH:BH,'INC INV'!BJ:BJ)/F81,0)} -> 0 | AA81: {=IFERROR(XLOOKUP(B81,'INC INV'!BN:BN,'INC INV'!BP:BP)/F81,0)} -> 0
A82: Photos-DL-Black-Background | B82: ME0018009000 | C82: PHOTO | D82: {=XLOOKUP(B82,'ORDER LIST'!C:C,'ORDER LIST'!B:B)} -> Photos-DL-Black-Background | E82: {=XLOOKUP(B82,'PRICE LIST'!E:E,#REF!)} -> #N/A | F82: {=XLOOKUP(B82,SALES!A:A,SALES!C:C)} -> 2.1666667 | G82: {=XLOOKUP(B82,INV!A:A,INV!G:G)} -> 10 | H82: =IF(G82/F82<0,0,G82/F82) -> 4.6153846 | I82: =F82*J82 -> 17.333333 | J82: 8 | K82: =IF((H82-1+V82)<0,0,H82-1+V82) -> 3.6153846 | L82: =IF((K82-1+W82)<0,0,K82-1+W82) -> 2.6153846 | M82: =IF((L82-1+X82)<0,0,L82-1+X82) -> 1.6153846 | N82: =IF((M82-1+Y82)<0,0,M82-1+Y82) -> 5.6923077 | O82: =IF((N82-1+Z82)<0,0,N82-1+Z82) -> 4.6923077 | P82: =IF((O82-1+AA82)<0,0,O82-1+AA82) -> 3.6923077 | Q82: =T82*F82 -> 9.3333333 | S82: =U82*F82 -> 0 | T82: =IF(P82<J82,J82-P82,0) -> 4.3076923 | U82: =IF(N82<3,3-N82,0) -> 0 | V82: {=iferror(XLOOKUP(B82,'INC INV'!AJ:AJ,'INC INV'!AL:AL)/F82,0)} -> 0 | W82: {=IFERROR(XLOOKUP(B82,'INC INV'!AP:AP,'INC INV'!AR:AR)/F82,0)} -> 0 | X82: {=IFERROR(XLOOKUP(B82,'INC INV'!AV:AV,'INC INV'!AX:AX)/F82,0)} -> 0 | Y82: {=IFERROR(XLOOKUP(B82,'INC INV'!BB:BB,'INC INV'!BD:BD)/F82,0)} -> 5.0769231 | Z82: {=IFERROR(XLOOKUP(B82,'INC INV'!BH:BH,'INC INV'!BJ:BJ)/F82,0)} -> 0 | AA82: {=IFERROR(XLOOKUP(B82,'INC INV'!BN:BN,'INC INV'!BP:BP)/F82,0)} -> 0
A83: Jai Bhairavi Devi Copper Cuff | B83: CA0019900009 | C83: JEWELRY | D83: {=XLOOKUP(B83,'ORDER LIST'!C:C,'ORDER LIST'!B:B)} -> Jai Bhairavi Devi Copper Cuff | F83: {=XLOOKUP(B83,SALES!A:A,SALES!C:C)} -> 40.25 | G83: {=XLOOKUP(B83,INV!A:A,INV!G:G)} -> 193 | H83: =IF(G83/F83<0,0,G83/F83) -> 4.7950311 | I83: =F83*J83 -> 322 | J83: 8 | K83: =IF((H83-1+V83)<0,0,H83-1+V83) -> 3.7950311 | L83: =IF((K83-1+W83)<0,0,K83-1+W83) -> 4.6583851 | M83: =IF((L83-1+X83)<0,0,L83-1+X83) -> 3.6583851 | N83: =IF((M83-1+Y83)<0,0,M83-1+Y83) -> 8.5465839 | O83: =IF((N83-1+Z83)<0,0,N83-1+Z83) -> 8.0434783 | P83: =IF((O83-1+AA83)<0,0,O83-1+AA83) -> 7.0434783 | Q83: =T83*F83 -> 38.5 | S83: =U83*F83 -> 0 | T83: =IF(P83<J83,J83-P83,0) -> 0.95652174 | U83: =IF(N83<3,3-N83,0) -> 0 | V83: {=iferror(XLOOKUP(B83,'INC INV'!AJ:AJ,'INC INV'!AL:AL)/F83,0)} -> 0 | W83: {=IFERROR(XLOOKUP(B83,'INC INV'!AP:AP,'INC INV'!AR:AR)/F83,0)} -> 1.863354 | X83: {=IFERROR(XLOOKUP(B83,'INC INV'!AV:AV,'INC INV'!AX:AX)/F83,0)} -> 0 | Y83: {=IFERROR(XLOOKUP(B83,'INC INV'!BB:BB,'INC INV'!BD:BD)/F83,0)} -> 5.8881988 | Z83: {=IFERROR(XLOOKUP(B83,'INC INV'!BH:BH,'INC INV'!BJ:BJ)/F83,0)} -> 0.49689441 | AA83: {=IFERROR(XLOOKUP(B83,'INC INV'!BN:BN,'INC INV'!BP:BP)/F83,0)} -> 0
A84: Hammered Copper Uruli Medium | B84: HO0080500000 | C84: CRAFT | D84: {=XLOOKUP(B84,'ORDER LIST'!C:C,'ORDER LIST'!B:B)} -> Hammered Copper Uruli Medium | F84: 10 | G84: {=XLOOKUP(B84,INV!A:A,INV!G:G)} -> 48 | H84: =IF(G84/F84<0,0,G84/F84) -> 4.8 | I84: =F84*J84 -> 80 | J84: 8 | K84: =IF((H84-1+V84)<0,0,H84-1+V84) -> 3.8 | L84: =IF((K84-1+W84)<0,0,K84-1+W84) -> 6.3 | M84: =IF((L84-1+X84)<0,0,L84-1+X84) -> 5.3 | N84: =IF((M84-1+Y84)<0,0,M84-1+Y84) -> 9.8 | O84: =IF((N84-1+Z84)<0,0,N84-1+Z84) -> 8.8 | P84: =IF((O84-1+AA84)<0,0,O84-1+AA84) -> 7.8 | Q84: =T84*F84 -> 2 | S84: =U84*F84 -> 0 | T84: =IF(P84<J84,J84-P84,0) -> 0.2 | U84: =IF(N84<3,3-N84,0) -> 0 | V84: {=iferror(XLOOKUP(B84,'INC INV'!AJ:AJ,'INC INV'!AL:AL)/F84,0)} -> 0 | W84: {=IFERROR(XLOOKUP(B84,'INC INV'!AP:AP,'INC INV'!AR:AR)/F84,0)} -> 3.5 | X84: {=IFERROR(XLOOKUP(B84,'INC INV'!AV:AV,'INC INV'!AX:AX)/F84,0)} -> 0 | Y84: {=IFERROR(XLOOKUP(B84,'INC INV'!BB:BB,'INC INV'!BD:BD)/F84,0)} -> 5.5 | Z84: {=IFERROR(XLOOKUP(B84,'INC INV'!BH:BH,'INC INV'!BJ:BJ)/F84,0)} -> 0 | AA84: {=IFERROR(XLOOKUP(B84,'INC INV'!BN:BN,'INC INV'!BP:BP)/F84,0)} -> 0
A85: Devi w/Bangles Black Ver | B85: ME0020211400 | C85: PHOTO | E85: {=XLOOKUP(B85,'PRICE LIST'!E:E,#REF!)} -> #N/A | F85: {=XLOOKUP(B85,SALES!A:A,SALES!C:C)} -> 1.8333333 | G85: {=XLOOKUP(B85,INV!A:A,INV!G:G)} -> 0 | H85: =IF(G85/F85<0,0,G85/F85) -> 0 | I85: =F85*J85 -> 14.666667 | J85: 8 | K85: =IF((H85-1+V85)<0,0,H85-1+V85) -> 3.9090909 | L85: =IF((K85-1+W85)<0,0,K85-1+W85) -> 2.9090909 | M85: =IF((L85-1+X85)<0,0,L85-1+X85) -> 1.9090909 | N85: =IF((M85-1+Y85)<0,0,M85-1+Y85) -> 9.6363636 | O85: =IF((N85-1+Z85)<0,0,N85-1+Z85) -> 8.6363636 | P85: =IF((O85-1+AA85)<0,0,O85-1+AA85) -> 7.6363636 | Q85: =T85*F85 -> 0.66666667 | S85: =U85*F85 -> 0 | T85: =IF(P85<J85,J85-P85,0) -> 0.36363636 | U85: =IF(N85<3,3-N85,0) -> 0 | V85: {=iferror(XLOOKUP(B85,'INC INV'!AJ:AJ,'INC INV'!AL:AL)/F85,0)} -> 4.9090909 | W85: {=IFERROR(XLOOKUP(B85,'INC INV'!AP:AP,'INC INV'!AR:AR)/F85,0)} -> 0 | X85: {=IFERROR(XLOOKUP(B85,'INC INV'!AV:AV,'INC INV'!AX:AX)/F85,0)} -> 0 | Y85: {=IFERROR(XLOOKUP(B85,'INC INV'!BB:BB,'INC INV'!BD:BD)/F85,0)} -> 8.7272727 | Z85: {=IFERROR(XLOOKUP(B85,'INC INV'!BH:BH,'INC INV'!BJ:BJ)/F85,0)} -> 0 | AA85: {=IFERROR(XLOOKUP(B85,'INC INV'!BN:BN,'INC INV'!BP:BP)/F85,0)} -> 0
A86: English Joy 24x7 | B86: ME0002701500 | C86: BOOK | D86: {=XLOOKUP(B86,'ORDER LIST'!C:C,'ORDER LIST'!B:B)} -> English Joy 24x7 | F86: {=XLOOKUP(B86,SALES!A:A,SALES!C:C)} -> 16.25 | G86: {=XLOOKUP(B86,INV!A:A,INV!G:G)} -> 80 | H86: =IF(G86/F86<0,0,G86/F86) -> 4.9230769 | I86: =F86*J86 -> 130 | J86: 8 | K86: =IF((H86-1+V86)<0,0,H86-1+V86) -> 3.9230769 | L86: =IF((K86-1+W86)<0,0,K86-1+W86) -> 4.7692308 | M86: =IF((L86-1+X86)<0,0,L86-1+X86) -> 3.7692308 | N86: =IF((M86-1+Y86)<0,0,M86-1+Y86) -> 8.2461538 | O86: =IF((N86-1+Z86)<0,0,N86-1+Z86) -> 7.2461538 | P86: =IF((O86-1+AA86)<0,0,O86-1+AA86) -> 6.2461538 | Q86: =T86*F86 -> 28.5 | S86: =U86*F86 -> 0 | T86: =IF(P86<J86,J86-P86,0) -> 1.7538462 | U86: =IF(N86<3,3-N86,0) -> 0 | V86: {=iferror(XLOOKUP(B86,'INC INV'!AJ:AJ,'INC INV'!AL:AL)/F86,0)} -> 0 | W86: {=IFERROR(XLOOKUP(B86,'INC INV'!AP:AP,'INC INV'!AR:AR)/F86,0)} -> 1.8461538 | X86: {=IFERROR(XLOOKUP(B86,'INC INV'!AV:AV,'INC INV'!AX:AX)/F86,0)} -> 0 | Y86: {=IFERROR(XLOOKUP(B86,'INC INV'!BB:BB,'INC INV'!BD:BD)/F86,0)} -> 5.4769231 | Z86: {=IFERROR(XLOOKUP(B86,'INC INV'!BH:BH,'INC INV'!BJ:BJ)/F86,0)} -> 0 | AA86: {=IFERROR(XLOOKUP(B86,'INC INV'!BN:BN,'INC INV'!BP:BP)/F86,0)} -> 0
A87: Devi w/Bangles Yellow Ver | B87: ME0020010000 | C87: PHOTO | D87: {=XLOOKUP(B87,'ORDER LIST'!C:C,'ORDER LIST'!B:B)} -> Devi w/Bangles Yellow Ver | E87: {=XLOOKUP(B87,'PRICE LIST'!E:E,#REF!)} -> #N/A | F87: {=XLOOKUP(B87,SALES!A:A,SALES!C:C)} -> 3.25 | G87: {=XLOOKUP(B87,INV!A:A,INV!G:G)} -> 16 | H87: =IF(G87/F87<0,0,G87/F87) -> 4.9230769 | I87: =F87*J87 -> 26 | J87: 8 | K87: =IF((H87-1+V87)<0,0,H87-1+V87) -> 3.9230769 | L87: =IF((K87-1+W87)<0,0,K87-1+W87) -> 2.9230769 | M87: =IF((L87-1+X87)<0,0,L87-1+X87) -> 1.9230769 | N87: =IF((M87-1+Y87)<0,0,M87-1+Y87) -> 4.9230769 | O87: =IF((N87-1+Z87)<0,0,N87-1+Z87) -> 3.9230769 | P87: =IF((O87-1+AA87)<0,0,O87-1+AA87) -> 2.9230769 | Q87: =T87*F87 -> 16.5 | S87: =U87*F87 -> 0 | T87: =IF(P87<J87,J87-P87,0) -> 5.0769231 | U87: =IF(N87<3,3-N87,0) -> 0 | V87: {=iferror(XLOOKUP(B87,'INC INV'!AJ:AJ,'INC INV'!AL:AL)/F87,0)} -> 0 | W87: {=IFERROR(XLOOKUP(B87,'INC INV'!AP:AP,'INC INV'!AR:AR)/F87,0)} -> 0 | X87: {=IFERROR(XLOOKUP(B87,'INC INV'!AV:AV,'INC INV'!AX:AX)/F87,0)} -> 0 | Y87: {=IFERROR(XLOOKUP(B87,'INC INV'!BB:BB,'INC INV'!BD:BD)/F87,0)} -> 4 | Z87: {=IFERROR(XLOOKUP(B87,'INC INV'!BH:BH,'INC INV'!BJ:BJ)/F87,0)} -> 0 | AA87: {=IFERROR(XLOOKUP(B87,'INC INV'!BN:BN,'INC INV'!BP:BP)/F87,0)} -> 0
A88: Turmeric | B88: TC0005800400 | C88: CONX | D88: {=XLOOKUP(B88,'ORDER LIST'!C:C,'ORDER LIST'!B:B)} -> Turmeric | E88: L | F88: {=XLOOKUP(B88,SALES!A:A,SALES!C:C)} -> 42.25 | G88: {=XLOOKUP(B88,INV!A:A,INV!G:G)} -> 209 | H88: =IF(G88/F88<0,0,G88/F88) -> 4.9467456 | I88: =F88*J88 -> 422.5 | J88: 10 | K88: =IF((H88-1+V88)<0,0,H88-1+V88) -> 3.9467456 | L88: =IF((K88-1+W88)<0,0,K88-1+W88) -> 4.9585799 | M88: =IF((L88-1+X88)<0,0,L88-1+X88) -> 3.9585799 | N88: =IF((M88-1+Y88)<0,0,M88-1+Y88) -> 10.792899 | O88: =IF((N88-1+Z88)<0,0,N88-1+Z88) -> 9.7928994 | P88: =IF((O88-1+AA88)<0,0,O88-1+AA88) -> 8.7928994 | Q88: =T88*F88 -> 51 | S88: =U88*F88 -> 0 | T88: =IF(P88<J88,J88-P88,0) -> 1.2071006 | U88: =IF(N88<3,3-N88,0) -> 0 | V88: {=iferror(XLOOKUP(B88,'INC INV'!AJ:AJ,'INC INV'!AL:AL)/F88,0)} -> 0 | W88: {=IFERROR(XLOOKUP(B88,'INC INV'!AP:AP,'INC INV'!AR:AR)/F88,0)} -> 2.0118343 | X88: {=IFERROR(XLOOKUP(B88,'INC INV'!AV:AV,'INC INV'!AX:AX)/F88,0)} -> 0 | Y88: {=IFERROR(XLOOKUP(B88,'INC INV'!BB:BB,'INC INV'!BD:BD)/F88,0)} -> 7.8343195 | Z88: {=IFERROR(XLOOKUP(B88,'INC INV'!BH:BH,'INC INV'!BJ:BJ)/F88,0)} -> 0 | AA88: {=IFERROR(XLOOKUP(B88,'INC INV'!BN:BN,'INC INV'!BP:BP)/F88,0)} -> 0
A89: SD606 Sadhguru Photo (18x24) | B89: ME0025412400 | C89: PHOTO | D89: {=XLOOKUP(B89,'ORDER LIST'!C:C,'ORDER LIST'!B:B)} -> SD606 Sadhguru Photo (18x24) | E89: {=XLOOKUP(B89,'PRICE LIST'!E:E,#REF!)} -> #N/A | F89: 3 | G89: {=XLOOKUP(B89,INV!A:A,INV!G:G)} -> 0 | H89: =IF(G89/F89<0,0,G89/F89) -> 0 | I89: =F89*J89 -> 24 | J89: 8 | K89: =IF((H89-1+V89)<0,0,H89-1+V89) -> 4 | L89: =IF((K89-1+W89)<0,0,K89-1+W89) -> 11.333333 | M89: =IF((L89-1+X89)<0,0,L89-1+X89) -> 10.333333 | N89: =IF((M89-1+Y89)<0,0,M89-1+Y89) -> 9.3333333 | O89: =IF((N89-1+Z89)<0,0,N89-1+Z89) -> 8.3333333 | P89: =IF((O89-1+AA89)<0,0,O89-1+AA89) -> 7.3333333 | Q89: =T89*F89 -> 2 | S89: =U89*F89 -> 0 | T89: =IF(P89<J89,J89-P89,0) -> 0.66666667 | U89: =IF(N89<3,3-N89,0) -> 0 | V89: {=iferror(XLOOKUP(B89,'INC INV'!AJ:AJ,'INC INV'!AL:AL)/F89,0)} -> 5 | W89: {=IFERROR(XLOOKUP(B89,'INC INV'!AP:AP,'INC INV'!AR:AR)/F89,0)} -> 8.3333333 | X89: {=IFERROR(XLOOKUP(B89,'INC INV'!AV:AV,'INC INV'!AX:AX)/F89,0)} -> 0 | Y89: {=IFERROR(XLOOKUP(B89,'INC INV'!BB:BB,'INC INV'!BD:BD)/F89,0)} -> 0 | Z89: {=IFERROR(XLOOKUP(B89,'INC INV'!BH:BH,'INC INV'!BJ:BJ)/F89,0)} -> 0 | AA89: {=IFERROR(XLOOKUP(B89,'INC INV'!BN:BN,'INC INV'!BP:BP)/F89,0)} -> 0
A90: Gents-Shivanga-pooja-kit-with-Rudraksha-pendant | B90: YS0008416900 | C90: CONX | D90: {=XLOOKUP(B90,'ORDER LIST'!C:C,'ORDER LIST'!B:B)} -> Gents-Shivanga-pooja-kit-with-Rudraksha-pendant | F90: {=XLOOKUP(B90,SALES!A:A,SALES!C:C)} -> 31 | G90: {=XLOOKUP(B90,INV!A:A,INV!G:G)} -> 155 | H90: =IF(G90/F90<0,0,G90/F90) -> 5 | I90: =F90*J90 -> 310 | J90: 10 | K90: =IF((H90-1+V90)<0,0,H90-1+V90) -> 4 | L90: =IF((K90-1+W90)<0,0,K90-1+W90) -> 3 | M90: =IF((L90-1+X90)<0,0,L90-1+X90) -> 4.2580645 | N90: =IF((M90-1+Y90)<0,0,M90-1+Y90) -> 3.2580645 | O90: =IF((N90-1+Z90)<0,0,N90-1+Z90) -> 12.258065 | P90: =IF((O90-1+AA90)<0,0,O90-1+AA90) -> 11.258065 | Q90: =T90*F90 -> 0 | S90: =U90*F90 -> 0 | T90: =IF(P90<J90,J90-P90,0) -> 0 | U90: =IF(N90<3,3-N90,0) -> 0 | V90: {=iferror(XLOOKUP(B90,'INC INV'!AJ:AJ,'INC INV'!AL:AL)/F90,0)} -> 0 | W90: {=IFERROR(XLOOKUP(B90,'INC INV'!AP:AP,'INC INV'!AR:AR)/F90,0)} -> 0 | X90: {=IFERROR(XLOOKUP(B90,'INC INV'!AV:AV,'INC INV'!AX:AX)/F90,0)} -> 2.2580645 | Y90: {=IFERROR(XLOOKUP(B90,'INC INV'!BB:BB,'INC INV'!BD:BD)/F90,0)} -> 0 | Z90: {=IFERROR(XLOOKUP(B90,'INC INV'!BH:BH,'INC INV'!BJ:BJ)/F90,0)} -> 10 | AA90: {=IFERROR(XLOOKUP(B90,'INC INV'!BN:BN,'INC INV'!BP:BP)/F90,0)} -> 0
A91: SE803 Sadhguru Photo (8x12) | B91: ME0026410100 | C91: PHOTO | D91: {=XLOOKUP(B91,'ORDER LIST'!C:C,'ORDER LIST'!B:B)} -> SE803 Sadhguru Photo (8x12) | E91: {=XLOOKUP(B91,'PRICE LIST'!E:E,#REF!)} -> #N/A | F91: 5 | G91: {=XLOOKUP(B91,INV!A:A,INV!G:G)} -> 15 | H91: =IF(G91/F91<0,0,G91/F91) -> 3 | I91: =F91*J91 -> 40 | J91: 8 | K91: =IF((H91-1+V91)<0,0,H91-1+V91) -> 4 | L91: =IF((K91-1+W91)<0,0,K91-1+W91) -> 13 | M91: =IF((L91-1+X91)<0,0,L91-1+X91) -> 12 | N91: =IF((M91-1+Y91)<0,0,M91-1+Y91) -> 11 | O91: =IF((N91-1+Z91)<0,0,N91-1+Z91) -> 10 | P91: =IF((O91-1+AA91)<0,0,O91-1+AA91) -> 9 | Q91: =T91*F91 -> 0 | S91: =U91*F91 -> 0 | T91: =IF(P91<J91,J91-P91,0) -> 0 | U91: =IF(N91<3,3-N91,0) -> 0 | V91: {=iferror(XLOOKUP(B91,'INC INV'!AJ:AJ,'INC INV'!AL:AL)/F91,0)} -> 2 | W91: {=IFERROR(XLOOKUP(B91,'INC INV'!AP:AP,'INC INV'!AR:AR)/F91,0)} -> 10 | X91: {=IFERROR(XLOOKUP(B91,'INC INV'!AV:AV,'INC INV'!AX:AX)/F91,0)} -> 0 | Y91: {=IFERROR(XLOOKUP(B91,'INC INV'!BB:BB,'INC INV'!BD:BD)/F91,0)} -> 0 | Z91: {=IFERROR(XLOOKUP(B91,'INC INV'!BH:BH,'INC INV'!BJ:BJ)/F91,0)} -> 0 | AA91: {=IFERROR(XLOOKUP(B91,'INC INV'!BN:BN,'INC INV'!BP:BP)/F91,0)} -> 0
A92: Nandi Statue | B92: TC0007600000 | C92: TEMPLE | F92: {=XLOOKUP(B92,SALES!A:A,SALES!C:C)} -> 32.25 | G92: {=XLOOKUP(B92,INV!A:A,INV!G:G)} -> 172 | H92: =IF(G92/F92<0,0,G92/F92) -> 5.3333333 | I92: =F92*J92 -> 258 | J92: 8 | K92: =IF((H92-1+V92)<0,0,H92-1+V92) -> 4.3333333 | L92: =IF((K92-1+W92)<0,0,K92-1+W92) -> 3.3333333 | M92: =IF((L92-1+X92)<0,0,L92-1+X92) -> 2.3333333 | N92: =IF((M92-1+Y92)<0,0,M92-1+Y92) -> 8.1550388 | O92: =IF((N92-1+Z92)<0,0,N92-1+Z92) -> 7.7751938 | P92: =IF((O92-1+AA92)<0,0,O92-1+AA92) -> 6.7751938 | Q92: =T92*F92 -> 39.5 | S92: =U92*F92 -> 0 | T92: =IF(P92<J92,J92-P92,0) -> 1.2248062 | U92: =IF(N92<3,3-N92,0) -> 0 | V92: {=iferror(XLOOKUP(B92,'INC INV'!AJ:AJ,'INC INV'!AL:AL)/F92,0)} -> 0 | W92: {=IFERROR(XLOOKUP(B92,'INC INV'!AP:AP,'INC INV'!AR:AR)/F92,0)} -> 0 | X92: {=IFERROR(XLOOKUP(B92,'INC INV'!AV:AV,'INC INV'!AX:AX)/F92,0)} -> 0 | Y92: {=IFERROR(XLOOKUP(B92,'INC INV'!BB:BB,'INC INV'!BD:BD)/F92,0)} -> 6.8217054 | Z92: {=IFERROR(XLOOKUP(B92,'INC INV'!BH:BH,'INC INV'!BJ:BJ)/F92,0)} -> 0.62015504 | AA92: {=IFERROR(XLOOKUP(B92,'INC INV'!BN:BN,'INC INV'!BP:BP)/F92,0)} -> 0
A93: Devi Red Pendant Cord | B93: CA0035800000 | C93: TEMPLE | D93: {=XLOOKUP(B93,'ORDER LIST'!C:C,'ORDER LIST'!B:B)} -> Devi Red Pendant Cord | F93: {=XLOOKUP(B93,SALES!A:A,SALES!C:C)} -> 129.08333 | G93: {=XLOOKUP(B93,INV!A:A,INV!G:G)} -> 695 | H93: =IF(G93/F93<0,0,G93/F93) -> 5.3841188 | I93: =F93*J93 -> 1290.8333 | J93: 10 | K93: =IF((H93-1+V93)<0,0,H93-1+V93) -> 4.3841188 | L93: =IF((K93-1+W93)<0,0,K93-1+W93) -> 3.3841188 | M93: =IF((L93-1+X93)<0,0,L93-1+X93) -> 2.8489348 | N93: =IF((M93-1+Y93)<0,0,M93-1+Y93) -> 9.8127824 | O93: =IF((N93-1+Z93)<0,0,N93-1+Z93) -> 10.323434 | P93: =IF((O93-1+AA93)<0,0,O93-1+AA93) -> 9.3234345 | Q93: =T93*F93 -> 87.333333 | S93: =U93*F93 -> 0 | T93: =IF(P93<J93,J93-P93,0) -> 0.67656553 | U93: =IF(N93<3,3-N93,0) -> 0 | V93: {=iferror(XLOOKUP(B93,'INC INV'!AJ:AJ,'INC INV'!AL:AL)/F93,0)} -> 0 | W93: {=IFERROR(XLOOKUP(B93,'INC INV'!AP:AP,'INC INV'!AR:AR)/F93,0)} -> 0 | X93: {=IFERROR(XLOOKUP(B93,'INC INV'!AV:AV,'INC INV'!AX:AX)/F93,0)} -> 0.46481601 | Y93: {=IFERROR(XLOOKUP(B93,'INC INV'!BB:BB,'INC INV'!BD:BD)/F93,0)} -> 7.9638476 | Z93: {=IFERROR(XLOOKUP(B93,'INC INV'!BH:BH,'INC INV'!BJ:BJ)/F93,0)} -> 1.510652 | AA93: {=IFERROR(XLOOKUP(B93,'INC INV'!BN:BN,'INC INV'!BP:BP)/F93,0)} -> 0
A94: SG-Photos-Kailash-8 | B94: ME0027209000 | C94: PHOTO | D94: {=XLOOKUP(B94,'ORDER LIST'!C:C,'ORDER LIST'!B:B)} -> SG-Photos-Kailash-8 | E94: {=XLOOKUP(B94,'PRICE LIST'!E:E,#REF!)} -> #N/A | F94: {=XLOOKUP(B94,SALES!A:A,SALES!C:C)} -> 6.25 | G94: {=XLOOKUP(B94,INV!A:A,INV!G:G)} -> 34 | H94: =IF(G94/F94<0,0,G94/F94) -> 5.44 | I94: =F94*J94 -> 50 | J94: 8 | K94: =IF((H94-1+V94)<0,0,H94-1+V94) -> 4.44 | L94: =IF((K94-1+W94)<0,0,K94-1+W94) -> 3.44 | M94: =IF((L94-1+X94)<0,0,L94-1+X94) -> 2.44 | N94: =IF((M94-1+Y94)<0,0,M94-1+Y94) -> 8.16 | O94: =IF((N94-1+Z94)<0,0,N94-1+Z94) -> 7.16 | P94: =IF((O94-1+AA94)<0,0,O94-1+AA94) -> 6.16 | Q94: =T94*F94 -> 11.5 | S94: =U94*F94 -> 0 | T94: =IF(P94<J94,J94-P94,0) -> 1.84 | U94: =IF(N94<3,3-N94,0) -> 0 | V94: {=iferror(XLOOKUP(B94,'INC INV'!AJ:AJ,'INC INV'!AL:AL)/F94,0)} -> 0 | W94: {=IFERROR(XLOOKUP(B94,'INC INV'!AP:AP,'INC INV'!AR:AR)/F94,0)} -> 0 | X94: {=IFERROR(XLOOKUP(B94,'INC INV'!AV:AV,'INC INV'!AX:AX)/F94,0)} -> 0 | Y94: {=IFERROR(XLOOKUP(B94,'INC INV'!BB:BB,'INC INV'!BD:BD)/F94,0)} -> 6.72 | Z94: {=IFERROR(XLOOKUP(B94,'INC INV'!BH:BH,'INC INV'!BJ:BJ)/F94,0)} -> 0 | AA94: {=IFERROR(XLOOKUP(B94,'INC INV'!BN:BN,'INC INV'!BP:BP)/F94,0)} -> 0
A95: Kumkum | B95: TC0005700200 | C95: CONX | E95: S | F95: {=XLOOKUP(B95,SALES!A:A,SALES!C:C)} -> 179.91667 | G95: {=XLOOKUP(B95,INV!A:A,INV!G:G)} -> 1006 | H95: =IF(G95/F95<0,0,G95/F95) -> 5.5914775 | I95: =F95*J95 -> 1799.1667 | J95: 10 | K95: =IF((H95-1+V95)<0,0,H95-1+V95) -> 4.5914775 | L95: =IF((K95-1+W95)<0,0,K95-1+W95) -> 3.5914775 | M95: =IF((L95-1+X95)<0,0,L95-1+X95) -> 2.5914775 | N95: =IF((M95-1+Y95)<0,0,M95-1+Y95) -> 7.9833256 | O95: =IF((N95-1+Z95)<0,0,N95-1+Z95) -> 10.262622 | P95: =IF((O95-1+AA95)<0,0,O95-1+AA95) -> 9.2626216 | Q95: =T95*F95 -> 132.66667 | S95: =U95*F95 -> 0 | T95: =IF(P95<J95,J95-P95,0) -> 0.73737842 | U95: =IF(N95<3,3-N95,0) -> 0 | V95: {=iferror(XLOOKUP(B95,'INC INV'!AJ:AJ,'INC INV'!AL:AL)/F95,0)} -> 0 | W95: {=IFERROR(XLOOKUP(B95,'INC INV'!AP:AP,'INC INV'!AR:AR)/F95,0)} -> 0 | X95: {=IFERROR(XLOOKUP(B95,'INC INV'!AV:AV,'INC INV'!AX:AX)/F95,0)} -> 0 | Y95: {=IFERROR(XLOOKUP(B95,'INC INV'!BB:BB,'INC INV'!BD:BD)/F95,0)} -> 6.3918481 | Z95: {=IFERROR(XLOOKUP(B95,'INC INV'!BH:BH,'INC INV'!BJ:BJ)/F95,0)} -> 3.279296 | AA95: {=IFERROR(XLOOKUP(B95,'INC INV'!BN:BN,'INC INV'!BP:BP)/F95,0)} -> 0
A96: Incense-Sticks-Organic-SamplerPackOf10 | B96: HO0029600002 | C96: INCENSE | D96: {=XLOOKUP(B96,'ORDER LIST'!C:C,'ORDER LIST'!B:B)} -> Incense-Sticks-Organic-SamplerPackOf10 | F96: {=XLOOKUP(B96,SALES!A:A,SALES!C:C)} -> 176.5 | G96: {=XLOOKUP(B96,INV!A:A,INV!G:G)} -> 996 | H96: =IF(G96/F96<0,0,G96/F96) -> 5.6430595 | I96: =F96*J96 -> 1765 | J96: 10 | K96: =IF((H96-1+V96)<0,0,H96-1+V96) -> 4.6430595 | L96: =IF((K96-1+W96)<0,0,K96-1+W96) -> 4.3512748 | M96: =IF((L96-1+X96)<0,0,L96-1+X96) -> 3.3512748 | N96: =IF((M96-1+Y96)<0,0,M96-1+Y96) -> 10.243626 | O96: =IF((N96-1+Z96)<0,0,N96-1+Z96) -> 9.470255 | P96: =IF((O96-1+AA96)<0,0,O96-1+AA96) -> 8.470255 | Q96: =T96*F96 -> 270 | S96: =U96*F96 -> 0 | T96: =IF(P96<J96,J96-P96,0) -> 1.529745 | U96: =IF(N96<3,3-N96,0) -> 0 | V96: {=iferror(XLOOKUP(B96,'INC INV'!AJ:AJ,'INC INV'!AL:AL)/F96,0)} -> 0 | W96: {=IFERROR(XLOOKUP(B96,'INC INV'!AP:AP,'INC INV'!AR:AR)/F96,0)} -> 0.7082153 | X96: {=IFERROR(XLOOKUP(B96,'INC INV'!AV:AV,'INC INV'!AX:AX)/F96,0)} -> 0 | Y96: {=IFERROR(XLOOKUP(B96,'INC INV'!BB:BB,'INC INV'!BD:BD)/F96,0)} -> 7.8923513 | Z96: {=IFERROR(XLOOKUP(B96,'INC INV'!BH:BH,'INC INV'!BJ:BJ)/F96,0)} -> 0.2266289 | AA96: {=IFERROR(XLOOKUP(B96,'INC INV'!BN:BN,'INC INV'!BP:BP)/F96,0)} -> 0
A97: SG-Photos-Compassion | B97: ME0025409000 | C97: PHOTO | D97: {=XLOOKUP(B97,'ORDER LIST'!C:C,'ORDER LIST'!B:B)} -> SG-Photos-Compassion | E97: {=XLOOKUP(B97,'PRICE LIST'!E:E,#REF!)} -> #N/A | F97: {=XLOOKUP(B97,SALES!A:A,SALES!C:C)} -> 7.0833333 | G97: {=XLOOKUP(B97,INV!A:A,INV!G:G)} -> 40 | H97: =IF(G97/F97<0,0,G97/F97) -> 5.6470588 | I97: =F97*J97 -> 56.666667 | J97: 8 | K97: =IF((H97-1+V97)<0,0,H97-1+V97) -> 4.6470588 | L97: =IF((K97-1+W97)<0,0,K97-1+W97) -> 3.6470588 | M97: =IF((L97-1+X97)<0,0,L97-1+X97) -> 2.6470588 | N97: =IF((M97-1+Y97)<0,0,M97-1+Y97) -> 11.388235 | O97: =IF((N97-1+Z97)<0,0,N97-1+Z97) -> 10.388235 | P97: =IF((O97-1+AA97)<0,0,O97-1+AA97) -> 9.3882353 | Q97: =T97*F97 -> 0 | S97: =U97*F97 -> 0 | T97: =IF(P97<J97,J97-P97,0) -> 0 | U97: =IF(N97<3,3-N97,0) -> 0 | V97: {=iferror(XLOOKUP(B97,'INC INV'!AJ:AJ,'INC INV'!AL:AL)/F97,0)} -> 0 | W97: {=IFERROR(XLOOKUP(B97,'INC INV'!AP:AP,'INC INV'!AR:AR)/F97,0)} -> 0 | X97: {=IFERROR(XLOOKUP(B97,'INC INV'!AV:AV,'INC INV'!AX:AX)/F97,0)} -> 0 | Y97: {=IFERROR(XLOOKUP(B97,'INC INV'!BB:BB,'INC INV'!BD:BD)/F97,0)} -> 9.7411765 | Z97: {=IFERROR(XLOOKUP(B97,'INC INV'!BH:BH,'INC INV'!BJ:BJ)/F97,0)} -> 0 | AA97: {=IFERROR(XLOOKUP(B97,'INC INV'!BN:BN,'INC INV'!BP:BP)/F97,0)} -> 0
A98: Incense-Cone-Vibhuti-20Pcs | B98: HO0026100002 | C98: INCENSE | D98: {=XLOOKUP(B98,'ORDER LIST'!C:C,'ORDER LIST'!B:B)} -> Incense-Cone-Vibhuti-20Pcs | F98: {=XLOOKUP(B98,SALES!A:A,SALES!C:C)} -> 65.083333 | G98: {=XLOOKUP(B98,INV!A:A,INV!G:G)} -> 376 | H98: =IF(G98/F98<0,0,G98/F98) -> 5.7772087 | I98: =F98*J98 -> 520.66667 | J98: 8 | K98: =IF((H98-1+V98)<0,0,H98-1+V98) -> 4.7772087 | L98: =IF((K98-1+W98)<0,0,K98-1+W98) -> 9.4622279 | M98: =IF((L98-1+X98)<0,0,L98-1+X98) -> 8.4622279 | N98: =IF((M98-1+Y98)<0,0,M98-1+Y98) -> 11.564661 | O98: =IF((N98-1+Z98)<0,0,N98-1+Z98) -> 10.564661 | P98: =IF((O98-1+AA98)<0,0,O98-1+AA98) -> 9.5646607 | Q98: =T98*F98 -> 0 | S98: =U98*F98 -> 0 | T98: =IF(P98<J98,J98-P98,0) -> 0 | U98: =IF(N98<3,3-N98,0) -> 0 | V98: {=iferror(XLOOKUP(B98,'INC INV'!AJ:AJ,'INC INV'!AL:AL)/F98,0)} -> 0 | W98: {=IFERROR(XLOOKUP(B98,'INC INV'!AP:AP,'INC INV'!AR:AR)/F98,0)} -> 5.6850192 | X98: {=IFERROR(XLOOKUP(B98,'INC INV'!AV:AV,'INC INV'!AX:AX)/F98,0)} -> 0 | Y98: {=IFERROR(XLOOKUP(B98,'INC INV'!BB:BB,'INC INV'!BD:BD)/F98,0)} -> 4.1024328 | Z98: {=IFERROR(XLOOKUP(B98,'INC INV'!BH:BH,'INC INV'!BJ:BJ)/F98,0)} -> 0 | AA98: {=IFERROR(XLOOKUP(B98,'INC INV'!BN:BN,'INC INV'!BP:BP)/F98,0)} -> 0
A99: NeemWoodComb-DualEnd | B99: BC0000400002 | C99: BODY CARE | D99: {=XLOOKUP(B99,'ORDER LIST'!C:C,'ORDER LIST'!B:B)} -> NeemWoodComb-DualEnd | F99: {=XLOOKUP(B99,SALES!A:A,SALES!C:C)} -> 52.666667 | G99: {=XLOOKUP(B99,INV!A:A,INV!G:G)} -> 309 | H99: =IF(G99/F99<0,0,G99/F99) -> 5.8670886 | I99: =F99*J99 -> 421.33333 | J99: 8 | K99: =IF((H99-1+V99)<0,0,H99-1+V99) -> 4.8670886 | L99: =IF((K99-1+W99)<0,0,K99-1+W99) -> 3.9620253 | M99: =IF((L99-1+X99)<0,0,L99-1+X99) -> 2.9620253 | N99: =IF((M99-1+Y99)<0,0,M99-1+Y99) -> 7.4493671 | O99: =IF((N99-1+Z99)<0,0,N99-1+Z99) -> 7.3987342 | P99: =IF((O99-1+AA99)<0,0,O99-1+AA99) -> 6.3987342 | Q99: =T99*F99 -> 84.333333 | S99: =U99*F99 -> 0 | T99: =IF(P99<J99,J99-P99,0) -> 1.6012658 | U99: =IF(N99<3,3-N99,0) -> 0 | V99: {=iferror(XLOOKUP(B99,'INC INV'!AJ:AJ,'INC INV'!AL:AL)/F99,0)} -> 0 | W99: {=IFERROR(XLOOKUP(B99,'INC INV'!AP:AP,'INC INV'!AR:AR)/F99,0)} -> 0.094936709 | X99: {=IFERROR(XLOOKUP(B99,'INC INV'!AV:AV,'INC INV'!AX:AX)/F99,0)} -> 0 | Y99: {=IFERROR(XLOOKUP(B99,'INC INV'!BB:BB,'INC INV'!BD:BD)/F99,0)} -> 5.4873418 | Z99: {=IFERROR(XLOOKUP(B99,'INC INV'!BH:BH,'INC INV'!BJ:BJ)/F99,0)} -> 0.94936709 | AA99: {=IFERROR(XLOOKUP(B99,'INC INV'!BN:BN,'INC INV'!BP:BP)/F99,0)} -> 0
A100: Eternal Echoes - A Book Of Poems (1994-2021) | B100: ME0001201500 | C100: BOOK | D100: {=XLOOKUP(B100,'ORDER LIST'!C:C,'ORDER LIST'!B:B)} -> Eternal Echoes - A Book Of Poems (1994-2021) | F100: {=XLOOKUP(B100,SALES!A:A,SALES!C:C)} -> 11.333333 | G100: {=XLOOKUP(B100,INV!A:A,INV!G:G)} -> 67 | H100: =IF(G100/F100<0,0,G100/F100) -> 5.9117647 | I100: =F100*J100 -> 90.666667 | J100: 8 | K100: =IF((H100-1+V100)<0,0,H100-1+V100) -> 4.9117647 | L100: =IF((K100-1+W100)<0,0,K100-1+W100) -> 5.2352941 | M100: =IF((L100-1+X100)<0,0,L100-1+X100) -> 4.2352941 | N100: =IF((M100-1+Y100)<0,0,M100-1+Y100) -> 9.5882353 | O100: =IF((N100-1+Z100)<0,0,N100-1+Z100) -> 8.5882353 | P100: =IF((O100-1+AA100)<0,0,O100-1+AA100) -> 7.5882353 | Q100: =T100*F100 -> 4.6666667 | S100: =U100*F100 -> 0 | T100: =IF(P100<J100,J100-P100,0) -> 0.41176471 | U100: =IF(N100<3,3-N100,0) -> 0 | V100: {=iferror(XLOOKUP(B100,'INC INV'!AJ:AJ,'INC INV'!AL:AL)/F100,0)} -> 0 | W100: {=IFERROR(XLOOKUP(B100,'INC INV'!AP:AP,'INC INV'!AR:AR)/F100,0)} -> 1.3235294 | X100: {=IFERROR(XLOOKUP(B100,'INC INV'!AV:AV,'INC INV'!AX:AX)/F100,0)} -> 0 | Y100: {=IFERROR(XLOOKUP(B100,'INC INV'!BB:BB,'INC INV'!BD:BD)/F100,0)} -> 6.3529412 | Z100: {=IFERROR(XLOOKUP(B100,'INC INV'!BH:BH,'INC INV'!BJ:BJ)/F100,0)} -> 0 | AA100: {=IFERROR(XLOOKUP(B100,'INC INV'!BN:BN,'INC INV'!BP:BP)/F100,0)} -> 0
...

Sheet PR CHK
A1: SKU | B1: Name | C1: CAN RP (CAD) | D1: CAN RP (USD) | E1: US RP | F1: US RP * 1.4 (CAD) | G1: 1.4X CLAUDE (CAD) | H1: DIFFERENCE | I1: DELTA % | J1: COGS (USD)
A2: TC0003300309 | B2: Linga Bhairavi Copper Pendant, Medium (Consecrated) | C2: 30 | D2: =C2*0.73 -> 21.9 | E2: 35 | F2: 49 | G2: 49 | H2: =G2-C2 -> 19 | I2: =H2/C2 -> 0.63333333 | J2: 1
A3: TC0000500000 | B3: Adiyogi Vastram (Consecrated) | C3: 9 | D3: =C3*0.73 -> 6.57 | E3: 9 | F3: 12.6 | G3: 12.99 | H3: =G3-C3 -> 3.99 | I3: =H3/C3 -> 0.44333333 | J3: 2
A4: NF0005520606 | B4: Organic Moong Beans, 80oz | C4: 18 | D4: =C4*0.73 -> 13.14 | E4: 18 | F4: 25.2 | G4: 25 | H4: =G4-C4 -> 7 | I4: =H4/C4 -> 0.38888889 | J4: 8
A5: NF0005304806 | B5: 100% Pure Sesame Oil, 33.8 oz | C5: 25 | D5: =C5*0.73 -> 18.25 | E5: 25 | F5: 35 | G5: 35 | H5: =G5-C5 -> 10 | I5: =H5/C5 -> 0.4 | J5: 27
A6: NF0005304206 | B6: 100% Pure Sesame Oil, 1.45 gal | C6: 75 | D6: =C6*0.73 -> 54.75 | E6: 75 | F6: 105 | G6: 105 | H6: =G6-C6 -> 30 | I6: =H6/C6 -> 0.4 | J6: 5.2
A7: HO0072600000 | B7: Sandalwood Powder, 4.8 oz | C7: 12 | D7: =C7*0.73 -> 8.76 | E7: 12 | F7: 16.8 | G7: 16.99 | H7: =G7-C7 -> 4.99 | I7: =H7/C7 -> 0.41583333
A8: HI0005504606 | B8: Neem Oil, 8 oz | C8: 12.99 | D8: =C8*0.73 -> 9.4827 | E8: 12.99 | F8: 18.186 | G8: 17.99 | H8: =G8-C8 -> 5 | I8: =H8/C8 -> 0.38491147 | J8: 2
A9: HI0001804606 | B9: Castor Oil, 8 oz | C9: 12.99 | D9: =C9*0.73 -> 9.4827 | E9: 12.99 | F9: 18.186 | G9: 17.99 | H9: =G9-C9 -> 5 | I9: =H9/C9 -> 0.38491147 | J9: 2
A10: CA0134700606 | B10: White Organic Cotton Unisex Zip Hoodie - XXL | C10: 55 | D10: =C10*0.73 -> 40.15 | E10: 55 | F10: 77 | G10: 75 | H10: =G10-C10 -> 20 | I10: =H10/C10 -> 0.36363636
A11: CA0134700506 | B11: White Organic Cotton Unisex Zip Hoodie - XL | C11: 55 | D11: =C11*0.73 -> 40.15 | E11: 55 | F11: 77 | G11: 75 | H11: =G11-C11 -> 20 | I11: =H11/C11 -> 0.36363636
A12: CA0134700206 | B12: White Organic Cotton Unisex Zip Hoodie - S | C12: 55 | D12: =C12*0.73 -> 40.15 | E12: 55 | F12: 77 | G12: 75 | H12: =G12-C12 -> 20 | I12: =H12/C12 -> 0.36363636
A13: CA0077500400 | B13: Unisex Save Soil T-Shirt - L | C13: 15 | D13: =C13*0.73 -> 10.95 | E13: 15 | F13: 21 | G13: 20 | H13: =G13-C13 -> 5 | I13: =H13/C13 -> 0.33333333
A14: CA0077500300 | B14: Unisex Save Soil T-Shirt - M | C14: 15 | D14: =C14*0.73 -> 10.95 | E14: 15 | F14: 21 | G14: 20 | H14: =G14-C14 -> 5 | I14: =H14/C14 -> 0.33333333
A15: CA0077500200 | B15: Unisex Save Soil T-Shirt - S | C15: 15 | D15: =C15*0.73 -> 10.95 | E15: 15 | F15: 21 | G15: 20 | H15: =G15-C15 -> 5 | I15: =H15/C15 -> 0.33333333
A16: CA0061500606 | B16: White Organic Cotton Sweatpants for Men - XXL | C16: 45 | D16: =C16*0.73 -> 32.85 | E16: 45 | F16: 63 | G16: 62.99 | H16: =G16-C16 -> 17.99 | I16: =H16/C16 -> 0.39977778
A17: CA0059700306 | B17: White Cotton Kurta for Men-S | C17: 29 | D17: =C17*0.73 -> 21.17 | E17: 29 | F17: 40.6 | G17: 40 | H17: =G17-C17 -> 11 | I17: =H17/C17 -> 0.37931034
A18: TC0011617000 | B18: Brass Devi Panel in Turmeric (Consecrated) | C18: 1111 | D18: =C18*0.73 -> 811.03 | E18: 999 | F18: 1398.6 | G18: 1399 | H18: =G18-C18 -> 288 | I18: =H18/C18 -> 0.25922592 | J18: {=XLOOKUP(A18,'PRICE LIST'!E:E,'PRICE LIST'!H:H)}
A19: TC0011616900 | B19: Brass Devi Panel in Kumkum (Consecrated) | C19: 1111 | D19: =C19*0.73 -> 811.03 | E19: 999 | F19: 1398.6 | G19: 1399 | H19: =G19-C19 -> 288 | I19: =H19/C19 -> 0.25922592 | J19: {=XLOOKUP(A19,'PRICE LIST'!E:E,'PRICE LIST'!H:H)}
A20: TC0008317700 | B20: Adiyogi Statue, 6" (Consecrated) | C20: 1200 | D20: =C20*0.73 -> 876 | E20: 1200 | F20: 1680 | G20: 1699 | H20: =G20-C20 -> 499 | I20: =H20/C20 -> 0.41583333 | J20: {=XLOOKUP(A20,'PRICE LIST'!E:E,'PRICE LIST'!H:H)}
A21: TC0003500009 | B21: Linga Bhairavi Metallic Pendant (Consecrated) | C21: 199 | D21: =C21*0.73 -> 145.27 | E21: 199 | F21: 278.6 | G21: 279 | H21: =G21-C21 -> 80 | I21: =H21/C21 -> 0.40201005 | J21: {=XLOOKUP(A21,'PRICE LIST'!E:E,'PRICE LIST'!H:H)}
A22: CA0042300009 | B22: Linga Bhairavi Silver Chain, 21" | C22: 99 | D22: =C22*0.73 -> 72.27 | E22: 99 | F22: 138.6 | G22: 139 | H22: =G22-C22 -> 40 | I22: =H22/C22 -> 0.4040404 | J22: {=XLOOKUP(A22,'PRICE LIST'!E:E,'PRICE LIST'!H:H)}
A23: TC0000817100 | B23: Dhyanalinga Yantra (Consecrated) | C23: 491 | D23: =C23*0.73 -> 358.43 | E23: 491 | F23: 687.4 | G23: 689 | H23: =G23-C23 -> 198 | I23: =H23/C23 -> 0.40325866 | J23: {=XLOOKUP(A23,'PRICE LIST'!E:E,'PRICE LIST'!H:H)}
A24: CA0118300000 | B24: Adiyogi Rudraksha With Silver Chain (Consecrated) | C24: 112 | D24: =C24*0.73 -> 81.76 | E24: 112 | F24: 156.8 | G24: 155 | H24: =G24-C24 -> 43 | I24: =H24/C24 -> 0.38392857 | J24: {=XLOOKUP(A24,'PRICE LIST'!E:E,'PRICE LIST'!H:H)}
A25: RS0000400000 | B25: Gaurishankar Rudraksha Bead (Consecrated) | C25: 395 | D25: =C25*0.73 -> 288.35 | E25: 395 | F25: 553 | G25: 549 | H25: =G25-C25 -> 154 | I25: =H25/C25 -> 0.38987342 | J25: {=XLOOKUP(A25,'PRICE LIST'!E:E,'PRICE LIST'!H:H)}
A26: CA0036000009 | B26: Linga Bhairavi Silver Chain, 17" | C26: 91 | D26: =C26*0.73 -> 66.43 | E26: 91 | F26: 127.4 | G26: 127 | H26: =G26-C26 -> 36 | I26: =H26/C26 -> 0.3956044 | J26: {=XLOOKUP(A26,'PRICE LIST'!E:E,'PRICE LIST'!H:H)}
A27: TC0003400309 | B27: Linga Bhairavi Silver Pendant - M (CX506) | C27: 122 | D27: =C27*0.73 -> 89.06 | E27: 122 | F27: 170.8 | G27: 169 | H27: =G27-C27 -> 47 | I27: =H27/C27 -> 0.3852459 | J27: {=XLOOKUP(A27,'PRICE LIST'!E:E,'PRICE LIST'!H:H)}
A28: YS0005400200 | B28: Copper Pot for Water Storage, 1.32 gal | C28: 133 | D28: =C28*0.73 -> 97.09 | E28: 133 | F28: 186.2 | G28: 185 | H28: =G28-C28 -> 52 | I28: =H28/C28 -> 0.39097744 | J28: {=XLOOKUP(A28,'PRICE LIST'!E:E,'PRICE LIST'!H:H)}
A29: TC0003400209 | B29: Linga Bhairavi Silver Pendant - S (CX505) | C29: 111 | D29: =C29*0.73 -> 81.03 | E29: 111 | F29: 155.4 | G29: 155 | H29: =G29-C29 -> 44 | I29: =H29/C29 -> 0.3963964 | J29: {=XLOOKUP(A29,'PRICE LIST'!E:E,'PRICE LIST'!H:H)}
... A42: TC0000900000 | B42: Linga Jyoti Offering Lamp (Consecrated) | C42: 65 | D42: =C42*0.73 -> 47.45 | E42: 65 | F42: 91 | G42: 89.99 | H42: =G42-C42 -> 24.99 | I42: =H42/C42 -> 0.38446154 | J42: {=XLOOKUP(A42,'PRICE LIST'!E:E,'PRICE LIST'!H:H)}
A43: YS0018016906 | B43: Ochre 4mm Natural Rubber Jute Yoga Mat, 75" Long | C43: 59 | D43: =C43*0.73 -> 43.07 | E43: 59 | F43: 82.6 | G43: 82.99 | H43: =G43-C43 -> 23.99 | I43: =H43/C43 -> 0.40661017 | J43: {=XLOOKUP(A43,'PRICE LIST'!R:R,'PRICE LIST'!S:S)}
A44: YS0014400006 | B44: Ocean 4mm Natural Rubber Jute Yoga Mat, 75" Long | C44: 59 | D44: =C44*0.73 -> 43.07 | E44: 59 | F44: 82.6 | G44: 82.99 | H44: =G44-C44 -> 23.99 | I44: =H44/C44 -> 0.40661017 | J44: {=XLOOKUP(A44,'PRICE LIST'!R:R,'PRICE LIST'!S:S)}
A45: CA0152000005 | B45: Padam and Sarpa Textured Brass Pendant with Chain | C45: 49 | D45: =C45*0.73 -> 35.77 | E45: 49 | F45: 68.6 | G45: 68.99 | H45: =G45-C45 -> 19.99 | I45: =H45/C45 -> 0.40795918 | J45: {=XLOOKUP(A45,'PRICE LIST'!E:E,'PRICE LIST'!H:H)}
A46: CA0151900005 | B46: Padam and Lotus Textured Brass Pendant with Chain | C46: 49 | D46: =C46*0.73 -> 35.77 | E46: 49 | F46: 68.6 | G46: 68.99 | H46: =G46-C46 -> 19.99 | I46: =H46/C46 -> 0.40795918 | J46: {=XLOOKUP(A46,'PRICE LIST'!E:E,'PRICE LIST'!H:H)}
A47: RS0000607600 | B47: Rudraksha Panchamukhi Mala Bead size-5.5mm | C47: 140 | D47: =C47*0.73 -> 102.2 | E47: 140 | F47: 196 | G47: 195 | H47: =G47-C47 -> 55 | I47: =H47/C47 -> 0.39285714 | J47: {=XLOOKUP(A47,'PRICE LIST'!E:E,'PRICE LIST'!H:H)}
A48: ME0036300000 | B48: Mahabharat USB | C48: 50 | D48: =C48*0.73 -> 36.5 | E48: 50 | F48: 70 | G48: 69.99 | H48: =G48-C48 -> 19.99 | I48: =H48/C48 -> 0.3998 | J48: {=XLOOKUP(A48,'PRICE LIST'!E:E,'PRICE LIST'!H:H)}
A49: YS0006400000 | B49: Guru Pooja Set | C49: 50 | D49: =C49*0.73 -> 36.5 | E49: 50 | F49: 70 | G49: 69.99 | H49: =G49-C49 -> 19.99 | I49: =H49/C49 -> 0.3998 | J49: {=XLOOKUP(A49,'PRICE LIST'!E:E,'PRICE LIST'!H:H)}
A50: HO0000200000 | B50: Linga Bhairavi Lamp | C50: 45 | D50: =C50*0.73 -> 32.85 | E50: 45 | F50: 63 | G50: 62.99 | H50: =G50-C50 -> 17.99 | I50: =H50/C50 -> 0.39977778 | J50: {=XLOOKUP(A50,'PRICE LIST'!E:E,'PRICE LIST'!H:H)}
A51: YS0018017006 | B51: Sage 2mm Natural Rubber Jute Yoga Mat, 75" Long | C51: 49 | D51: =C51*0.73 -> 35.77 | E51: 49 | F51: 68.6 | G51: 68.99 | H51: =G51-C51 -> 19.99 | I51: =H51/C51 -> 0.40795918 | J51: {=XLOOKUP(A51,'PRICE LIST'!R:R,'PRICE LIST'!S:S)}
A52: YS0014500006 | B52: Earth 2mm Natural Rubber Jute Yoga Mat, 75" Long | C52: 49 | D52: =C52*0.73 -> 35.77 | E52: 49 | F52: 68.6 | G52: 68.99 | H52: =G52-C52 -> 19.99 | I52: =H52/C52 -> 0.40795918 | J52: {=XLOOKUP(A52,'PRICE LIST'!R:R,'PRICE LIST'!S:S)}
A53: YS0011600000 | B53: White Organic Cotton Rug Yoga Mat | C53: 49 | D53: =C53*0.73 -> 35.77 | E53: 49 | F53: 68.6 | G53: 68.99 | H53: =G53-C53 -> 19.99 | I53: =H53/C53 -> 0.40795918 | J53: {=XLOOKUP(A53,'PRICE LIST'!E:E,'PRICE LIST'!H:H)}
A54: YS0005703802 | B54: Hammered Copper Water Jug, 50.7 oz | C54: 45 | D54: =C54*0.73 -> 32.85 | E54: 45 | F54: 63 | G54: 62.99 | H54: =G54-C54 -> 17.99 | I54: =H54/C54 -> 0.39977778 | J54: {=XLOOKUP(A54,'PRICE LIST'!E:E,'PRICE LIST'!H:H)}
A55: TC0002800400 | B55: Bhairavi Raksha - L | C55: 50 | D55: =C55*0.73 -> 36.5 | E55: 45 | F55: 63 | G55: 62.99 | H55: =G55-C55 -> 12.99 | I55: =H55/C55 -> 0.2598 | J55: {=XLOOKUP(A55,'PRICE LIST'!E:E,'PRICE LIST'!H:H)}
A56: HO0021300000 | B56: Incense Cone Copper Stand | C56: 35 | D56: =C56*0.73 -> 25.55 | E56: 35 | F56: 49 | G56: 49 | H56: =G56-C56 -> 14 | I56: =H56/C56 -> 0.4 | J56: {=XLOOKUP(A56,'PRICE LIST'!E:E,'PRICE LIST'!H:H)}
A57: YS0011700000 | B57: Organic Dharba Grass Meditation Mat | C57: 55 | D57: =C57*0.73 -> 40.15 | E57: 55 | F57: 77 | G57: 75 | H57: =G57-C57 -> 20 | I57: =H57/C57 -> 0.36363636 | J57: {=XLOOKUP(A57,'PRICE LIST'!E:E,'PRICE LIST'!H:H)}
A58: TC0006400000 | B58: Linga Bhairavi Devi Trishul | C58: 39 | D58: =C58*0.73 -> 28.47 | E58: 39 | F58: 54.6 | G58: 54.99 | H58: =G58-C58 -> 15.99 | I58: =H58/C58 -> 0.41 | J58: {=XLOOKUP(A58,'PRICE LIST'!E:E,'PRICE LIST'!H:H)}
A59: TC0002800300 | B59: Bhairavi Raksha - M | C59: 50 | D59: =C59*0.73 -> 36.5 | E59: 45 | F59: 63 | G59: 62.99 | H59: =G59-C59 -> 12.99 | I59: =H59/C59 -> 0.2598 | J59: {=XLOOKUP(A59,'PRICE LIST'!E:E,'PRICE LIST'!H:H)}
A60: ME0043700006 | B60: Death Book - Hardcover | C60: 30 | D60: =C60*0.73 -> 21.9 | E60: 30 | F60: 42 | G60: 41.99 | H60: =G60-C60 -> 11.99 | I60: =H60/C60 -> 0.39966667 | J60: {=XLOOKUP(A60,'PRICE LIST'!R:R,'PRICE LIST'!S:S)}
A61: CA0203700400 | B61: Rust Relaxed Vneck for Women-L | C61: 34 | D61: =C61*0.73 -> 24.82 | E61: 34 | F61: 47.6 | G61: 47.99 | H61: =G61-C61 -> 13.99 | I61: =H61/C61 -> 0.41147059 | J61: {=XLOOKUP(A61,'PRICE LIST'!E:E,'PRICE LIST'!H:H)}
A62: CA0203700300 | B62: Rust Relaxed Vneck for Women-M | C62: 34 | D62: =C62*0.73 -> 24.82 | E62: 34 | F62: 47.6 | G62: 47.99 | H62: =G62-C62 -> 13.99 | I62: =H62/C62 -> 0.41147059 | J62: {=XLOOKUP(A62,'PRICE LIST'!E:E,'PRICE LIST'!H:H)}
A63: CA0203700200 | B63: Rust Relaxed Vneck for Women-S | C63: 34 | D63: =C63*0.73 -> 24.82 | E63: 34 | F63: 47.6 | G63: 47.99 | H63: =G63-C63 -> 13.99 | I63: =H63/C63 -> 0.41147059 | J63: {=XLOOKUP(A63,'PRICE LIST'!E:E,'PRICE LIST'!H:H)}
A64: CA0203700100 | B64: Rust Relaxed Vneck for Women-XS | C64: 34 | D64: =C64*0.73 -> 24.82 | E64: 34 | F64: 47.6 | G64: 47.99 | H64: =G64-C64 -> 13.99 | I64: =H64/C64 -> 0.41147059 | J64: {=XLOOKUP(A64,'PRICE LIST'!E:E,'PRICE LIST'!H:H)}
A65: RS0001000400 | B65: Spatik Mala (Quartz Stones) Style - 5 | C65: 50 | D65: =C65*0.73 -> 36.5 | E65: 50 | F65: 70 | G65: 69.99 | H65: =G65-C65 -> 19.99 | I65: =H65/C65 -> 0.3998 | J65: {=XLOOKUP(A65,'PRICE LIST'!E:E,'PRICE LIST'!H:H)}
A66: TC0007518000 | B66: Adiyogi Statue, 2.5'' Brass | C66: 55 | D66: =C66*0.73 -> 40.15 | E66: 35 | F66: 49 | G66: 49 | H66: =G66-C66 -> -6 | I66: =H66/C66 -> -0.10909091 | J66: {=XLOOKUP(A66,'PRICE LIST'!E:E,'PRICE LIST'!H:H)}
A67: CA0130900500 | B67: Adiyogi Hoodie - Navy Blue XL | C67: 49 | D67: =C67*0.73 -> 35.77 | E67: 49 | F67: 68.6 | G67: 68.99 | H67: =G67-C67 -> 19.99 | I67: =H67/C67 -> 0.40795918 | J67: {=XLOOKUP(A67,'PRICE LIST'!E:E,'PRICE LIST'!H:H)}
A68: CA0130900400 | B68: Adiyogi Hoodie - Navy Blue L | C68: 49 | D68: =C68*0.73 -> 35.77 | E68: 49 | F68: 68.6 | G68: 68.99 | H68: =G68-C68 -> 19.99 | I68: =H68/C68 -> 0.40795918 | J68: {=XLOOKUP(A68,'PRICE LIST'!E:E,'PRICE LIST'!H:H)}
A69: CA0130900300 | B69: Adiyogi Hoodie - Navy Blue M | C69: 49 | D69: =C69*0.73 -> 35.77 | E69: 49 | F69: 68.6 | G69: 68.99 | H69: =G69-C69 -> 19.99 | I69: =H69/C69 -> 0.40795918 | J69: {=XLOOKUP(A69,'PRICE LIST'!E:E,'PRICE LIST'!H:H)}
A70: CA0130900200 | B70: Adiyogi Hoodie - Navy Blue S | C70: 49 | D70: =C70*0.73 -> 35.77 | E70: 49 | F70: 68.6 | G70: 68.99 | H70: =G70-C70 -> 19.99 | I70: =H70/C70 -> 0.40795918 | J70: {=XLOOKUP(A70,'PRICE LIST'!E:E,'PRICE LIST'!H:H)}
A71: ME0001101506 | B71: Karma Book | C71: 30 | D71: =C71*0.73 -> 21.9 | E71: 26.99 | F71: 37.786 | G71: 37.99 | H71: =G71-C71 -> 7.99 | I71: =H71/C71 -> 0.26633333 | J71: {=XLOOKUP(A71,'PRICE LIST'!R:R,'PRICE LIST'!S:S)}
A72: ME0000801506 | B72: Inner Engineering A Yogi's Guide to Joy | C72: 25 | D72: =C72*0.73 -> 18.25 | E72: 28 | F72: 39.2 | G72: 38.99 | H72: =G72-C72 -> 13.99 | I72: =H72/C72 -> 0.5596 | J72: {=XLOOKUP(A72,'PRICE LIST'!R:R,'PRICE LIST'!S:S)}
A73: TC0002800200 | B73: Bhairavi Raksha - S | C73: 50 | D73: =C73*0.73 -> 36.5 | E73: 40 | F73: 56 | G73: 55.99 | H73: =G73-C73 -> 5.99 | I73: =H73/C73 -> 0.1198 | J73: {=XLOOKUP(A73,'PRICE LIST'!E:E,'PRICE LIST'!H:H)}
